{"systemConfig":{"currentGameId":"102018","pollingIntervalPlayersWeekStats":10,"pollingIntervalLeagueTeamMatchup":30,"overridePollingPlayersWeekStats":false},"games":{"102018":{"gameId":"102018","type":"core","code":"core","season":"2018","previousSeason":"2017","DEPRECIATED_DO_NOT_USE":"week, isSeasonStarted, isLiveGames","week":"17","isSeasonStarted":true,"isLiveGames":false,"siteMessages":{"leagueHome":"","teamMatchup":"","iOSHome":false,"androidHome":false,"feedbackModal":false},"state":{"week":"17","isRegistrationOpen":false,"isSeasonStarted":true,"isLiveGames":false,"isWeekGamesStarted":true,"isWeekGamesCompleted":true,"isLiveDraftLobbyOpen":false,"isPlayoffChallengePromoEnabled":false,"isOnTheFieldEnabled":true,"isMoreGamesPromoEnabled":false,"serverTime":"2019-02-15T13:47:49-08:00","nextGameStartTime":null,"isAppCacheEnabled":true,"routesToExcludeFromCache":["\/v2\/game\/joinlivedraftlobbyleague"],"statUpdateId":"1142299"},"players":{"100027":{"stats":{"week":{"2015":{"1":{"1":"1","45":"2","48":"1","52":"25","54":"28","60":"1","62":"361","66":"1","pts":"1.00"}}}}},"100021":{"stats":{"week":{"2015":{"1":{"1":"1","45":"3","46":"1","52":"9","54":"21","59":"1","62":"464","68":"1","pts":"5.00"}}}}},"2533057":{"stats":{"week":{"2015":{"1":{"1":"1","70":"6","71":"2","72":"1","84":"1","85":"1","86":"6","pts":"9.00"}}}}},"2495979":{"stats":{"week":{"2015":{"1":{"pts":null}}}}},"2506109":{"stats":{"week":{"2015":{"1":{"1":"1","2":"38","3":"26","4":"12","5":"351","6":"1","7":"1","8":"2","9":"1","32":"1","pts":"18.04"}}}}},"2508061":{"stats":{"week":{"2015":{"1":{"1":"1","8":"1","20":"9","21":"133","22":"1","25":"1","27":"3","pts":"19.30"}}}}},"2539311":{"stats":{"week":{"2015":{"1":{"1":"1","70":"3","71":"3","pts":"4.50"}}}}},"2552483":{"stats":{"week":{"2015":{"1":{"1":"1","70":"1","71":"1","72":"1","84":"1","85":"1","86":"8","pts":"3.50"}}}}},"776":{"stats":{"week":{"2015":{"1":{"pts":null}}}}},"2506369":{"stats":{"week":{"2015":{"1":{"pts":null}}}}},"2495920":{"stats":{"week":{"2015":{"1":{"pts":null}}}}},"71251":{"stats":{"week":{"2015":{"1":{"1":"1","70":"2","71":"3","pts":"3.50"}}}}},"2550613":{"stats":{"week":{"2015":{"1":{"1":"1","70":"3","71":"2","pts":"4.00"}}}}},"2506063":{"stats":{"week":{"2015":{"1":{"pts":null}}}}},"2543801":{"stats":{"week":{"2015":{"1":{"pts":null}}}}},"238498":{"stats":{"week":{"2015":{"1":{"1":"1","13":"1","14":"9","20":"11","21":"97","pts":"10.60"}}}}},"2507220":{"stats":{"week":{"2015":{"1":{"1":"1","70":"4","84":"1","pts":"4.00"}}}}},"2504211":{"stats":{"week":{"2015":{"1":{"1":"1","2":"32","3":"25","4":"7","5":"288","6":"4","8":"2","13":"3","14":"1","pts":"27.62"}}}}},"2495469":{"stats":{"week":{"2015":{"1":{"1":"1","13":"15","14":"69","20":"4","21":"51","31":"1","pts":"12.00"}}}}},"2504844":{"stats":{"week":{"2015":{"1":{"pts":null}}}}},"497240":{"stats":{"week":{"2015":{"1":{"1":"1","20":"5","21":"94","22":"3","75":"1","pts":"27.40"}}}}},"2649":{"stats":{"week":{"2015":{"1":{"1":"1","20":"2","21":"24","27":"1","pts":"2.40"}}}}},"2552289":{"stats":{"week":{"2015":{"1":{"1":"1","70":"2","72":"1","85":"1","pts":"4.00"}}}}},"2495561":{"stats":{"week":{"2015":{"1":{"pts":null}}}}},"2552271":{"stats":{"week":{"2015":{"1":{"1":"1","71":"1","pts":"0.50"}}}}},"2533538":{"stats":{"week":{"2015":{"1":{"1":"1","70":"1","71":"2","84":"1","85":"1","pts":"2.00"}}}}},"494287":{"stats":{"week":{"2015":{"1":{"1":"1","70":"3","71":"2","pts":"4.00"}}}}},"2495565":{"stats":{"week":{"2015":{"1":{"pts":null}}}}},"2540221":{"stats":{"week":{"2015":{"1":{"1":"1","70":"1","pts":"1.00"}}}}},"2506088":{"stats":{"week":{"2015":{"1":{"pts":null}}}}},"238227":{"stats":{"week":{"2015":{"1":{"pts":null}}}}},"2495762":{"stats":{"week":{"2015":{"1":{"pts":null}}}}},"2507590":{"stats":{"week":{"2015":{"1":{"1":"1","70":"1","71":"1","85":"1","pts":"1.50"}}}}},"2539256":{"stats":{"week":{"2015":{"1":{"pts":null}}}}},"2495497":{"stats":{"week":{"2015":{"1":{"pts":null}}}}},"2539937":{"stats":{"week":{"2015":{"1":{"pts":null}}}}},"2532797":{"stats":{"week":{"2015":{"1":{"1":"1","13":"5","14":"1","20":"1","21":"12","pts":"1.30"}}}}},"2543486":{"stats":{"week":{"2015":{"1":{"pts":null}}}}},"2543483":{"stats":{"week":{"2015":{"1":{"1":"1","71":"1","85":"1","pts":"0.50"}}}}},"2534822":{"stats":{"week":{"2015":{"1":{"1":"1","70":"1","71":"1","pts":"1.50"}}}}},"2506922":{"stats":{"week":{"2015":{"1":{"1":"1","33":"4","pts":"4.00"}}}}},"2495486":{"stats":{"week":{"2015":{"1":{"pts":null}}}}},"80636":{"stats":{"week":{"2015":{"1":{"pts":null}}}}},"80427":{"stats":{"week":{"2015":{"1":{"1":"1","20":"4","21":"58","pts":"5.80"}}}}},"2495228":{"stats":{"week":{"2015":{"1":{"1":"1","70":"2","71":"1","72":"1","84":"1","85":"1","86":"7","pts":"4.50"}}}}},"2540137":{"stats":{"week":{"2015":{"1":{"pts":null}}}}},"2508109":{"stats":{"week":{"2015":{"1":{"1":"1","70":"1","71":"3","pts":"2.50"}}}}},"2543596":{"stats":{"week":{"2015":{"1":{"pts":null}}}}},"2535132":{"stats":{"week":{"2015":{"1":{"1":"1","70":"1","pts":"1.00"}}}}},"2541243":{"stats":{"week":{"2015":{"1":{"1":"1","70":"2","71":"1","73":"1","81":"1","pts":"5.50"}}}}},"2539291":{"stats":{"week":{"2015":{"1":{"1":"1","20":"3","21":"55","32":"1","pts":"7.50"}}}}},"2495573":{"stats":{"week":{"2015":{"1":{"pts":null}}}}},"2539197":{"stats":{"week":{"2015":{"1":{"pts":null}}}}},"2550154":{"stats":{"week":{"2015":{"1":{"1":"1","70":"1","pts":"1.00"}}}}},"496865":{"stats":{"week":{"2015":{"1":{"pts":null}}}}},"100011":{"stats":{"week":{"2015":{"1":{"1":"1","45":"2","46":"1","52":"106","54":"23","59":"1","62":"402","67":"1","pts":"4.00"}}}}},"100005":{"stats":{"week":{"2015":{"1":{"1":"1","52":"74","54":"31","60":"1","62":"322","66":"1","pts":"-1.00"}}}}},"100016":{"stats":{"week":{"2015":{"1":{"1":"1","45":"5","46":"1","47":"1","48":"1","52":"111","54":"20","58":"1","62":"396","66":"1","pts":"10.00"}}}}},"100013":{"stats":{"week":{"2015":{"1":{"1":"1","45":"2","48":"1","52":"14","54":"27","59":"1","62":"330","66":"1","pts":"2.00"}}}}},"100007":{"stats":{"week":{"2015":{"1":{"1":"1","46":"1","52":"37","54":"31","60":"1","62":"333","66":"1","pts":"1.00"}}}}},"100024":{"stats":{"week":{"2015":{"1":{"1":"1","45":"3","46":"1","47":"4","48":"4","52":"26","54":"10","57":"1","62":"321","66":"1","pts":"17.00"}}}}},"100014":{"stats":{"week":{"2015":{"1":{"1":"1","48":"1","52":"59","54":"27","59":"1","62":"342","66":"1","pts":"0.00"}}}}},"100003":{"stats":{"week":{"2015":{"1":{"1":"1","45":"2","46":"2","47":"1","52":"6","54":"14","58":"1","62":"304","66":"1","pts":"9.00"}}}}},"100019":{"stats":{"week":{"2015":{"1":{"1":"1","45":"1","46":"2","52":"128","53":"1","54":"10","57":"1","62":"349","66":"1","pts":"15.00"}}}}},"100032":{"stats":{"week":{"2015":{"1":{"1":"1","45":"3","47":"1","48":"2","52":"59","54":"17","58":"1","62":"256","65":"1","pts":"6.00"}}}}},"100004":{"stats":{"week":{"2015":{"1":{"1":"1","45":"5","46":"2","47":"1","48":"1","50":"1","52":"46","54":"9","57":"1","62":"265","65":"1","pts":"21.00"}}}}},"100015":{"stats":{"week":{"2015":{"1":{"1":"1","45":"2","46":"1","51":"1","52":"49","54":"14","58":"1","62":"263","65":"1","pts":"5.00"}}}}},"100030":{"stats":{"week":{"2015":{"1":{"pts":null}}}}},"100017":{"stats":{"week":{"2015":{"1":{"pts":null}}}}},"2495488":{"stats":{"week":{"2015":{"1":{"1":"1","70":"9","72":"2","84":"6","85":"3","86":"10","88":"1","pts":"13.00"}}}}},"925":{"stats":{"week":{"2015":{"1":{"pts":null}}}}},"276":{"stats":{"week":{"2015":{"1":{"pts":null}}}}},"2495663":{"stats":{"week":{"2015":{"1":{"pts":null}}}}},"2552471":{"stats":{"week":{"2015":{"1":{"1":"1","13":"12","14":"51","20":"3","21":"16","70":"1","pts":"6.70"}}}}},"2506352":{"stats":{"week":{"2015":{"1":{"1":"1","70":"7","72":"1","73":"1","81":"1","82":"1","84":"2","85":"1","86":"2","pts":"12.00"}}}}},"2495613":{"stats":{"week":{"2015":{"1":{"pts":null}}}}},"2506404":{"stats":{"week":{"2015":{"1":{"1":"1","13":"8","14":"31","20":"2","pts":"3.10"}}}}},"496735":{"stats":{"week":{"2015":{"1":{"1":"1","70":"6","pts":"6.00"}}}}},"2506340":{"stats":{"week":{"2015":{"1":{"1":"1","2":"33","3":"22","4":"11","5":"243","6":"3","8":"2","11":"1","13":"9","14":"15","pts":"23.22"}}}}},"2550272":{"stats":{"week":{"2015":{"1":{"1":"1","20":"3","21":"25","pts":"2.50"}}}}},"2507999":{"stats":{"week":{"2015":{"1":{"1":"1","13":"20","14":"91","15":"2","20":"1","21":"9","pts":"22.00"}}}}},"496733":{"stats":{"week":{"2015":{"1":{"1":"1","70":"4","71":"2","pts":"5.00"}}}}},"2539309":{"stats":{"week":{"2015":{"1":{"pts":null}}}}},"2532975":{"stats":{"week":{"2015":{"1":{"pts":null}}}}},"497236":{"stats":{"week":{"2015":{"1":{"pts":null}}}}},"2495988":{"stats":{"week":{"2015":{"1":{"pts":null}}}}},"2532431":{"stats":{"week":{"2015":{"1":{"1":"1","70":"2","71":"4","81":"1","pts":"5.00"}}}}},"2543477":{"stats":{"week":{"2015":{"1":{"1":"1","2":"40","3":"22","4":"18","5":"183","6":"1","7":"2","8":"5","13":"4","14":"26","pts":"9.92"}}}}},"2552425":{"stats":{"week":{"2015":{"1":{"1":"1","20":"7","21":"28","22":"1","27":"9","pts":"8.80"}}}}},"2495872":{"stats":{"week":{"2015":{"1":{"1":"1","70":"4","81":"1","pts":"5.00"}}}}},"80429":{"stats":{"week":{"2015":{"1":{"pts":null}}}}},"2533050":{"stats":{"week":{"2015":{"1":{"pts":null}}}}},"2507166":{"stats":{"week":{"2015":{"1":{"1":"1","20":"2","21":"54","27":"46","pts":"5.40"}}}}},"2540143":{"stats":{"week":{"2015":{"1":{"pts":null}}}}},"2506871":{"stats":{"week":{"2015":{"1":{"pts":null}}}}},"2539280":{"stats":{"week":{"2015":{"1":{"1":"1","70":"2","71":"2","pts":"3.00"}}}}},"2552369":{"stats":{"week":{"2015":{"1":{"pts":null}}}}},"497284":{"stats":{"week":{"2015":{"1":{"pts":null}}}}},"2550654":{"stats":{"week":{"2015":{"1":{"1":"1","70":"1","71":"1","pts":"1.50"}}}}},"2552689":{"stats":{"week":{"2015":{"1":{"1":"1","70":"5","71":"1","73":"1","81":"2","82":"27","pts":"9.50"}}}}},"2533031":{"stats":{"week":{"2015":{"1":{"1":"1","2":"49","3":"26","4":"23","5":"243","6":"2","7":"2","8":"2","13":"4","14":"20","32":"1","70":"1","pts":"17.72"}}}}},"2532865":{"stats":{"week":{"2015":{"1":{"1":"1","20":"7","21":"88","pts":"8.80"}}}}},"234":{"stats":{"week":{"2015":{"1":{"pts":null}}}}},"79631":{"stats":{"week":{"2015":{"1":{"pts":null}}}}},"2505998":{"stats":{"week":{"2015":{"1":{"pts":null}}}}},"2532951":{"stats":{"week":{"2015":{"1":{"pts":null}}}}},"2495885":{"stats":{"week":{"2015":{"1":{"pts":null}}}}},"2508110":{"stats":{"week":{"2015":{"1":{"pts":null}}}}},"2533046":{"stats":{"week":{"2015":{"1":{"1":"1","20":"3","21":"17","22":"1","pts":"7.70"}}}}},"2533457":{"stats":{"week":{"2015":{"1":{"pts":null}}}}},"496820":{"stats":{"week":{"2015":{"1":{"pts":null}}}}},"496739":{"stats":{"week":{"2015":{"1":{"1":"1","70":"7","71":"5","81":"1","84":"1","pts":"10.50"}}}}},"2495455":{"stats":{"week":{"2015":{"1":{"1":"1","2":"31","3":"18","4":"13","5":"175","6":"1","7":"1","8":"2","13":"14","14":"35","pts":"12.50"}}}}},"2539234":{"stats":{"week":{"2015":{"1":{"pts":null}}}}},"2506931":{"stats":{"week":{"2015":{"1":{"1":"1","71":"2","85":"1","pts":"1.00"}}}}},"1037374":{"stats":{"week":{"2015":{"1":{"1":"1","70":"6","71":"1","81":"1","pts":"7.50"}}}}},"2543470":{"stats":{"week":{"2015":{"1":{"1":"1","70":"6","71":"1","pts":"6.50"}}}}},"2506581":{"stats":{"week":{"2015":{"1":{"1":"1","2":"24","3":"15","4":"9","5":"179","6":"2","7":"1","13":"2","14":"-1","31":"1","75":"1","83":"-23","pts":"13.06"}}}}},"2532923":{"stats":{"week":{"2015":{"1":{"pts":null}}}}},"2532848":{"stats":{"week":{"2015":{"1":{"1":"1","30":"1","31":"1","70":"2","71":"3","73":"1","81":"1","pts":"4.50"}}}}},"2506789":{"stats":{"week":{"2015":{"1":{"1":"1","70":"3","71":"1","pts":"3.50"}}}}},"79850":{"stats":{"week":{"2015":{"1":{"pts":null}}}}},"2532822":{"stats":{"week":{"2015":{"1":{"pts":null}}}}},"2495712":{"stats":{"week":{"2015":{"1":{"pts":null}}}}},"2495824":{"stats":{"week":{"2015":{"1":{"pts":null}}}}},"1990":{"stats":{"week":{"2015":{"1":{"pts":null}}}}},"2495893":{"stats":{"week":{"2015":{"1":{"pts":null}}}}},"2539290":{"stats":{"week":{"2015":{"1":{"1":"1","71":"2","81":"1","pts":"2.00"}}}}},"497224":{"stats":{"week":{"2015":{"1":{"1":"1","20":"1","21":"9","pts":"0.90"}}}}},"2533049":{"stats":{"week":{"2015":{"1":{"1":"1","70":"1","71":"1","81":"1","pts":"2.50"}}}}},"2495471":{"stats":{"week":{"2015":{"1":{"1":"1","13":"4","14":"16","27":"15","pts":"1.60"}}}}},"2532790":{"stats":{"week":{"2015":{"1":{"1":"1","20":"3","21":"89","22":"1","23":"1","24":"1","27":"10","70":"1","pts":"14.90"}}}}},"2543711":{"stats":{"week":{"2015":{"1":{"1":"1","70":"7","71":"2","84":"3","pts":"8.00"}}}}},"2550546":{"stats":{"week":{"2015":{"1":{"pts":null}}}}},"2532789":{"stats":{"week":{"2015":{"1":{"pts":null}}}}},"2552430":{"stats":{"week":{"2015":{"1":{"pts":null}}}}},"1062":{"stats":{"week":{"2015":{"1":{"pts":null}}}}},"80431":{"stats":{"week":{"2015":{"1":{"1":"1","70":"6","73":"1","81":"1","82":"42","85":"1","pts":"9.00"}}}}},"496796":{"stats":{"week":{"2015":{"1":{"1":"1","70":"3","71":"1","pts":"3.50"}}}}},"2507834":{"stats":{"week":{"2015":{"1":{"pts":null}}}}},"949":{"stats":{"week":{"2015":{"1":{"1":"1","13":"18","14":"56","20":"4","21":"25","pts":"8.10"}}}}},"2532877":{"stats":{"week":{"2015":{"1":{"pts":null}}}}},"2530747":{"stats":{"week":{"2015":{"1":{"pts":null}}}}},"79611":{"stats":{"week":{"2015":{"1":{"pts":null}}}}},"2495485":{"stats":{"week":{"2015":{"1":{"pts":null}}}}},"2543485":{"stats":{"week":{"2015":{"1":{"pts":null}}}}},"2534871":{"stats":{"week":{"2015":{"1":{"pts":null}}}}},"2533039":{"stats":{"week":{"2015":{"1":{"1":"1","20":"5","21":"78","pts":"7.80"}}}}},"2532861":{"stats":{"week":{"2015":{"1":{"1":"1","70":"3","81":"1","pts":"4.00"}}}}},"2543614":{"stats":{"week":{"2015":{"1":{"1":"1","20":"6","21":"46","22":"1","27":"5","pts":"10.60"}}}}},"2506004":{"stats":{"week":{"2015":{"1":{"pts":null}}}}},"4483":{"stats":{"week":{"2015":{"1":{"pts":null}}}}},"2540280":{"stats":{"week":{"2015":{"1":{"pts":null}}}}},"2505076":{"stats":{"week":{"2015":{"1":{"1":"1","2":"8","3":"5","4":"3","5":"49","13":"3","14":"23","30":"1","31":"1","pts":"2.26"}}}}},"497226":{"stats":{"week":{"2015":{"1":{"pts":null}}}}},"2507596":{"stats":{"week":{"2015":{"1":{"pts":null}}}}},"81294":{"stats":{"week":{"2015":{"1":{"1":"1","2":"34","3":"18","4":"16","5":"236","6":"1","7":"1","8":"4","30":"1","31":"1","pts":"9.44"}}}}},"2540165":{"stats":{"week":{"2015":{"1":{"1":"1","20":"9","21":"98","22":"2","32":"1","70":"1","pts":"23.80"}}}}},"2552488":{"stats":{"week":{"2015":{"1":{"1":"1","70":"5","71":"2","73":"1","81":"3","89":"1","pts":"11.00"}}}}},"2552486":{"stats":{"week":{"2015":{"1":{"1":"1","70":"1","71":"4","pts":"3.00"}}}}},"2550189":{"stats":{"week":{"2015":{"1":{"1":"1","13":"12","14":"20","20":"2","21":"13","pts":"3.30"}}}}},"80421":{"stats":{"week":{"2015":{"1":{"pts":null}}}}},"2495700":{"stats":{"week":{"2015":{"1":{"1":"1","20":"1","21":"11","70":"1","pts":"1.10"}}}}},"2540258":{"stats":{"week":{"2015":{"1":{"1":"1","20":"6","21":"106","22":"2","23":"1","25":"1","pts":"22.60"}}}}},"2495717":{"stats":{"week":{"2015":{"1":{"pts":null}}}}},"2505010":{"stats":{"week":{"2015":{"1":{"pts":null}}}}},"2505312":{"stats":{"week":{"2015":{"1":{"pts":null}}}}},"2495490":{"stats":{"week":{"2015":{"1":{"1":"1","70":"3","71":"2","72":"1","85":"1","pts":"6.00"}}}}},"2539336":{"stats":{"week":{"2015":{"1":{"pts":null}}}}},"2550636":{"stats":{"week":{"2015":{"1":{"1":"1","33":"3","36":"1","38":"1","44":"1","pts":"9.00"}}}}},"2506264":{"stats":{"week":{"2015":{"1":{"1":"1","33":"2","36":"1","38":"1","39":"1","70":"1","pts":"13.00"}}}}},"79607":{"stats":{"week":{"2015":{"1":{"1":"1","13":"17","14":"41","20":"3","21":"46","pts":"8.70"}}}}},"270":{"stats":{"week":{"2015":{"1":{"pts":null}}}}},"2495240":{"stats":{"week":{"2015":{"1":{"1":"1","2":"19","3":"14","4":"5","5":"195","6":"1","11":"1","12":"1","13":"9","14":"41","31":"1","75":"1","pts":"15.90"}}}}},"2505708":{"stats":{"week":{"2015":{"1":{"1":"1","70":"3","71":"1","pts":"3.50"}}}}},"2495621":{"stats":{"week":{"2015":{"1":{"pts":null}}}}},"2505622":{"stats":{"week":{"2015":{"1":{"pts":null}}}}},"2553446":{"stats":{"week":{"2015":{"1":{"1":"1","20":"2","21":"14","pts":"1.40"}}}}},"2552272":{"stats":{"week":{"2015":{"1":{"1":"1","70":"8","71":"1","84":"3","pts":"8.50"}}}}},"2506482":{"stats":{"week":{"2015":{"1":{"pts":null}}}}},"2550617":{"stats":{"week":{"2015":{"1":{"1":"1","20":"2","21":"20","pts":"2.00"}}}}},"71309":{"stats":{"week":{"2015":{"1":{"1":"1","33":"2","38":"2","43":"1","44":"1","pts":"8.00"}}}}},"2532842":{"stats":{"week":{"2015":{"1":{"pts":null}}}}},"2532871":{"stats":{"week":{"2015":{"1":{"pts":null}}}}},"80425":{"stats":{"week":{"2015":{"1":{"pts":null}}}}},"79897":{"stats":{"week":{"2015":{"1":{"pts":null}}}}},"2507488":{"stats":{"week":{"2015":{"1":{"pts":null}}}}},"2532940":{"stats":{"week":{"2015":{"1":{"pts":null}}}}},"2532956":{"stats":{"week":{"2015":{"1":{"1":"1","2":"34","3":"22","4":"12","5":"226","6":"1","8":"3","13":"3","14":"7","30":"1","31":"1","70":"1","pts":"11.74"}}}}},"2552429":{"stats":{"week":{"2015":{"1":{"1":"1","27":"106","pts":"0.00"}}}}},"2541544":{"stats":{"week":{"2015":{"1":{"pts":null}}}}},"2507617":{"stats":{"week":{"2015":{"1":{"pts":null}}}}},"2552386":{"stats":{"week":{"2015":{"1":{"1":"1","70":"2","81":"1","pts":"3.00"}}}}},"2543600":{"stats":{"week":{"2015":{"1":{"1":"1","13":"9","14":"42","20":"1","21":"7","pts":"4.90"}}}}},"729":{"stats":{"week":{"2015":{"1":{"pts":null}}}}},"2543469":{"stats":{"week":{"2015":{"1":{"pts":null}}}}},"2553733":{"stats":{"week":{"2015":{"1":{"pts":null}}}}},"2535876":{"stats":{"week":{"2015":{"1":{"1":"1","pts":"0.00"}}}}},"2506313":{"stats":{"week":{"2015":{"1":{"pts":null}}}}},"2506883":{"stats":{"week":{"2015":{"1":{"pts":null}}}}},"2532966":{"stats":{"week":{"2015":{"1":{"pts":null}}}}},"2543851":{"stats":{"week":{"2015":{"1":{"pts":null}}}}},"1060":{"stats":{"week":{"2015":{"1":{"pts":null}}}}},"2541316":{"stats":{"week":{"2015":{"1":{"1":"1","20":"1","21":"18","pts":"1.80"}}}}},"2495178":{"stats":{"week":{"2015":{"1":{"1":"1","70":"1","81":"1","pts":"2.00"}}}}},"2506363":{"stats":{"week":{"2015":{"1":{"1":"1","2":"23","3":"18","4":"5","5":"189","6":"3","13":"8","14":"35","pts":"23.06"}}}}},"2495341":{"stats":{"week":{"2015":{"1":{"pts":null}}}}},"2533008":{"stats":{"week":{"2015":{"1":{"1":"1","70":"2","71":"2","85":"1","pts":"3.00"}}}}},"2543691":{"stats":{"week":{"2015":{"1":{"pts":null}}}}},"2540168":{"stats":{"week":{"2015":{"1":{"pts":null}}}}},"2507374":{"stats":{"week":{"2015":{"1":{"pts":null}}}}},"2552385":{"stats":{"week":{"2015":{"1":{"1":"1","70":"5","84":"1","pts":"5.00"}}}}},"2495153":{"stats":{"week":{"2015":{"1":{"1":"1","70":"6","pts":"6.00"}}}}},"2543495":{"stats":{"week":{"2015":{"1":{"1":"1","20":"4","21":"59","pts":"5.90"}}}}},"2495461":{"stats":{"week":{"2015":{"1":{"pts":null}}}}},"2532868":{"stats":{"week":{"2015":{"1":{"pts":null}}}}},"2533034":{"stats":{"week":{"2015":{"1":{"1":"1","13":"13","14":"53","20":"1","21":"22","pts":"7.50"}}}}},"2532820":{"stats":{"week":{"2015":{"1":{"1":"1","2":"31","3":"21","4":"10","5":"196","6":"1","7":"2","8":"1","13":"2","14":"-1","31":"1","83":"-3","pts":"7.74"}}}}},"1581":{"stats":{"week":{"2015":{"1":{"1":"1","pts":"0.00"}}}}},"2543509":{"stats":{"week":{"2015":{"1":{"1":"1","20":"1","21":"27","pts":"2.70"}}}}},"2495229":{"stats":{"week":{"2015":{"1":{"pts":null}}}}},"2505625":{"stats":{"week":{"2015":{"1":{"pts":null}}}}},"2346":{"stats":{"week":{"2015":{"1":{"1":"1","20":"6","21":"74","pts":"7.40"}}}}},"2539932":{"stats":{"week":{"2015":{"1":{"1":"1","70":"6","71":"3","81":"1","pts":"8.50"}}}}},"2540190":{"stats":{"week":{"2015":{"1":{"pts":null}}}}},"2552379":{"stats":{"week":{"2015":{"1":{"pts":null}}}}},"496833":{"stats":{"week":{"2015":{"1":{"pts":null}}}}},"2508112":{"stats":{"week":{"2015":{"1":{"pts":null}}}}},"2539296":{"stats":{"week":{"2015":{"1":{"1":"1","70":"2","84":"1","pts":"2.00"}}}}},"2552635":{"stats":{"week":{"2015":{"1":{"pts":null}}}}},"2506526":{"stats":{"week":{"2015":{"1":{"pts":null}}}}},"71265":{"stats":{"week":{"2015":{"1":{"pts":null}}}}},"2540160":{"stats":{"week":{"2015":{"1":{"1":"1","20":"7","21":"63","22":"1","pts":"12.30"}}}}},"2495252":{"stats":{"week":{"2015":{"1":{"pts":null}}}}},"2495276":{"stats":{"week":{"2015":{"1":{"pts":null}}}}},"2495503":{"stats":{"week":{"2015":{"1":{"pts":null}}}}},"2508080":{"stats":{"week":{"2015":{"1":{"pts":null}}}}},"2540178":{"stats":{"week":{"2015":{"1":{"pts":null}}}}},"2552458":{"stats":{"week":{"2015":{"1":{"1":"1","20":"1","21":"9","pts":"0.90"}}}}},"2543724":{"stats":{"week":{"2015":{"1":{"1":"1","70":"3","pts":"3.00"}}}}},"2550160":{"stats":{"week":{"2015":{"1":{"1":"1","70":"4","71":"2","pts":"5.00"}}}}},"496822":{"stats":{"week":{"2015":{"1":{"1":"1","70":"3","71":"1","84":"1","pts":"3.50"}}}}},"2495507":{"stats":{"week":{"2015":{"1":{"pts":null}}}}},"2543868":{"stats":{"week":{"2015":{"1":{"pts":null}}}}},"2540141":{"stats":{"week":{"2015":{"1":{"pts":null}}}}},"2540011":{"stats":{"week":{"2015":{"1":{"1":"1","13":"3","14":"11","27":"36","pts":"1.10"}}}}},"238466":{"stats":{"week":{"2015":{"1":{"pts":null}}}}},"2532926":{"stats":{"week":{"2015":{"1":{"pts":null}}}}},"2540278":{"stats":{"week":{"2015":{"1":{"pts":null}}}}},"2514414":{"stats":{"week":{"2015":{"1":{"pts":null}}}}},"2539306":{"stats":{"week":{"2015":{"1":{"1":"1","70":"1","85":"1","pts":"1.00"}}}}},"2543855":{"stats":{"week":{"2015":{"1":{"1":"1","70":"5","71":"1","81":"2","pts":"7.50"}}}}},"2532920":{"stats":{"week":{"2015":{"1":{"1":"1","70":"4","71":"1","73":"1","74":"1","75":"1","76":"1","81":"2","82":"30","pts":"18.50"}}}}},"494289":{"stats":{"week":{"2015":{"1":{"1":"1","70":"1","71":"2","pts":"2.00"}}}}},"2532907":{"stats":{"week":{"2015":{"1":{"pts":null}}}}},"2550313":{"stats":{"week":{"2015":{"1":{"1":"1","13":"1","14":"11","20":"3","21":"27","pts":"3.80"}}}}},"2495150":{"stats":{"week":{"2015":{"1":{"1":"1","33":"1","38":"1","43":"1","pts":"4.00"}}}}},"2533545":{"stats":{"week":{"2015":{"1":{"pts":null}}}}},"2533056":{"stats":{"week":{"2015":{"1":{"1":"1","70":"7","72":"1","84":"1","85":"1","86":"5","pts":"9.00"}}}}},"2550572":{"stats":{"week":{"2015":{"1":{"1":"1","70":"4","71":"3","pts":"5.50"}}}}},"494261":{"stats":{"week":{"2015":{"1":{"1":"1","70":"3","pts":"3.00"}}}}},"2552420":{"stats":{"week":{"2015":{"1":{"pts":null}}}}},"2495139":{"stats":{"week":{"2015":{"1":{"1":"1","20":"4","21":"43","31":"1","75":"1","pts":"4.30"}}}}},"2506889":{"stats":{"week":{"2015":{"1":{"pts":null}}}}},"2505940":{"stats":{"week":{"2015":{"1":{"pts":null}}}}},"2534797":{"stats":{"week":{"2015":{"1":{"pts":null}}}}},"2506353":{"stats":{"week":{"2015":{"1":{"1":"1","70":"6","71":"2","72":"1","81":"1","84":"2","85":"1","86":"9","pts":"10.00"}}}}},"2507568":{"stats":{"week":{"2015":{"1":{"pts":null}}}}},"2495851":{"stats":{"week":{"2015":{"1":{"pts":null}}}}},"2495267":{"stats":{"week":{"2015":{"1":{"pts":null}}}}},"230":{"stats":{"week":{"2015":{"1":{"pts":null}}}}},"2532839":{"stats":{"week":{"2015":{"1":{"pts":null}}}}},"2495611":{"stats":{"week":{"2015":{"1":{"pts":null}}}}},"2543488":{"stats":{"week":{"2015":{"1":{"1":"1","13":"1","14":"14","20":"8","21":"53","27":"74","28":"1","pts":"6.70"}}}}},"2534770":{"stats":{"week":{"2015":{"1":{"pts":null}}}}},"2530794":{"stats":{"week":{"2015":{"1":{"pts":null}}}}},"2506893":{"stats":{"week":{"2015":{"1":{"pts":null}}}}},"2552424":{"stats":{"week":{"2015":{"1":{"1":"1","20":"2","21":"45","27":"1","30":"1","31":"2","75":"1","pts":"2.50"}}}}},"79605":{"stats":{"week":{"2015":{"1":{"pts":null}}}}},"2553725":{"stats":{"week":{"2015":{"1":{"pts":null}}}}},"2506347":{"stats":{"week":{"2015":{"1":{"pts":null}}}}},"2540225":{"stats":{"week":{"2015":{"1":{"1":"1","13":"2","14":"2","pts":"0.20"}}}}},"2507183":{"stats":{"week":{"2015":{"1":{"pts":null}}}}},"2506108":{"stats":{"week":{"2015":{"1":{"pts":null}}}}},"2533444":{"stats":{"week":{"2015":{"1":{"1":"1","34":"1","37":"1","38":"1","pts":"6.00"}}}}},"2507232":{"stats":{"week":{"2015":{"1":{"1":"1","33":"4","37":"1","pts":"7.00"}}}}},"2543503":{"stats":{"week":{"2015":{"1":{"1":"1","71":"3","pts":"1.50"}}}}},"2553112":{"stats":{"week":{"2015":{"1":{"1":"1","34":"1","36":"1","43":"1","pts":"3.00"}}}}},"2552261":{"stats":{"week":{"2015":{"1":{"1":"1","70":"2","pts":"2.00"}}}}},"2540197":{"stats":{"week":{"2015":{"1":{"1":"1","70":"4","71":"2","72":"1","81":"1","85":"1","pts":"8.00"}}}}},"2535718":{"stats":{"week":{"2015":{"1":{"1":"1","70":"4","71":"1","84":"2","pts":"4.50"}}}}},"2534832":{"stats":{"week":{"2015":{"1":{"pts":null}}}}},"2533062":{"stats":{"week":{"2015":{"1":{"1":"1","70":"6","81":"4","89":"1","pts":"10.00"}}}}},"2543462":{"stats":{"week":{"2015":{"1":{"pts":null}}}}},"2552461":{"stats":{"week":{"2015":{"1":{"1":"1","13":"7","14":"22","pts":"2.20"}}}}},"2543492":{"stats":{"week":{"2015":{"1":{"pts":null}}}}},"2541315":{"stats":{"week":{"2015":{"1":{"1":"1","70":"6","71":"1","pts":"6.50"}}}}},"2495479":{"stats":{"week":{"2015":{"1":{"pts":null}}}}},"2506314":{"stats":{"week":{"2015":{"1":{"pts":null}}}}},"1974":{"stats":{"week":{"2015":{"1":{"pts":null}}}}},"2550551":{"stats":{"week":{"2015":{"1":{"pts":null}}}}},"2550575":{"stats":{"week":{"2015":{"1":{"1":"1","70":"1","71":"2","pts":"2.00"}}}}},"496835":{"stats":{"week":{"2015":{"1":{"pts":null}}}}},"2539263":{"stats":{"week":{"2015":{"1":{"pts":null}}}}},"2540169":{"stats":{"week":{"2015":{"1":{"1":"1","20":"2","21":"27","pts":"2.70"}}}}},"280":{"stats":{"week":{"2015":{"1":{"pts":null}}}}},"2543638":{"stats":{"week":{"2015":{"1":{"1":"1","13":"1","14":"9","20":"1","21":"2","27":"81","31":"1","75":"1","pts":"1.10"}}}}},"2506861":{"stats":{"week":{"2015":{"1":{"1":"1","70":"1","71":"1","73":"1","81":"1","82":"2","pts":"4.50"}}}}},"2552389":{"stats":{"week":{"2015":{"1":{"1":"1","70":"1","81":"2","pts":"3.00"}}}}},"2540200":{"stats":{"week":{"2015":{"1":{"1":"1","pts":"0.00"}}}}},"1344":{"stats":{"week":{"2015":{"1":{"pts":null}}}}},"2541162":{"stats":{"week":{"2015":{"1":{"1":"1","70":"1","pts":"1.00"}}}}},"2539240":{"stats":{"week":{"2015":{"1":{"1":"1","70":"4","pts":"4.00"}}}}},"2507401":{"stats":{"week":{"2015":{"1":{"pts":null}}}}},"1330":{"stats":{"week":{"2015":{"1":{"pts":null}}}}},"2540157":{"stats":{"week":{"2015":{"1":{"pts":null}}}}},"2543456":{"stats":{"week":{"2015":{"1":{"1":"1","70":"3","71":"1","74":"1","84":"1","pts":"5.50"}}}}},"80656":{"stats":{"week":{"2015":{"1":{"pts":null}}}}},"2530515":{"stats":{"week":{"2015":{"1":{"1":"1","70":"1","pts":"0.00"}}}}},"2532939":{"stats":{"week":{"2015":{"1":{"pts":null}}}}},"2550512":{"stats":{"week":{"2015":{"1":{"1":"1","13":"1","20":"1","21":"3","pts":"0.30"}}}}},"2539260":{"stats":{"week":{"2015":{"1":{"pts":null}}}}},"2550442":{"stats":{"week":{"2015":{"1":{"pts":null}}}}},"2552307":{"stats":{"week":{"2015":{"1":{"pts":null}}}}},"2550353":{"stats":{"week":{"2015":{"1":{"1":"1","20":"5","21":"60","30":"1","31":"1","pts":"4.00"}}}}},"2533037":{"stats":{"week":{"2015":{"1":{"pts":null}}}}},"2543494":{"stats":{"week":{"2015":{"1":{"1":"1","70":"2","pts":"2.00"}}}}},"2505551":{"stats":{"week":{"2015":{"1":{"pts":null}}}}},"2532800":{"stats":{"week":{"2015":{"1":{"1":"1","70":"7","71":"1","72":"1","84":"1","85":"2","86":"3","pts":"9.50"}}}}},"2531049":{"stats":{"week":{"2015":{"1":{"pts":null}}}}},"2507837":{"stats":{"week":{"2015":{"1":{"1":"1","70":"1","pts":"1.00"}}}}},"2507225":{"stats":{"week":{"2015":{"1":{"pts":null}}}}},"2543874":{"stats":{"week":{"2015":{"1":{"1":"1","70":"1","pts":"1.00"}}}}},"2495491":{"stats":{"week":{"2015":{"1":{"pts":null}}}}},"2552415":{"stats":{"week":{"2015":{"1":{"1":"1","13":"1","14":"2","20":"1","27":"23","pts":"0.20"}}}}},"2507673":{"stats":{"week":{"2015":{"1":{"pts":null}}}}},"2543501":{"stats":{"week":{"2015":{"1":{"1":"1","70":"1","71":"1","pts":"1.50"}}}}},"2532875":{"stats":{"week":{"2015":{"1":{"pts":null}}}}},"497172":{"stats":{"week":{"2015":{"1":{"pts":null}}}}},"2550355":{"stats":{"week":{"2015":{"1":{"pts":null}}}}},"2543555":{"stats":{"week":{"2015":{"1":{"pts":null}}}}},"2532887":{"stats":{"week":{"2015":{"1":{"pts":null}}}}},"2495189":{"stats":{"week":{"2015":{"1":{"1":"1","27":"13","pts":"0.00"}}}}},"2543547":{"stats":{"week":{"2015":{"1":{"pts":null}}}}},"2495493":{"stats":{"week":{"2015":{"1":{"1":"1","70":"3","72":"1","74":"1","85":"1","86":"9","pts":"7.00"}}}}},"2495116":{"stats":{"week":{"2015":{"1":{"1":"1","70":"3","71":"1","72":"2","75":"1","84":"2","85":"2","86":"10","88":"1","pts":"9.50"}}}}},"2543681":{"stats":{"week":{"2015":{"1":{"1":"1","70":"1","71":"1","pts":"1.50"}}}}},"2495448":{"stats":{"week":{"2015":{"1":{"1":"1","20":"5","21":"38","22":"1","pts":"9.80"}}}}},"2507486":{"stats":{"week":{"2015":{"1":{"pts":null}}}}},"2549915":{"stats":{"week":{"2015":{"1":{"pts":null}}}}},"2552578":{"stats":{"week":{"2015":{"1":{"pts":null}}}}},"2507253":{"stats":{"week":{"2015":{"1":{"pts":null}}}}},"2495328":{"stats":{"week":{"2015":{"1":{"1":"1","13":"12","14":"62","20":"2","21":"16","pts":"7.80"}}}}},"2540140":{"stats":{"week":{"2015":{"1":{"1":"1","70":"1","71":"2","81":"1","84":"1","pts":"3.00"}}}}},"2543814":{"stats":{"week":{"2015":{"1":{"1":"1","70":"2","71":"4","81":"1","pts":"5.00"}}}}},"2552489":{"stats":{"week":{"2015":{"1":{"1":"1","70":"2","84":"1","pts":"2.00"}}}}},"2530711":{"stats":{"week":{"2015":{"1":{"pts":null}}}}},"71217":{"stats":{"week":{"2015":{"1":{"pts":null}}}}},"2506112":{"stats":{"week":{"2015":{"1":{"pts":null}}}}},"2508097":{"stats":{"week":{"2015":{"1":{"pts":null}}}}},"2553462":{"stats":{"week":{"2015":{"1":{"pts":null}}}}},"2539223":{"stats":{"week":{"2015":{"1":{"1":"1","70":"3","71":"1","pts":"3.50"}}}}},"81831":{"stats":{"week":{"2015":{"1":{"pts":null}}}}},"2540037":{"stats":{"week":{"2015":{"1":{"1":"1","13":"2","14":"2","20":"2","21":"3","pts":"0.50"}}}}},"2539946":{"stats":{"week":{"2015":{"1":{"pts":null}}}}},"496760":{"stats":{"week":{"2015":{"1":{"1":"1","70":"2","pts":"2.00"}}}}},"2507428":{"stats":{"week":{"2015":{"1":{"pts":null}}}}},"2503471":{"stats":{"week":{"2015":{"1":{"1":"1","44":"1","pts":"0.00"}}}}},"2495343":{"stats":{"week":{"2015":{"1":{"1":"1","70":"1","pts":"1.00"}}}}},"1037885":{"stats":{"week":{"2015":{"1":{"pts":null}}}}},"2552263":{"stats":{"week":{"2015":{"1":{"1":"1","70":"1","pts":"1.00"}}}}},"2533435":{"stats":{"week":{"2015":{"1":{"1":"1","70":"1","71":"1","pts":"1.50"}}}}},"496723":{"stats":{"week":{"2015":{"1":{"1":"1","70":"2","81":"1","pts":"3.00"}}}}},"2543830":{"stats":{"week":{"2015":{"1":{"pts":null}}}}},"2532826":{"stats":{"week":{"2015":{"1":{"1":"1","71":"1","pts":"0.50"}}}}},"2552380":{"stats":{"week":{"2015":{"1":{"pts":null}}}}},"497320":{"stats":{"week":{"2015":{"1":{"1":"1","20":"3","21":"36","pts":"3.60"}}}}},"496861":{"stats":{"week":{"2015":{"1":{"1":"1","70":"1","71":"1","pts":"1.50"}}}}},"2552492":{"stats":{"week":{"2015":{"1":{"1":"1","70":"1","72":"1","84":"1","85":"1","86":"8","pts":"3.00"}}}}},"2552593":{"stats":{"week":{"2015":{"1":{"pts":null}}}}},"2495297":{"stats":{"week":{"2015":{"1":{"pts":null}}}}},"2533036":{"stats":{"week":{"2015":{"1":{"pts":null}}}}},"2495867":{"stats":{"week":{"2015":{"1":{"pts":null}}}}},"2507484":{"stats":{"week":{"2015":{"1":{"pts":null}}}}},"2535687":{"stats":{"week":{"2015":{"1":{"1":"1","70":"1","71":"1","pts":"1.50"}}}}},"2495190":{"stats":{"week":{"2015":{"1":{"1":"1","70":"1","71":"1","72":"0.5","81":"1","85":"1","86":"2.5","pts":"3.50"}}}}},"2534241":{"stats":{"week":{"2015":{"1":{"1":"1","20":"2","21":"8","pts":"0.80"}}}}},"2543759":{"stats":{"week":{"2015":{"1":{"1":"1","20":"1","21":"15","pts":"1.50"}}}}},"2507557":{"stats":{"week":{"2015":{"1":{"1":"1","71":"3","72":"0.5","85":"2","86":"2.5","pts":"2.50"}}}}},"2540202":{"stats":{"week":{"2015":{"1":{"1":"1","20":"1","21":"12","pts":"1.20"}}}}},"2540170":{"stats":{"week":{"2015":{"1":{"1":"1","70":"2","81":"1","pts":"3.00"}}}}},"2532903":{"stats":{"week":{"2015":{"1":{"1":"1","20":"4","21":"34","22":"1","pts":"9.40"}}}}},"2553648":{"stats":{"week":{"2015":{"1":{"pts":null}}}}},"2539982":{"stats":{"week":{"2015":{"1":{"1":"1","70":"6","84":"1","pts":"6.00"}}}}},"2540177":{"stats":{"week":{"2015":{"1":{"1":"1","20":"2","21":"59","pts":"5.90"}}}}},"2552477":{"stats":{"week":{"2015":{"1":{"1":"1","pts":"0.00"}}}}},"2543563":{"stats":{"week":{"2015":{"1":{"pts":null}}}}},"2539292":{"stats":{"week":{"2015":{"1":{"pts":null}}}}},"4471":{"stats":{"week":{"2015":{"1":{"pts":null}}}}},"1037852":{"stats":{"week":{"2015":{"1":{"pts":null}}}}},"2530610":{"stats":{"week":{"2015":{"1":{"pts":null}}}}},"2495265":{"stats":{"week":{"2015":{"1":{"pts":null}}}}},"2550279":{"stats":{"week":{"2015":{"1":{"pts":null}}}}},"2495170":{"stats":{"week":{"2015":{"1":{"1":"1","70":"2","81":"1","pts":"3.00"}}}}},"2552276":{"stats":{"week":{"2015":{"1":{"1":"1","70":"2","72":"1","74":"2","75":"1","85":"1","86":"38","pts":"10.00"}}}}},"2552316":{"stats":{"week":{"2015":{"1":{"1":"1","70":"1","pts":"1.00"}}}}},"2508135":{"stats":{"week":{"2015":{"1":{"pts":null}}}}},"2543792":{"stats":{"week":{"2015":{"1":{"pts":null}}}}},"2507737":{"stats":{"week":{"2015":{"1":{"pts":null}}}}},"496949":{"stats":{"week":{"2015":{"1":{"pts":null}}}}},"81841":{"stats":{"week":{"2015":{"1":{"pts":null}}}}},"2530855":{"stats":{"week":{"2015":{"1":{"pts":null}}}}},"2552490":{"stats":{"week":{"2015":{"1":{"1":"1","70":"1","pts":"1.00"}}}}},"2543720":{"stats":{"week":{"2015":{"1":{"1":"1","71":"3","pts":"1.50"}}}}},"2533333":{"stats":{"week":{"2015":{"1":{"pts":null}}}}},"2532818":{"stats":{"week":{"2015":{"1":{"pts":null}}}}},"2553318":{"stats":{"week":{"2015":{"1":{"1":"1","pts":"0.00"}}}}},"2507902":{"stats":{"week":{"2015":{"1":{"pts":null}}}}},"2495306":{"stats":{"week":{"2015":{"1":{"pts":null}}}}},"2543721":{"stats":{"week":{"2015":{"1":{"pts":null}}}}},"2550145":{"stats":{"week":{"2015":{"1":{"pts":null}}}}},"2543727":{"stats":{"week":{"2015":{"1":{"1":"1","70":"1","pts":"1.00"}}}}},"2552325":{"stats":{"week":{"2015":{"1":{"1":"1","70":"1","71":"1","pts":"1.50"}}}}},"2508063":{"stats":{"week":{"2015":{"1":{"pts":null}}}}},"2501078":{"stats":{"week":{"2015":{"1":{"pts":null}}}}},"2543692":{"stats":{"week":{"2015":{"1":{"1":"1","70":"4","81":"1","84":"1","pts":"5.00"}}}}},"2495201":{"stats":{"week":{"2015":{"1":{"1":"1","70":"5","71":"1","pts":"5.50"}}}}},"2552733":{"stats":{"week":{"2015":{"1":{"1":"1","71":"1","pts":"0.50"}}}}},"2495142":{"stats":{"week":{"2015":{"1":{"pts":null}}}}},"2530474":{"stats":{"week":{"2015":{"1":{"1":"1","70":"3","72":"2","84":"2","85":"3","86":"6","88":"1","pts":"7.00"}}}}},"2550268":{"stats":{"week":{"2015":{"1":{"1":"1","70":"1","pts":"0.00"}}}}},"2507187":{"stats":{"week":{"2015":{"1":{"pts":null}}}}},"497206":{"stats":{"week":{"2015":{"1":{"pts":null}}}}},"2541199":{"stats":{"week":{"2015":{"1":{"pts":null}}}}},"2540286":{"stats":{"week":{"2015":{"1":{"pts":null}}}}},"2532838":{"stats":{"week":{"2015":{"1":{"pts":null}}}}},"2533332":{"stats":{"week":{"2015":{"1":{"pts":null}}}}},"2532989":{"stats":{"week":{"2015":{"1":{"1":"1","71":"1","pts":"0.50"}}}}},"2552297":{"stats":{"week":{"2015":{"1":{"1":"1","74":"1","pts":"2.00"}}}}},"2543457":{"stats":{"week":{"2015":{"1":{"1":"1","pts":"0.00"}}}}},"79901":{"stats":{"week":{"2015":{"1":{"1":"1","81":"1","pts":"1.00"}}}}},"2553442":{"stats":{"week":{"2015":{"1":{"1":"1","70":"2","pts":"2.00"}}}}},"2543676":{"stats":{"week":{"2015":{"1":{"pts":null}}}}},"2495340":{"stats":{"week":{"2015":{"1":{"1":"1","20":"1","pts":"0.00"}}}}},"1681":{"stats":{"week":{"2015":{"1":{"pts":null}}}}},"2495677":{"stats":{"week":{"2015":{"1":{"pts":null}}}}},"2495443":{"stats":{"week":{"2015":{"1":{"pts":null}}}}},"497242":{"stats":{"week":{"2015":{"1":{"pts":null}}}}},"2533451":{"stats":{"week":{"2015":{"1":{"pts":null}}}}},"100022":{"stats":{"week":{"2015":{"1":{"1":"1","47":"1","48":"1","52":"12","54":"31","60":"1","62":"427","67":"1","pts":"1.00"}}}}},"100026":{"stats":{"week":{"2015":{"1":{"1":"1","45":"2","46":"1","52":"58","54":"19","58":"1","62":"408","67":"1","pts":"5.00"}}}}},"100010":{"stats":{"week":{"2015":{"1":{"1":"1","45":"2","46":"2","47":"1","48":"1","50":"1","52":"139","54":"33","60":"1","62":"483","68":"1","pts":"13.00"}}}}},"100028":{"stats":{"week":{"2015":{"1":{"1":"1","45":"1","46":"2","48":"1","52":"24","54":"22","59":"1","62":"302","66":"1","pts":"5.00"}}}}},"2495187":{"stats":{"week":{"2015":{"1":{"pts":null}}}}},"2552314":{"stats":{"week":{"2015":{"1":{"1":"1","70":"1","pts":"1.00"}}}}},"2495483":{"stats":{"week":{"2015":{"1":{"1":"1","70":"2","pts":"2.00"}}}}},"2552296":{"stats":{"week":{"2015":{"1":{"1":"1","70":"2","71":"1","72":"1","73":"1","81":"1","84":"2","85":"1","86":"13","pts":"7.50"}}}}},"497145":{"stats":{"week":{"2015":{"1":{"pts":null}}}}},"2505245":{"stats":{"week":{"2015":{"1":{"pts":null}}}}},"2543847":{"stats":{"week":{"2015":{"1":{"1":"1","20":"4","21":"46","22":"1","pts":"10.60"}}}}},"2507817":{"stats":{"week":{"2015":{"1":{"1":"1","70":"2","pts":"2.00"}}}}},"754":{"stats":{"week":{"2015":{"1":{"pts":null}}}}},"2506481":{"stats":{"week":{"2015":{"1":{"pts":null}}}}},"497326":{"stats":{"week":{"2015":{"1":{"1":"1","20":"4","21":"24","27":"34","pts":"2.40"}}}}},"79860":{"stats":{"week":{"2015":{"1":{"1":"1","2":"30","3":"19","4":"11","5":"246","6":"2","7":"2","8":"1","13":"1","14":"-1","pts":"13.74"}}}}},"2532841":{"stats":{"week":{"2015":{"1":{"pts":null}}}}},"2539320":{"stats":{"week":{"2015":{"1":{"pts":null}}}}},"2541958":{"stats":{"week":{"2015":{"1":{"1":"1","70":"4","pts":"4.00"}}}}},"2528181":{"stats":{"week":{"2015":{"1":{"pts":null}}}}},"2552615":{"stats":{"week":{"2015":{"1":{"pts":null}}}}},"496903":{"stats":{"week":{"2015":{"1":{"pts":null}}}}},"2552374":{"stats":{"week":{"2015":{"1":{"1":"1","13":"7","14":"50","15":"1","20":"4","21":"44","27":"105","31":"1","75":"1","pts":"15.40"}}}}},"2495647":{"stats":{"week":{"2015":{"1":{"pts":null}}}}},"2539217":{"stats":{"week":{"2015":{"1":{"pts":null}}}}},"2506287":{"stats":{"week":{"2015":{"1":{"pts":null}}}}},"2539277":{"stats":{"week":{"2015":{"1":{"1":"1","70":"3","71":"2","84":"1","pts":"4.00"}}}}},"2552292":{"stats":{"week":{"2015":{"1":{"1":"1","70":"4","71":"1","74":"1","pts":"6.50"}}}}},"2495775":{"stats":{"week":{"2015":{"1":{"1":"1","70":"9","81":"2","pts":"11.00"}}}}},"2506677":{"stats":{"week":{"2015":{"1":{"1":"1","33":"4","pts":"4.00"}}}}},"2540928":{"stats":{"week":{"2015":{"1":{"1":"1","20":"4","21":"82","22":"1","pts":"14.20"}}}}},"2552436":{"stats":{"week":{"2015":{"1":{"pts":null}}}}},"2552321":{"stats":{"week":{"2015":{"1":{"1":"1","70":"3","71":"1","81":"1","84":"1","pts":"4.50"}}}}},"497234":{"stats":{"week":{"2015":{"1":{"pts":null}}}}},"2495184":{"stats":{"week":{"2015":{"1":{"1":"1","70":"2","81":"2","84":"2","85":"1","pts":"4.00"}}}}},"2550325":{"stats":{"week":{"2015":{"1":{"1":"1","33":"4","38":"1","pts":"7.00"}}}}},"2495651":{"stats":{"week":{"2015":{"1":{"pts":null}}}}},"2507793":{"stats":{"week":{"2015":{"1":{"1":"1","70":"1","pts":"1.00"}}}}},"2506121":{"stats":{"week":{"2015":{"1":{"1":"1","2":"41","3":"34","4":"7","5":"403","6":"2","7":"2","8":"2","10":"1","13":"2","14":"-2","75":"1","pts":"19.92"}}}}},"2540154":{"stats":{"week":{"2015":{"1":{"1":"1","20":"15","21":"166","25":"1","pts":"16.60"}}}}},"2505583":{"stats":{"week":{"2015":{"1":{"pts":null}}}}},"2552469":{"stats":{"week":{"2015":{"1":{"1":"1","13":"14","14":"51","20":"3","21":"16","30":"1","31":"1","70":"1","pts":"4.70"}}}}},"2539931":{"stats":{"week":{"2015":{"1":{"1":"1","70":"2","72":"1","84":"2","85":"2","86":"9","pts":"4.00"}}}}},"2532853":{"stats":{"week":{"2015":{"1":{"pts":null}}}}},"2533340":{"stats":{"week":{"2015":{"1":{"pts":null}}}}},"2552676":{"stats":{"week":{"2015":{"1":{"1":"1","85":"1","pts":"0.00"}}}}},"2540164":{"stats":{"week":{"2015":{"1":{"1":"1","70":"4","71":"1","pts":"4.50"}}}}},"2540159":{"stats":{"week":{"2015":{"1":{"1":"1","70":"5","71":"2","84":"1","pts":"6.00"}}}}},"2495466":{"stats":{"week":{"2015":{"1":{"1":"1","13":"9","14":"24","20":"8","21":"98","pts":"12.20"}}}}},"2540180":{"stats":{"week":{"2015":{"1":{"1":"1","70":"8","81":"3","84":"1","89":"1","pts":"11.00"}}}}},"2504775":{"stats":{"week":{"2015":{"1":{"1":"1","2":"48","3":"30","4":"18","5":"355","6":"1","7":"1","8":"2","9":"1","13":"1","14":"3","pts":"16.50"}}}}},"2543498":{"stats":{"week":{"2015":{"1":{"1":"1","13":"1","14":"4","20":"4","21":"49","pts":"5.30"}}}}},"2532937":{"stats":{"week":{"2015":{"1":{"pts":null}}}}},"2553631":{"stats":{"week":{"2015":{"1":{"1":"1","13":"2","14":"6","pts":"0.60"}}}}},"100002":{"stats":{"week":{"2015":{"1":{"1":"1","45":"4","46":"1","50":"1","52":"42","54":"13","57":"1","62":"219","65":"1","pts":"16.00"}}}}},"100009":{"stats":{"week":{"2015":{"1":{"1":"1","45":"2","46":"2","50":"1","52":"20","54":"7","57":"1","62":"173","64":"1","pts":"16.00"}}}}},"100006":{"stats":{"week":{"2015":{"1":{"1":"1","45":"2","46":"1","47":"1","48":"2","52":"37","54":"13","57":"1","62":"246","65":"1","pts":"10.00"}}}}},"100018":{"stats":{"week":{"2015":{"1":{"1":"1","51":"1","52":"96","54":"33","60":"1","62":"396","66":"1","pts":"-1.00"}}}}},"100012":{"stats":{"week":{"2015":{"1":{"1":"1","45":"4","46":"2","48":"1","50":"1","52":"31","54":"14","58":"1","62":"273","65":"1","pts":"15.00"}}}}},"100031":{"stats":{"week":{"2015":{"1":{"1":"1","45":"2","47":"1","48":"2","52":"100","54":"36","61":"1","62":"309","66":"1","pts":"0.00"}}}}},"2543769":{"stats":{"week":{"2015":{"1":{"1":"1","70":"6","71":"1","pts":"6.50"}}}}},"2543466":{"stats":{"week":{"2015":{"1":{"1":"1","20":"4","21":"53","22":"1","pts":"11.30"}}}}},"2495821":{"stats":{"week":{"2015":{"1":{"pts":null}}}}},"2542022":{"stats":{"week":{"2015":{"1":{"pts":null}}}}},"744":{"stats":{"week":{"2015":{"1":{"1":"1","70":"5","71":"1","84":"1","pts":"5.50"}}}}},"2534437":{"stats":{"week":{"2015":{"1":{"1":"1","13":"1","14":"4","20":"2","21":"5","70":"2","pts":"2.90"}}}}},"2506921":{"stats":{"week":{"2015":{"1":{"pts":null}}}}},"2535892":{"stats":{"week":{"2015":{"1":{"pts":null}}}}},"2506879":{"stats":{"week":{"2015":{"1":{"1":"1","70":"2","pts":"2.00"}}}}},"2507473":{"stats":{"week":{"2015":{"1":{"pts":null}}}}},"4327":{"stats":{"week":{"2015":{"1":{"pts":null}}}}},"2495783":{"stats":{"week":{"2015":{"1":{"pts":null}}}}},"2530491":{"stats":{"week":{"2015":{"1":{"1":"1","70":"6","71":"2","pts":"7.00"}}}}},"2495136":{"stats":{"week":{"2015":{"1":{"pts":null}}}}},"2543682":{"stats":{"week":{"2015":{"1":{"1":"1","13":"12","14":"74","15":"1","20":"2","21":"12","22":"1","27":"17","31":"1","pts":"20.60"}}}}},"2530510":{"stats":{"week":{"2015":{"1":{"1":"1","70":"3","84":"1","pts":"3.00"}}}}},"382":{"stats":{"week":{"2015":{"1":{"1":"1","2":"32","3":"18","4":"14","5":"117","7":"2","8":"2","pts":"0.68"}}}}},"2540230":{"stats":{"week":{"2015":{"1":{"1":"1","20":"4","21":"17","pts":"1.70"}}}}},"768":{"stats":{"week":{"2015":{"1":{"pts":null}}}}},"2543499":{"stats":{"week":{"2015":{"1":{"1":"1","2":"12","3":"7","4":"5","5":"61","13":"1","14":"8","31":"1","pts":"3.24"}}}}},"2552487":{"stats":{"week":{"2015":{"1":{"1":"1","20":"5","21":"47","pts":"4.70"}}}}},"2532873":{"stats":{"week":{"2015":{"1":{"1":"1","70":"3","pts":"3.00"}}}}},"927":{"stats":{"week":{"2015":{"1":{"pts":null}}}}},"2506899":{"stats":{"week":{"2015":{"1":{"pts":null}}}}},"2541161":{"stats":{"week":{"2015":{"1":{"1":"1","13":"11","14":"44","20":"7","21":"36","pts":"8.00"}}}}},"2507843":{"stats":{"week":{"2015":{"1":{"1":"1","70":"6","71":"3","pts":"7.50"}}}}},"496749":{"stats":{"week":{"2015":{"1":{"pts":null}}}}},"2552466":{"stats":{"week":{"2015":{"1":{"1":"1","2":"15","3":"13","4":"2","5":"209","6":"4","8":"2","11":"1","12":"1","13":"2","14":"6","pts":"24.96"}}}}},"2532898":{"stats":{"week":{"2015":{"1":{"1":"1","70":"6","71":"1","72":"1","81":"1","84":"3","85":"1","86":"8","pts":"9.50"}}}}},"2506349":{"stats":{"week":{"2015":{"1":{"pts":null}}}}},"2504595":{"stats":{"week":{"2015":{"1":{"pts":null}}}}},"2506345":{"stats":{"week":{"2015":{"1":{"pts":null}}}}},"2543781":{"stats":{"week":{"2015":{"1":{"pts":null}}}}},"71441":{"stats":{"week":{"2015":{"1":{"1":"1","70":"7","71":"1","73":"1","76":"1","81":"1","82":"31","pts":"16.50"}}}}},"2532961":{"stats":{"week":{"2015":{"1":{"1":"1","70":"6","71":"3","pts":"7.50"}}}}},"89758":{"stats":{"week":{"2015":{"1":{"1":"1","70":"4","pts":"4.00"}}}}},"1302":{"stats":{"week":{"2015":{"1":{"1":"1","70":"2","71":"1","73":"1","76":"1","81":"2","82":"51","90":"1","pts":"12.50"}}}}},"2550541":{"stats":{"week":{"2015":{"1":{"1":"1","70":"1","71":"1","pts":"1.50"}}}}},"2540288":{"stats":{"week":{"2015":{"1":{"1":"1","70":"3","71":"2","73":"1","81":"1","pts":"7.00"}}}}},"2530660":{"stats":{"week":{"2015":{"1":{"pts":null}}}}},"2499278":{"stats":{"week":{"2015":{"1":{"1":"1","70":"6","71":"1","pts":"6.50"}}}}},"2543497":{"stats":{"week":{"2015":{"1":{"pts":null}}}}},"2540148":{"stats":{"week":{"2015":{"1":{"1":"1","20":"9","21":"104","22":"2","25":"1","pts":"22.40"}}}}},"2543463":{"stats":{"week":{"2015":{"1":{"1":"1","70":"3","71":"1","pts":"3.50"}}}}},"2543603":{"stats":{"week":{"2015":{"1":{"1":"1","13":"19","14":"63","15":"2","pts":"18.30"}}}}},"2495272":{"stats":{"week":{"2015":{"1":{"1":"1","70":"5","pts":"5.00"}}}}},"2495966":{"stats":{"week":{"2015":{"1":{"1":"1","20":"3","21":"43","22":"1","pts":"10.30"}}}}},"497322":{"stats":{"week":{"2015":{"1":{"1":"1","20":"8","21":"65","27":"20","pts":"6.50"}}}}},"2550164":{"stats":{"week":{"2015":{"1":{"1":"1","27":"27","70":"5","71":"1","81":"1","pts":"6.50"}}}}},"2532977":{"stats":{"week":{"2015":{"1":{"1":"1","20":"4","21":"101","22":"1","23":"1","24":"1","25":"1","pts":"16.10"}}}}},"774":{"stats":{"week":{"2015":{"1":{"pts":null}}}}},"89802":{"stats":{"week":{"2015":{"1":{"1":"1","33":"6","pts":"6.00"}}}}},"2532884":{"stats":{"week":{"2015":{"1":{"1":"1","20":"2","21":"19","pts":"1.90"}}}}},"2495143":{"stats":{"week":{"2015":{"1":{"1":"1","2":"34","3":"25","4":"9","5":"269","6":"2","13":"4","14":"1","pts":"18.86"}}}}},"2540269":{"stats":{"week":{"2015":{"1":{"pts":null}}}}},"2495832":{"stats":{"week":{"2015":{"1":{"pts":null}}}}},"2501863":{"stats":{"week":{"2015":{"1":{"pts":null}}}}},"497328":{"stats":{"week":{"2015":{"1":{"1":"1","20":"7","21":"60","pts":"6.00"}}}}},"2508107":{"stats":{"week":{"2015":{"1":{"1":"1","70":"8","73":"1","76":"1","81":"1","82":"24","pts":"17.00"}}}}},"2539237":{"stats":{"week":{"2015":{"1":{"1":"1","70":"3","71":"1","pts":"3.50"}}}}},"2553435":{"stats":{"week":{"2015":{"1":{"1":"1","20":"1","21":"55","22":"1","23":"1","24":"1","27":"43","pts":"11.50"}}}}},"2541302":{"stats":{"week":{"2015":{"1":{"1":"1","70":"6","71":"1","pts":"6.50"}}}}},"2508043":{"stats":{"week":{"2015":{"1":{"pts":null}}}}},"2506029":{"stats":{"week":{"2015":{"1":{"pts":null}}}}},"2534571":{"stats":{"week":{"2015":{"1":{"pts":null}}}}},"2535535":{"stats":{"week":{"2015":{"1":{"1":"1","70":"1","71":"1","pts":"0.00"}}}}},"2553833":{"stats":{"week":{"2015":{"1":{"1":"1","33":"3","34":"1","36":"1","37":"1","pts":"9.00"}}}}},"2536028":{"stats":{"week":{"2015":{"1":{"pts":null}}}}},"2532899":{"stats":{"week":{"2015":{"1":{"1":"1","13":"11","14":"52","20":"1","21":"2","pts":"5.40"}}}}},"2543504":{"stats":{"week":{"2015":{"1":{"1":"1","70":"6","84":"1","pts":"6.00"}}}}},"2506106":{"stats":{"week":{"2015":{"1":{"1":"1","20":"6","21":"87","pts":"8.70"}}}}},"496828":{"stats":{"week":{"2015":{"1":{"1":"1","70":"4","71":"1","72":"2","84":"2","85":"2","86":"16","88":"1","pts":"8.50"}}}}},"2506155":{"stats":{"week":{"2015":{"1":{"pts":null}}}}},"2552033":{"stats":{"week":{"2015":{"1":{"1":"1","2":"33","3":"16","4":"17","5":"210","6":"2","7":"2","8":"4","11":"1","13":"6","14":"18","31":"2","70":"1","75":"2","83":"-7","pts":"14.20"}}}}},"2553895":{"stats":{"week":{"2015":{"1":{"1":"1","20":"2","21":"14","pts":"1.40"}}}}},"2532946":{"stats":{"week":{"2015":{"1":{"1":"1","73":"1","76":"1","81":"1","82":"26","pts":"9.00"}}}}},"2499276":{"stats":{"week":{"2015":{"1":{"pts":null}}}}},"2506386":{"stats":{"week":{"2015":{"1":{"pts":null}}}}},"2495288":{"stats":{"week":{"2015":{"1":{"1":"1","pts":"0.00"}}}}},"2543493":{"stats":{"week":{"2015":{"1":{"1":"1","70":"2","71":"2","81":"1","pts":"4.00"}}}}},"2506469":{"stats":{"week":{"2015":{"1":{"pts":null}}}}},"2533437":{"stats":{"week":{"2015":{"1":{"pts":null}}}}},"2543464":{"stats":{"week":{"2015":{"1":{"1":"1","70":"5","71":"1","72":"2","81":"1","84":"2","85":"2","86":"8","88":"1","pts":"10.50"}}}}},"81879":{"stats":{"week":{"2015":{"1":{"pts":null}}}}},"2506400":{"stats":{"week":{"2015":{"1":{"pts":null}}}}},"2550328":{"stats":{"week":{"2015":{"1":{"1":"1","20":"4","21":"41","22":"1","pts":"10.10"}}}}},"2495476":{"stats":{"week":{"2015":{"1":{"1":"1","70":"3","72":"1","84":"3","85":"1","86":"8","pts":"5.00"}}}}},"2506122":{"stats":{"week":{"2015":{"1":{"1":"1","20":"3","21":"19","pts":"1.90"}}}}},"2495481":{"stats":{"week":{"2015":{"1":{"1":"1","70":"3","84":"1","pts":"3.00"}}}}},"2539319":{"stats":{"week":{"2015":{"1":{"1":"1","70":"4","71":"1","72":"2","84":"1","85":"2","86":"1","88":"1","pts":"8.50"}}}}},"2541556":{"stats":{"week":{"2015":{"1":{"1":"1","33":"1","37":"1","38":"1","39":"2","pts":"17.00"}}}}},"2539943":{"stats":{"week":{"2015":{"1":{"1":"1","70":"4","71":"1","pts":"4.50"}}}}},"2532828":{"stats":{"week":{"2015":{"1":{"1":"1","70":"3","71":"2","74":"1","pts":"6.00"}}}}},"71269":{"stats":{"week":{"2015":{"1":{"1":"1","20":"5","21":"37","pts":"3.70"}}}}},"2533060":{"stats":{"week":{"2015":{"1":{"1":"1","70":"2","pts":"2.00"}}}}},"496963":{"stats":{"week":{"2015":{"1":{"pts":null}}}}},"494317":{"stats":{"week":{"2015":{"1":{"pts":null}}}}},"2540151":{"stats":{"week":{"2015":{"1":{"1":"1","20":"1","21":"11","pts":"1.10"}}}}},"4433":{"stats":{"week":{"2015":{"1":{"pts":null}}}}},"2539243":{"stats":{"week":{"2015":{"1":{"1":"1","70":"3","71":"1","pts":"3.50"}}}}},"2552656":{"stats":{"week":{"2015":{"1":{"1":"1","27":"15","70":"1","pts":"0.00"}}}}},"2495467":{"stats":{"week":{"2015":{"1":{"1":"1","13":"3","14":"5","20":"1","21":"13","27":"61","pts":"1.80"}}}}},"81306":{"stats":{"week":{"2015":{"1":{"pts":null}}}}},"2552592":{"stats":{"week":{"2015":{"1":{"1":"1","70":"3","71":"2","81":"1","84":"1","pts":"5.00"}}}}},"262":{"stats":{"week":{"2015":{"1":{"pts":null}}}}},"2507644":{"stats":{"week":{"2015":{"1":{"1":"1","70":"2","pts":"2.00"}}}}},"79657":{"stats":{"week":{"2015":{"1":{"pts":null}}}}},"2539231":{"stats":{"week":{"2015":{"1":{"1":"1","70":"4","71":"1","pts":"4.50"}}}}},"2495202":{"stats":{"week":{"2015":{"1":{"1":"1","70":"1","84":"1","85":"2","pts":"1.00"}}}}},"2539262":{"stats":{"week":{"2015":{"1":{"pts":null}}}}},"222":{"stats":{"week":{"2015":{"1":{"pts":null}}}}},"2495450":{"stats":{"week":{"2015":{"1":{"1":"1","20":"5","21":"63","pts":"6.30"}}}}},"2539304":{"stats":{"week":{"2015":{"1":{"pts":null}}}}},"2503797":{"stats":{"week":{"2015":{"1":{"pts":null}}}}},"2552310":{"stats":{"week":{"2015":{"1":{"1":"1","70":"1","pts":"1.00"}}}}},"2535514":{"stats":{"week":{"2015":{"1":{"pts":null}}}}},"2543597":{"stats":{"week":{"2015":{"1":{"1":"1","70":"2","pts":"2.00"}}}}},"2506413":{"stats":{"week":{"2015":{"1":{"pts":null}}}}},"2533040":{"stats":{"week":{"2015":{"1":{"1":"1","20":"2","21":"34","pts":"3.40"}}}}},"494265":{"stats":{"week":{"2015":{"1":{"pts":null}}}}},"2495614":{"stats":{"week":{"2015":{"1":{"pts":null}}}}},"2495825":{"stats":{"week":{"2015":{"1":{"pts":null}}}}},"2495300":{"stats":{"week":{"2015":{"1":{"pts":null}}}}},"2507430":{"stats":{"week":{"2015":{"1":{"pts":null}}}}},"80680":{"stats":{"week":{"2015":{"1":{"pts":null}}}}},"2532869":{"stats":{"week":{"2015":{"1":{"1":"1","70":"1","71":"1","pts":"1.50"}}}}},"79852":{"stats":{"week":{"2015":{"1":{"pts":null}}}}},"2550658":{"stats":{"week":{"2015":{"1":{"pts":null}}}}},"2507846":{"stats":{"week":{"2015":{"1":{"pts":null}}}}},"2532804":{"stats":{"week":{"2015":{"1":{"1":"1","70":"6","71":"1","pts":"6.50"}}}}},"2507301":{"stats":{"week":{"2015":{"1":{"pts":null}}}}},"2543683":{"stats":{"week":{"2015":{"1":{"1":"1","20":"5","21":"110","22":"2","23":"1","25":"1","pts":"23.00"}}}}},"2508126":{"stats":{"week":{"2015":{"1":{"pts":null}}}}},"2552670":{"stats":{"week":{"2015":{"1":{"1":"1","70":"3","72":"1","74":"1","84":"1","85":"1","86":"5","pts":"7.00"}}}}},"786":{"stats":{"week":{"2015":{"1":{"pts":null}}}}},"2505510":{"stats":{"week":{"2015":{"1":{"pts":null}}}}},"494277":{"stats":{"week":{"2015":{"1":{"1":"1","70":"1","84":"1","pts":"1.00"}}}}},"206":{"stats":{"week":{"2015":{"1":{"pts":null}}}}},"2553497":{"stats":{"week":{"2015":{"1":{"pts":null}}}}},"2508083":{"stats":{"week":{"2015":{"1":{"pts":null}}}}},"2540156":{"stats":{"week":{"2015":{"1":{"1":"1","13":"8","14":"63","20":"6","21":"25","pts":"8.80"}}}}},"494251":{"stats":{"week":{"2015":{"1":{"pts":null}}}}},"497190":{"stats":{"week":{"2015":{"1":{"pts":null}}}}},"496814":{"stats":{"week":{"2015":{"1":{"1":"1","70":"1","71":"1","72":"1","84":"1","85":"1","86":"9","pts":"3.50"}}}}},"2532870":{"stats":{"week":{"2015":{"1":{"1":"1","70":"2","71":"2","81":"1","84":"1","85":"1","pts":"4.00"}}}}},"71431":{"stats":{"week":{"2015":{"1":{"pts":null}}}}},"496816":{"stats":{"week":{"2015":{"1":{"1":"1","70":"3","72":"1","84":"1","85":"1","86":"11","pts":"5.00"}}}}},"2533005":{"stats":{"week":{"2015":{"1":{"pts":null}}}}},"4267":{"stats":{"week":{"2015":{"1":{"pts":null}}}}},"2507399":{"stats":{"week":{"2015":{"1":{"pts":null}}}}},"2541966":{"stats":{"week":{"2015":{"1":{"1":"1","20":"1","21":"8","70":"1","pts":"0.80"}}}}},"2539266":{"stats":{"week":{"2015":{"1":{"pts":null}}}}},"2552647":{"stats":{"week":{"2015":{"1":{"1":"1","27":"2","pts":"0.00"}}}}},"2552631":{"stats":{"week":{"2015":{"1":{"1":"1","13":"9","14":"30","20":"1","21":"4","pts":"3.40"}}}}},"2543474":{"stats":{"week":{"2015":{"1":{"1":"1","70":"5","81":"1","pts":"6.00"}}}}},"494307":{"stats":{"week":{"2015":{"1":{"1":"1","70":"3","71":"1","73":"1","81":"1","pts":"6.50"}}}}},"79545":{"stats":{"week":{"2015":{"1":{"pts":null}}}}},"71423":{"stats":{"week":{"2015":{"1":{"1":"1","70":"1","85":"1","pts":"1.00"}}}}},"2354":{"stats":{"week":{"2015":{"1":{"1":"1","70":"1","71":"1","pts":"1.50"}}}}},"2505785":{"stats":{"week":{"2015":{"1":{"pts":null}}}}},"2507173":{"stats":{"week":{"2015":{"1":{"pts":null}}}}},"2507784":{"stats":{"week":{"2015":{"1":{"1":"1","70":"1","75":"1","85":"1","pts":"3.00"}}}}},"2495339":{"stats":{"week":{"2015":{"1":{"1":"1","70":"3","71":"1","pts":"3.50"}}}}},"2536340":{"stats":{"week":{"2015":{"1":{"1":"1","33":"1","38":"1","39":"1","pts":"9.00"}}}}},"2532986":{"stats":{"week":{"2015":{"1":{"1":"1","70":"1","pts":"1.00"}}}}},"2495853":{"stats":{"week":{"2015":{"1":{"pts":null}}}}},"496780":{"stats":{"week":{"2015":{"1":{"1":"1","70":"1","71":"1","72":"1","84":"1","85":"2","86":"6","pts":"3.50"}}}}},"2552273":{"stats":{"week":{"2015":{"1":{"1":"1","70":"1","71":"2","85":"1","pts":"2.00"}}}}},"2532964":{"stats":{"week":{"2015":{"1":{"pts":null}}}}},"2543664":{"stats":{"week":{"2015":{"1":{"pts":null}}}}},"2552280":{"stats":{"week":{"2015":{"1":{"1":"1","70":"2","71":"1","81":"1","pts":"3.50"}}}}},"2517637":{"stats":{"week":{"2015":{"1":{"1":"1","70":"1","75":"1","pts":"3.00"}}}}},"2495487":{"stats":{"week":{"2015":{"1":{"pts":null}}}}},"2543505":{"stats":{"week":{"2015":{"1":{"1":"1","71":"1","81":"1","pts":"1.50"}}}}},"71417":{"stats":{"week":{"2015":{"1":{"pts":null}}}}},"2542065":{"stats":{"week":{"2015":{"1":{"1":"1","2":"31","3":"23","4":"8","5":"142","6":"2","7":"1","8":"2","30":"1","31":"1","pts":"9.68"}}}}},"2550597":{"stats":{"week":{"2015":{"1":{"1":"1","20":"3","21":"12","pts":"1.20"}}}}},"80670":{"stats":{"week":{"2015":{"1":{"pts":null}}}}},"2532880":{"stats":{"week":{"2015":{"1":{"pts":null}}}}},"2543770":{"stats":{"week":{"2015":{"1":{"1":"1","13":"5","14":"12","20":"2","21":"23","pts":"3.50"}}}}},"2552291":{"stats":{"week":{"2015":{"1":{"1":"1","73":"1","81":"1","82":"8","pts":"3.00"}}}}},"2550198":{"stats":{"week":{"2015":{"1":{"1":"1","70":"1","pts":"0.00"}}}}},"2552402":{"stats":{"week":{"2015":{"1":{"1":"1","27":"10","pts":"0.00"}}}}},"2495835":{"stats":{"week":{"2015":{"1":{"pts":null}}}}},"2552282":{"stats":{"week":{"2015":{"1":{"1":"1","70":"1","pts":"1.00"}}}}},"2552329":{"stats":{"week":{"2015":{"1":{"1":"1","27":"10","pts":"0.00"}}}}},"2550256":{"stats":{"week":{"2015":{"1":{"1":"1","20":"1","21":"63","pts":"6.30"}}}}},"2506908":{"stats":{"week":{"2015":{"1":{"pts":null}}}}},"2495347":{"stats":{"week":{"2015":{"1":{"1":"1","27":"8","pts":"0.00"}}}}},"79629":{"stats":{"week":{"2015":{"1":{"pts":null}}}}},"2505576":{"stats":{"week":{"2015":{"1":{"pts":null}}}}},"2553523":{"stats":{"week":{"2015":{"1":{"pts":null}}}}},"2508084":{"stats":{"week":{"2015":{"1":{"1":"1","70":"2","71":"1","73":"1","74":"1","81":"1","82":"27","pts":"7.50"}}}}},"497238":{"stats":{"week":{"2015":{"1":{"1":"1","20":"1","21":"4","pts":"0.40"}}}}},"71459":{"stats":{"week":{"2015":{"1":{"pts":null}}}}},"2539270":{"stats":{"week":{"2015":{"1":{"1":"1","70":"2","71":"1","84":"1","pts":"2.50"}}}}},"2540005":{"stats":{"week":{"2015":{"1":{"1":"1","20":"2","21":"25","70":"1","pts":"2.50"}}}}},"2505988":{"stats":{"week":{"2015":{"1":{"pts":null}}}}},"2552468":{"stats":{"week":{"2015":{"1":{"1":"1","20":"1","21":"15","pts":"1.50"}}}}},"2543776":{"stats":{"week":{"2015":{"1":{"1":"1","70":"2","pts":"2.00"}}}}},"2539995":{"stats":{"week":{"2015":{"1":{"pts":null}}}}},"2507167":{"stats":{"week":{"2015":{"1":{"1":"1","73":"1","81":"1","pts":"3.00"}}}}},"2534799":{"stats":{"week":{"2015":{"1":{"pts":null}}}}},"71353":{"stats":{"week":{"2015":{"1":{"pts":null}}}}},"2553820":{"stats":{"week":{"2015":{"1":{"pts":null}}}}},"238403":{"stats":{"week":{"2015":{"1":{"pts":null}}}}},"2540176":{"stats":{"week":{"2015":{"1":{"1":"1","70":"1","pts":"1.00"}}}}},"2552464":{"stats":{"week":{"2015":{"1":{"1":"1","75":"1","pts":"0.00"}}}}},"2550167":{"stats":{"week":{"2015":{"1":{"1":"1","70":"1","pts":"1.00"}}}}},"496762":{"stats":{"week":{"2015":{"1":{"1":"1","70":"2","72":"1","74":"1","85":"2","86":"14","pts":"6.00"}}}}},"2495617":{"stats":{"week":{"2015":{"1":{"1":"1","70":"2","71":"1","84":"1","pts":"2.50"}}}}},"2495504":{"stats":{"week":{"2015":{"1":{"1":"1","70":"1","pts":"1.00"}}}}},"2539265":{"stats":{"week":{"2015":{"1":{"1":"1","20":"1","21":"24","pts":"2.40"}}}}},"2539219":{"stats":{"week":{"2015":{"1":{"1":"1","70":"1","81":"1","pts":"2.00"}}}}},"2550206":{"stats":{"week":{"2015":{"1":{"1":"1","pts":"0.00"}}}}},"2550163":{"stats":{"week":{"2015":{"1":{"1":"1","20":"1","21":"8","pts":"0.80"}}}}},"2536032":{"stats":{"week":{"2015":{"1":{"1":"1","70":"2","71":"1","pts":"2.50"}}}}},"2536532":{"stats":{"week":{"2015":{"1":{"pts":null}}}}},"2552262":{"stats":{"week":{"2015":{"1":{"1":"1","70":"2","pts":"2.00"}}}}},"2552397":{"stats":{"week":{"2015":{"1":{"1":"1","20":"1","21":"1","pts":"0.10"}}}}},"2553437":{"stats":{"week":{"2015":{"1":{"1":"1","70":"1","pts":"1.00"}}}}},"2495869":{"stats":{"week":{"2015":{"1":{"pts":null}}}}},"2541792":{"stats":{"week":{"2015":{"1":{"1":"1","70":"2","71":"1","pts":"2.50"}}}}},"2532901":{"stats":{"week":{"2015":{"1":{"pts":null}}}}},"2539233":{"stats":{"week":{"2015":{"1":{"1":"1","70":"2","pts":"2.00"}}}}},"2540020":{"stats":{"week":{"2015":{"1":{"1":"1","20":"2","21":"37","22":"1","pts":"9.70"}}}}},"2552318":{"stats":{"week":{"2015":{"1":{"pts":null}}}}},"2541154":{"stats":{"week":{"2015":{"1":{"1":"1","70":"1","pts":"1.00"}}}}},"2535869":{"stats":{"week":{"2015":{"1":{"1":"1","20":"1","21":"8","pts":"0.80"}}}}},"2504257":{"stats":{"week":{"2015":{"1":{"1":"1","33":"1","pts":"1.00"}}}}},"2543794":{"stats":{"week":{"2015":{"1":{"pts":null}}}}},"2495453":{"stats":{"week":{"2015":{"1":{"1":"1","70":"1","pts":"0.00"}}}}},"2541944":{"stats":{"week":{"2015":{"1":{"1":"1","20":"1","21":"6","pts":"0.60"}}}}},"2552680":{"stats":{"week":{"2015":{"1":{"pts":null}}}}},"2543605":{"stats":{"week":{"2015":{"1":{"pts":null}}}}},"100023":{"stats":{"week":{"2015":{"1":{"1":"1","46":"2","47":"1","48":"2","50":"1","52":"3","54":"27","59":"1","62":"436","67":"1","pts":"12.00"}}}}},"100008":{"stats":{"week":{"2015":{"1":{"1":"1","45":"1","52":"93","54":"20","58":"1","62":"285","65":"1","pts":"2.00"}}}}},"2535708":{"stats":{"week":{"2015":{"1":{"pts":null}}}}},"2550481":{"stats":{"week":{"2015":{"1":{"pts":null}}}}},"2540171":{"stats":{"week":{"2015":{"1":{"pts":null}}}}},"71193":{"stats":{"week":{"2015":{"1":{"pts":null}}}}},"2540147":{"stats":{"week":{"2015":{"1":{"pts":null}}}}},"2543869":{"stats":{"week":{"2015":{"1":{"1":"1","70":"2","71":"3","85":"1","pts":"3.50"}}}}},"2505354":{"stats":{"week":{"2015":{"1":{"pts":null}}}}},"2540211":{"stats":{"week":{"2015":{"1":{"1":"1","20":"2","21":"8","22":"1","pts":"6.80"}}}}},"2495108":{"stats":{"week":{"2015":{"1":{"1":"1","70":"6","71":"2","pts":"7.00"}}}}},"496853":{"stats":{"week":{"2015":{"1":{"pts":null}}}}},"2552454":{"stats":{"week":{"2015":{"1":{"1":"1","70":"2","71":"2","84":"1","pts":"3.00"}}}}},"2495678":{"stats":{"week":{"2015":{"1":{"pts":null}}}}},"2505629":{"stats":{"week":{"2015":{"1":{"pts":null}}}}},"2535698":{"stats":{"week":{"2015":{"1":{"1":"1","20":"4","21":"49","27":"-3","30":"1","31":"1","pts":"2.90"}}}}},"306":{"stats":{"week":{"2015":{"1":{"pts":null}}}}},"2539205":{"stats":{"week":{"2015":{"1":{"1":"1","20":"5","21":"60","pts":"6.00"}}}}},"497278":{"stats":{"week":{"2015":{"1":{"pts":null}}}}},"2495259":{"stats":{"week":{"2015":{"1":{"1":"1","33":"3","36":"1","37":"1","pts":"9.00"}}}}},"2533059":{"stats":{"week":{"2015":{"1":{"1":"1","70":"2","pts":"2.00"}}}}},"2505996":{"stats":{"week":{"2015":{"1":{"1":"1","2":"36","3":"20","4":"16","5":"189","8":"1","13":"1","14":"8","pts":"8.36"}}}}},"2506619":{"stats":{"week":{"2015":{"1":{"pts":null}}}}},"2543592":{"stats":{"week":{"2015":{"1":{"1":"1","70":"4","71":"4","85":"1","pts":"6.00"}}}}},"71345":{"stats":{"week":{"2015":{"1":{"pts":null}}}}},"496937":{"stats":{"week":{"2015":{"1":{"1":"1","70":"7","71":"2","84":"1","pts":"8.00"}}}}},"494259":{"stats":{"week":{"2015":{"1":{"1":"1","70":"4","71":"4","pts":"6.00"}}}}},"2540219":{"stats":{"week":{"2015":{"1":{"pts":null}}}}},"2543496":{"stats":{"week":{"2015":{"1":{"1":"1","20":"5","21":"44","pts":"4.40"}}}}},"2495311":{"stats":{"week":{"2015":{"1":{"pts":null}}}}},"4365":{"stats":{"week":{"2015":{"1":{"1":"1","70":"5","81":"1","pts":"6.00"}}}}},"497312":{"stats":{"week":{"2015":{"1":{"pts":null}}}}},"2505459":{"stats":{"week":{"2015":{"1":{"pts":null}}}}},"2495164":{"stats":{"week":{"2015":{"1":{"1":"1","70":"2","pts":"2.00"}}}}},"2508132":{"stats":{"week":{"2015":{"1":{"pts":null}}}}},"2533061":{"stats":{"week":{"2015":{"1":{"pts":null}}}}},"2532974":{"stats":{"week":{"2015":{"1":{"1":"1","70":"3","84":"1","pts":"3.00"}}}}},"2495159":{"stats":{"week":{"2015":{"1":{"1":"1","13":"1","14":"11","27":"3","pts":"1.10"}}}}},"2543565":{"stats":{"week":{"2015":{"1":{"1":"1","13":"6","14":"14","pts":"1.40"}}}}},"2533533":{"stats":{"week":{"2015":{"1":{"pts":null}}}}},"2552568":{"stats":{"week":{"2015":{"1":{"1":"1","70":"1","81":"1","pts":"2.00"}}}}},"2495473":{"stats":{"week":{"2015":{"1":{"pts":null}}}}},"2537933":{"stats":{"week":{"2015":{"1":{"pts":null}}}}},"284":{"stats":{"week":{"2015":{"1":{"pts":null}}}}},"2505363":{"stats":{"week":{"2015":{"1":{"pts":null}}}}},"2550312":{"stats":{"week":{"2015":{"1":{"1":"1","70":"2","pts":"2.00"}}}}},"2543490":{"stats":{"week":{"2015":{"1":{"1":"1","71":"3","85":"1","pts":"1.50"}}}}},"2532821":{"stats":{"week":{"2015":{"1":{"1":"1","70":"3","72":"1","84":"2","85":"1","86":"3","pts":"5.00"}}}}},"2552446":{"stats":{"week":{"2015":{"1":{"1":"1","85":"1","pts":"0.00"}}}}},"2533019":{"stats":{"week":{"2015":{"1":{"pts":null}}}}},"2532972":{"stats":{"week":{"2015":{"1":{"pts":null}}}}},"2543641":{"stats":{"week":{"2015":{"1":{"pts":null}}}}},"2495585":{"stats":{"week":{"2015":{"1":{"pts":null}}}}},"2495912":{"stats":{"week":{"2015":{"1":{"pts":null}}}}},"2532992":{"stats":{"week":{"2015":{"1":{"1":"1","71":"1","pts":"0.50"}}}}},"2532965":{"stats":{"week":{"2015":{"1":{"pts":null}}}}},"71249":{"stats":{"week":{"2015":{"1":{"pts":null}}}}},"100025":{"stats":{"week":{"2015":{"1":{"1":"1","45":"1","46":"2","52":"25","54":"26","59":"1","62":"395","66":"1","pts":"5.00"}}}}},"100001":{"stats":{"week":{"2015":{"1":{"1":"1","46":"2","48":"1","52":"77","54":"24","59":"1","62":"399","66":"1","pts":"4.00"}}}}},"1037889":{"stats":{"week":{"2015":{"1":{"pts":null}}}}},"497095":{"stats":{"week":{"2015":{"1":{"1":"1","2":"52","3":"36","4":"16","5":"336","6":"1","7":"2","9":"1","pts":"13.44"}}}}},"2495207":{"stats":{"week":{"2015":{"1":{"pts":null}}}}},"2495597":{"stats":{"week":{"2015":{"1":{"pts":null}}}}},"2540158":{"stats":{"week":{"2015":{"1":{"1":"1","20":"3","21":"46","70":"1","pts":"4.60"}}}}},"2507029":{"stats":{"week":{"2015":{"1":{"pts":null}}}}},"497260":{"stats":{"week":{"2015":{"1":{"pts":null}}}}},"2552453":{"stats":{"week":{"2015":{"1":{"1":"1","13":"20","14":"80","pts":"8.00"}}}}},"2495356":{"stats":{"week":{"2015":{"1":{"pts":null}}}}},"310":{"stats":{"week":{"2015":{"1":{"1":"1","2":"34","3":"23","4":"11","5":"298","6":"2","7":"2","8":"1","13":"5","14":"7","pts":"16.62"}}}}},"2495454":{"stats":{"week":{"2015":{"1":{"1":"1","20":"9","21":"141","22":"2","25":"1","pts":"26.10"}}}}},"494254":{"stats":{"week":{"2015":{"1":{"pts":null}}}}},"2506366":{"stats":{"week":{"2015":{"1":{"pts":null}}}}},"79848":{"stats":{"week":{"2015":{"1":{"1":"1","70":"5","71":"1","81":"3","84":"1","89":"1","pts":"8.50"}}}}},"2532890":{"stats":{"week":{"2015":{"1":{"1":"1","70":"5","71":"5","pts":"7.50"}}}}},"2543583":{"stats":{"week":{"2015":{"1":{"1":"1","13":"10","14":"18","20":"3","21":"29","pts":"4.70"}}}}},"2533051":{"stats":{"week":{"2015":{"1":{"1":"1","70":"1","71":"1","72":"1","84":"1","85":"2","86":"8","pts":"3.50"}}}}},"496788":{"stats":{"week":{"2015":{"1":{"1":"1","70":"2","71":"1","pts":"2.50"}}}}},"2504797":{"stats":{"week":{"2015":{"1":{"1":"1","33":"2","37":"1","38":"3","pts":"14.00"}}}}},"2506398":{"stats":{"week":{"2015":{"1":{"pts":null}}}}},"2552301":{"stats":{"week":{"2015":{"1":{"1":"1","70":"1","71":"2","81":"1","85":"1","pts":"3.00"}}}}},"2541535":{"stats":{"week":{"2015":{"1":{"1":"1","70":"9","71":"3","87":"1","pts":"10.50"}}}}},"2506467":{"stats":{"week":{"2015":{"1":{"1":"1","13":"5","14":"50","20":"7","21":"76","27":"25","31":"1","pts":"12.60"}}}}},"2550284":{"stats":{"week":{"2015":{"1":{"1":"1","70":"1","pts":"0.00"}}}}},"2495310":{"stats":{"week":{"2015":{"1":{"1":"1","70":"8","71":"2","81":"1","pts":"10.00"}}}}},"71197":{"stats":{"week":{"2015":{"1":{"pts":null}}}}},"496851":{"stats":{"week":{"2015":{"1":{"pts":null}}}}},"2539935":{"stats":{"week":{"2015":{"1":{"1":"1","70":"4","71":"2","73":"1","81":"1","pts":"8.00"}}}}},"71405":{"stats":{"week":{"2015":{"1":{"pts":null}}}}},"2543746":{"stats":{"week":{"2015":{"1":{"1":"1","20":"2","21":"19","pts":"1.90"}}}}},"2539653":{"stats":{"week":{"2015":{"1":{"1":"1","71":"1","81":"1","pts":"1.50"}}}}},"71341":{"stats":{"week":{"2015":{"1":{"pts":null}}}}},"2495801":{"stats":{"week":{"2015":{"1":{"pts":null}}}}},"2540163":{"stats":{"week":{"2015":{"1":{"1":"1","70":"2","71":"2","84":"1","pts":"3.00"}}}}},"2539334":{"stats":{"week":{"2015":{"1":{"1":"1","81":"1","pts":"1.00"}}}}},"2543500":{"stats":{"week":{"2015":{"1":{"1":"1","20":"10","21":"102","25":"1","pts":"10.20"}}}}},"2507218":{"stats":{"week":{"2015":{"1":{"pts":null}}}}},"2495140":{"stats":{"week":{"2015":{"1":{"1":"1","70":"1","pts":"1.00"}}}}},"2552600":{"stats":{"week":{"2015":{"1":{"1":"1","20":"1","21":"5","pts":"0.50"}}}}},"2532825":{"stats":{"week":{"2015":{"1":{"1":"1","70":"1","pts":"1.00"}}}}},"2540203":{"stats":{"week":{"2015":{"1":{"1":"1","20":"1","21":"4","70":"1","pts":"0.40"}}}}},"2506888":{"stats":{"week":{"2015":{"1":{"pts":null}}}}},"494315":{"stats":{"week":{"2015":{"1":{"pts":null}}}}},"2664":{"stats":{"week":{"2015":{"1":{"pts":null}}}}},"497282":{"stats":{"week":{"2015":{"1":{"pts":null}}}}},"497188":{"stats":{"week":{"2015":{"1":{"pts":null}}}}},"2550380":{"stats":{"week":{"2015":{"1":{"1":"1","33":"3","36":"1","43":"1","pts":"6.00"}}}}},"238489":{"stats":{"week":{"2015":{"1":{"pts":null}}}}},"2541431":{"stats":{"week":{"2015":{"1":{"1":"1","70":"2","pts":"2.00"}}}}},"2539215":{"stats":{"week":{"2015":{"1":{"pts":null}}}}},"2495158":{"stats":{"week":{"2015":{"1":{"pts":null}}}}},"324":{"stats":{"week":{"2015":{"1":{"pts":null}}}}},"2552327":{"stats":{"week":{"2015":{"1":{"1":"1","71":"1","85":"1","pts":"0.50"}}}}},"2530666":{"stats":{"week":{"2015":{"1":{"pts":null}}}}},"2540279":{"stats":{"week":{"2015":{"1":{"pts":null}}}}},"2543478":{"stats":{"week":{"2015":{"1":{"pts":null}}}}},"2543884":{"stats":{"week":{"2015":{"1":{"1":"1","70":"1","pts":"1.00"}}}}},"2507918":{"stats":{"week":{"2015":{"1":{"1":"1","71":"1","pts":"0.50"}}}}},"2552573":{"stats":{"week":{"2015":{"1":{"pts":null}}}}},"100020":{"stats":{"week":{"2015":{"1":{"1":"1","45":"1","47":"1","51":"1","52":"30","54":"20","58":"1","62":"395","66":"1","pts":"4.00"}}}}},"100029":{"stats":{"week":{"2015":{"1":{"1":"1","45":"5","46":"1","54":"3","56":"1","62":"248","65":"1","pts":"14.00"}}}}},"2543743":{"stats":{"week":{"2015":{"1":{"1":"1","13":"26","14":"168","15":"2","18":"1","20":"2","21":"14","pts":"30.20"}}}}},"2540155":{"stats":{"week":{"2015":{"1":{"1":"1","70":"7","pts":"7.00"}}}}},"2539293":{"stats":{"week":{"2015":{"1":{"pts":null}}}}},"2543459":{"stats":{"week":{"2015":{"1":{"1":"1","70":"10","71":"2","81":"1","84":"1","87":"1","pts":"12.00"}}}}},"2495186":{"stats":{"week":{"2015":{"1":{"pts":null}}}}},"2495459":{"stats":{"week":{"2015":{"1":{"1":"1","20":"1","21":"11","pts":"1.10"}}}}},"2505552":{"stats":{"week":{"2015":{"1":{"1":"1","70":"7","pts":"7.00"}}}}},"2506874":{"stats":{"week":{"2015":{"1":{"pts":null}}}}},"2534820":{"stats":{"week":{"2015":{"1":{"1":"1","20":"3","21":"40","pts":"4.00"}}}}},"2532948":{"stats":{"week":{"2015":{"1":{"1":"1","70":"5","71":"4","pts":"7.00"}}}}},"80668":{"stats":{"week":{"2015":{"1":{"1":"1","70":"1","pts":"1.00"}}}}},"2495826":{"stats":{"week":{"2015":{"1":{"1":"1","20":"3","21":"47","pts":"4.70"}}}}},"496790":{"stats":{"week":{"2015":{"1":{"1":"1","70":"3","71":"1","72":"0.5","85":"2","pts":"4.50"}}}}},"2500351":{"stats":{"week":{"2015":{"1":{"1":"1","33":"2","36":"1","37":"1","41":"1","pts":"8.00"}}}}},"2525323":{"stats":{"week":{"2015":{"1":{"1":"1","70":"3","79":"1","pts":"5.00"}}}}},"2543465":{"stats":{"week":{"2015":{"1":{"1":"1","2":"32","3":"23","4":"9","5":"231","7":"1","8":"5","13":"3","14":"16","pts":"8.84"}}}}},"2532978":{"stats":{"week":{"2015":{"1":{"1":"1","20":"1","21":"27","70":"1","pts":"2.70"}}}}},"2507917":{"stats":{"week":{"2015":{"1":{"1":"1","70":"2","73":"1","81":"2","82":"26","pts":"6.00"}}}}},"2541147":{"stats":{"week":{"2015":{"1":{"1":"1","20":"2","21":"27","pts":"2.70"}}}}},"2543650":{"stats":{"week":{"2015":{"1":{"1":"1","70":"3","72":"1","81":"1","84":"2","85":"2","86":"14","pts":"6.00"}}}}},"2532968":{"stats":{"week":{"2015":{"1":{"pts":null}}}}},"2540215":{"stats":{"week":{"2015":{"1":{"1":"1","20":"1","21":"5","70":"1","pts":"0.50"}}}}},"2508007":{"stats":{"week":{"2015":{"1":{"1":"1","27":"9","pts":"0.00"}}}}},"2543646":{"stats":{"week":{"2015":{"1":{"1":"1","20":"2","21":"5","pts":"0.50"}}}}},"496802":{"stats":{"week":{"2015":{"1":{"1":"1","70":"2","71":"1","pts":"2.50"}}}}},"2495807":{"stats":{"week":{"2015":{"1":{"1":"1","70":"7","71":"1","72":"1","81":"1","84":"1","85":"1","86":"10","pts":"10.50"}}}}},"2507164":{"stats":{"week":{"2015":{"1":{"pts":null}}}}},"2532331":{"stats":{"week":{"2015":{"1":{"pts":null}}}}},"2552391":{"stats":{"week":{"2015":{"1":{"1":"1","70":"4","72":"1","84":"1","85":"1","86":"14","pts":"6.00"}}}}},"2553117":{"stats":{"week":{"2015":{"1":{"pts":null}}}}},"2532814":{"stats":{"week":{"2015":{"1":{"pts":null}}}}},"2507763":{"stats":{"week":{"2015":{"1":{"1":"1","20":"6","21":"63","pts":"6.30"}}}}},"2495438":{"stats":{"week":{"2015":{"1":{"1":"1","20":"5","21":"53","pts":"5.30"}}}}},"2508088":{"stats":{"week":{"2015":{"1":{"pts":null}}}}},"2543639":{"stats":{"week":{"2015":{"1":{"pts":null}}}}},"2539250":{"stats":{"week":{"2015":{"1":{"pts":null}}}}},"2495314":{"stats":{"week":{"2015":{"1":{"pts":null}}}}},"2507010":{"stats":{"week":{"2015":{"1":{"pts":null}}}}},"2532835":{"stats":{"week":{"2015":{"1":{"1":"1","20":"1","21":"3","pts":"0.30"}}}}},"2539960":{"stats":{"week":{"2015":{"1":{"pts":null}}}}},"2539224":{"stats":{"week":{"2015":{"1":{"1":"1","70":"1","72":"1","84":"1","85":"1","86":"10","pts":"3.00"}}}}},"2495723":{"stats":{"week":{"2015":{"1":{"1":"1","70":"2","pts":"2.00"}}}}},"2543715":{"stats":{"week":{"2015":{"1":{"1":"1","13":"3","14":"20","20":"2","21":"8","pts":"2.80"}}}}},"2540152":{"stats":{"week":{"2015":{"1":{"pts":null}}}}},"2495247":{"stats":{"week":{"2015":{"1":{"pts":null}}}}},"2505587":{"stats":{"week":{"2015":{"1":{"pts":null}}}}},"2506881":{"stats":{"week":{"2015":{"1":{"pts":null}}}}},"2495258":{"stats":{"week":{"2015":{"1":{"pts":null}}}}},"2543739":{"stats":{"week":{"2015":{"1":{"1":"1","70":"2","pts":"2.00"}}}}},"218":{"stats":{"week":{"2015":{"1":{"pts":null}}}}},"2543741":{"stats":{"week":{"2015":{"1":{"1":"1","70":"1","pts":"1.00"}}}}},"2540145":{"stats":{"week":{"2015":{"1":{"1":"1","20":"1","21":"1","27":"21","pts":"0.10"}}}}},"2532794":{"stats":{"week":{"2015":{"1":{"pts":null}}}}},"2552312":{"stats":{"week":{"2015":{"1":{"1":"1","70":"1","pts":"1.00"}}}}},"2552603":{"stats":{"week":{"2015":{"1":{"1":"1","70":"1","pts":"1.00"}}}}},"2540138":{"stats":{"week":{"2015":{"1":{"pts":null}}}}},"2550242":{"stats":{"week":{"2015":{"1":{"1":"1","71":"1","pts":"0.50"}}}}},"163982":{"stats":{"week":{"2015":{"1":{"pts":null}}}}}}}},"nflGames":{"2015091000":{"nflGameId":"2015091000","nflGameCenterUrl":"http:\/\/www.nfl.com\/gamecenter\/2015091000\/2015\/REG1\/steelers@patriots","gameDateAndTime":"2015-09-10T17:30:00-07:00","isGameRosterLocked":true,"gameStatus":"game_closed","gameClock":"Final","gameQuarter":"END OF GAME","playStatusDisplay":"Gillette Stadium","isOffenseInRedZone":false,"network":"NBC","lastStatFileProcessed":331,"lastClockTimeProcessed":"2015-09-10 20:40:18","onTheFieldPlayers":[],"down":1,"yardLine":"PIT 47","yardsRemaining":10,"homeTeam":{"nflTeamId":"21","opponentAbbr":"PIT","score":28,"hasPossession":false,"gameScoreDisplay":"W 28-21"},"awayTeam":{"nflTeamId":"27","opponentAbbr":"@NE","score":21,"hasPossession":false,"gameScoreDisplay":"L 21-28"}},"2015091300":{"nflGameId":"2015091300","nflGameCenterUrl":"http:\/\/www.nfl.com\/gamecenter\/2015091300\/2015\/REG1\/packers@bears","gameDateAndTime":"2015-09-13T10:00:00-07:00","isGameRosterLocked":true,"gameStatus":"game_closed","gameClock":"Final","gameQuarter":"END OF GAME","playStatusDisplay":"Soldier Field","isOffenseInRedZone":false,"network":"FOX","lastStatFileProcessed":294,"lastClockTimeProcessed":"2015-09-13 13:14:30","onTheFieldPlayers":[],"down":2,"yardLine":"CHI 46","yardsRemaining":10,"homeTeam":{"nflTeamId":"5","opponentAbbr":"GB","score":23,"hasPossession":false,"gameScoreDisplay":"L 23-31"},"awayTeam":{"nflTeamId":"11","opponentAbbr":"@CHI","score":31,"hasPossession":false,"gameScoreDisplay":"W 31-23"}},"2015091301":{"nflGameId":"2015091301","nflGameCenterUrl":"http:\/\/www.nfl.com\/gamecenter\/2015091301\/2015\/REG1\/seahawks@rams","gameDateAndTime":"2015-09-13T10:00:00-07:00","isGameRosterLocked":true,"gameStatus":"pre_game","gameClock":"Sun 10:00am PDT","gameQuarter":"GAME CLOSED","playStatusDisplay":"Los Angeles Memorial Coliseum","isOffenseInRedZone":false,"network":"FOX","lastStatFileProcessed":-1,"lastClockTimeProcessed":"2015-09-13 13:30:33","onTheFieldPlayers":[],"down":1,"yardLine":"STL 43","yardsRemaining":10,"homeTeam":{"nflTeamId":"17","opponentAbbr":"SEA","score":34,"hasPossession":true,"gameScoreDisplay":null},"awayTeam":{"nflTeamId":"30","opponentAbbr":"@LA","score":31,"hasPossession":false,"gameScoreDisplay":null}},"2015091302":{"nflGameId":"2015091302","nflGameCenterUrl":"http:\/\/www.nfl.com\/gamecenter\/2015091302\/2015\/REG1\/panthers@jaguars","gameDateAndTime":"2015-09-13T10:00:00-07:00","isGameRosterLocked":true,"gameStatus":"game_closed","gameClock":"Final","gameQuarter":"END OF GAME","playStatusDisplay":"TIAA Bank Field","isOffenseInRedZone":false,"network":"FOX","lastStatFileProcessed":289,"lastClockTimeProcessed":"2015-09-13 13:09:23","onTheFieldPlayers":[],"down":2,"yardLine":"JAX 45","yardsRemaining":11,"homeTeam":{"nflTeamId":"15","opponentAbbr":"CAR","score":9,"hasPossession":false,"gameScoreDisplay":"L 9-20"},"awayTeam":{"nflTeamId":"4","opponentAbbr":"@JAX","score":20,"hasPossession":false,"gameScoreDisplay":"W 20-9"}},"2015091303":{"nflGameId":"2015091303","nflGameCenterUrl":"http:\/\/www.nfl.com\/gamecenter\/2015091303\/2015\/REG1\/dolphins@redskins","gameDateAndTime":"2015-09-13T10:00:00-07:00","isGameRosterLocked":true,"gameStatus":"game_closed","gameClock":"Final","gameQuarter":"END OF GAME","playStatusDisplay":"FedExField","isOffenseInRedZone":false,"network":"CBS","lastStatFileProcessed":448,"lastClockTimeProcessed":"2015-09-13 13:01:45","onTheFieldPlayers":[],"down":2,"yardLine":"MIA 45","yardsRemaining":11,"homeTeam":{"nflTeamId":"32","opponentAbbr":"MIA","score":10,"hasPossession":false,"gameScoreDisplay":"L 10-17"},"awayTeam":{"nflTeamId":"19","opponentAbbr":"@WAS","score":17,"hasPossession":false,"gameScoreDisplay":"W 17-10"}},"2015091304":{"nflGameId":"2015091304","nflGameCenterUrl":"http:\/\/www.nfl.com\/gamecenter\/2015091304\/2015\/REG1\/colts@bills","gameDateAndTime":"2015-09-13T10:00:00-07:00","isGameRosterLocked":true,"gameStatus":"game_closed","gameClock":"Final","gameQuarter":"END OF GAME","playStatusDisplay":"New Era Field","isOffenseInRedZone":false,"network":"CBS","lastStatFileProcessed":505,"lastClockTimeProcessed":"2015-09-13 13:09:16","onTheFieldPlayers":[],"down":4,"yardLine":"IND 47","yardsRemaining":14,"homeTeam":{"nflTeamId":"3","opponentAbbr":"IND","score":27,"hasPossession":false,"gameScoreDisplay":"W 27-14"},"awayTeam":{"nflTeamId":"14","opponentAbbr":"@BUF","score":14,"hasPossession":false,"gameScoreDisplay":"L 14-27"}},"2015091305":{"nflGameId":"2015091305","nflGameCenterUrl":"http:\/\/www.nfl.com\/gamecenter\/2015091305\/2015\/REG1\/browns@jets","gameDateAndTime":"2015-09-13T10:00:00-07:00","isGameRosterLocked":true,"gameStatus":"game_closed","gameClock":"Final","gameQuarter":"END OF GAME","playStatusDisplay":"MetLife Stadium","isOffenseInRedZone":false,"network":"CBS","lastStatFileProcessed":361,"lastClockTimeProcessed":"2015-09-13 13:03:52","onTheFieldPlayers":[],"down":4,"yardLine":"CLE 11","yardsRemaining":6,"homeTeam":{"nflTeamId":"24","opponentAbbr":"CLE","score":31,"hasPossession":false,"gameScoreDisplay":"W 31-10"},"awayTeam":{"nflTeamId":"7","opponentAbbr":"@NYJ","score":10,"hasPossession":false,"gameScoreDisplay":"L 10-31"}},"2015091306":{"nflGameId":"2015091306","nflGameCenterUrl":"http:\/\/www.nfl.com\/gamecenter\/2015091306\/2015\/REG1\/chiefs@texans","gameDateAndTime":"2015-09-13T10:00:00-07:00","isGameRosterLocked":true,"gameStatus":"game_closed","gameClock":"Final","gameQuarter":"END OF GAME","playStatusDisplay":"NRG Stadium","isOffenseInRedZone":false,"network":"CBS","lastStatFileProcessed":359,"lastClockTimeProcessed":"2015-09-13 13:17:13","onTheFieldPlayers":[],"down":3,"yardLine":"KC 48","yardsRemaining":12,"homeTeam":{"nflTeamId":"13","opponentAbbr":"KC","score":20,"hasPossession":false,"gameScoreDisplay":"L 20-27"},"awayTeam":{"nflTeamId":"16","opponentAbbr":"@HOU","score":27,"hasPossession":false,"gameScoreDisplay":"W 27-20"}},"2015091308":{"nflGameId":"2015091308","nflGameCenterUrl":"http:\/\/www.nfl.com\/gamecenter\/2015091308\/2015\/REG1\/lions@chargers","gameDateAndTime":"2015-09-13T13:05:00-07:00","isGameRosterLocked":true,"gameStatus":"game_closed","gameClock":"Final","gameQuarter":"END OF GAME","playStatusDisplay":"StubHub Center","isOffenseInRedZone":false,"network":"FOX","lastStatFileProcessed":291,"lastClockTimeProcessed":"2015-09-13 16:07:51","onTheFieldPlayers":[],"down":3,"yardLine":"DET 49","yardsRemaining":12,"homeTeam":{"nflTeamId":"28","opponentAbbr":"DET","score":33,"hasPossession":false,"gameScoreDisplay":"W 33-28"},"awayTeam":{"nflTeamId":"10","opponentAbbr":"@LAC","score":28,"hasPossession":false,"gameScoreDisplay":"L 28-33"}},"2015091307":{"nflGameId":"2015091307","nflGameCenterUrl":"http:\/\/www.nfl.com\/gamecenter\/2015091307\/2015\/REG1\/saints@cardinals","gameDateAndTime":"2015-09-13T13:05:00-07:00","isGameRosterLocked":true,"gameStatus":"game_closed","gameClock":"Final","gameQuarter":"END OF GAME","playStatusDisplay":"University of Phoenix Stadium","isOffenseInRedZone":false,"network":"FOX","lastStatFileProcessed":326,"lastClockTimeProcessed":"2015-09-13 16:12:03","onTheFieldPlayers":[],"down":2,"yardLine":"NO 36","yardsRemaining":11,"homeTeam":{"nflTeamId":"26","opponentAbbr":"NO","score":31,"hasPossession":false,"gameScoreDisplay":"W 31-19"},"awayTeam":{"nflTeamId":"22","opponentAbbr":"@ARI","score":19,"hasPossession":false,"gameScoreDisplay":"L 19-31"}},"2015091309":{"nflGameId":"2015091309","nflGameCenterUrl":"http:\/\/www.nfl.com\/gamecenter\/2015091309\/2015\/REG1\/ravens@broncos","gameDateAndTime":"2015-09-13T13:25:00-07:00","isGameRosterLocked":true,"gameStatus":"game_closed","gameClock":"Final","gameQuarter":"END OF GAME","playStatusDisplay":"Sports Authority Field at Mile High","isOffenseInRedZone":false,"network":"CBS","lastStatFileProcessed":294,"lastClockTimeProcessed":"2015-09-13 16:19:12","onTheFieldPlayers":[],"down":2,"yardLine":"DEN 19","yardsRemaining":11,"homeTeam":{"nflTeamId":"9","opponentAbbr":"BAL","score":19,"hasPossession":false,"gameScoreDisplay":"W 19-13"},"awayTeam":{"nflTeamId":"2","opponentAbbr":"@DEN","score":13,"hasPossession":false,"gameScoreDisplay":"L 13-19"}},"2015091310":{"nflGameId":"2015091310","nflGameCenterUrl":"http:\/\/www.nfl.com\/gamecenter\/2015091310\/2015\/REG1\/bengals@raiders","gameDateAndTime":"2015-09-13T13:25:00-07:00","isGameRosterLocked":true,"gameStatus":"game_closed","gameClock":"Final","gameQuarter":"END OF GAME","playStatusDisplay":"Oakland Coliseum","isOffenseInRedZone":false,"network":"CBS","lastStatFileProcessed":271,"lastClockTimeProcessed":"2015-09-13 16:26:42","onTheFieldPlayers":[],"down":4,"yardLine":"CIN 31","yardsRemaining":9,"homeTeam":{"nflTeamId":"18","opponentAbbr":"CIN","score":13,"hasPossession":false,"gameScoreDisplay":"L 13-33"},"awayTeam":{"nflTeamId":"6","opponentAbbr":"@OAK","score":33,"hasPossession":false,"gameScoreDisplay":"W 33-13"}},"2015091311":{"nflGameId":"2015091311","nflGameCenterUrl":"http:\/\/www.nfl.com\/gamecenter\/2015091311\/2015\/REG1\/titans@buccaneers","gameDateAndTime":"2015-09-13T13:25:00-07:00","isGameRosterLocked":true,"gameStatus":"game_closed","gameClock":"Final","gameQuarter":"END OF GAME","playStatusDisplay":"Raymond James Stadium","isOffenseInRedZone":false,"network":"CBS","lastStatFileProcessed":251,"lastClockTimeProcessed":"2015-09-13 16:30:57","onTheFieldPlayers":[],"down":2,"yardLine":"TB 45","yardsRemaining":5,"homeTeam":{"nflTeamId":"31","opponentAbbr":"TEN","score":14,"hasPossession":false,"gameScoreDisplay":"L 14-42"},"awayTeam":{"nflTeamId":"12","opponentAbbr":"@TB","score":42,"hasPossession":false,"gameScoreDisplay":"W 42-14"}},"2015091312":{"nflGameId":"2015091312","nflGameCenterUrl":"http:\/\/www.nfl.com\/gamecenter\/2015091312\/2015\/REG1\/giants@cowboys","gameDateAndTime":"2015-09-13T17:30:00-07:00","isGameRosterLocked":true,"gameStatus":"game_closed","gameClock":"Final","gameQuarter":"END OF GAME","playStatusDisplay":"AT&T Stadium","isOffenseInRedZone":false,"network":"NBC","lastStatFileProcessed":391,"lastClockTimeProcessed":"2015-09-13 20:44:39","onTheFieldPlayers":[],"down":1,"yardLine":"NYG 42","yardsRemaining":10,"homeTeam":{"nflTeamId":"8","opponentAbbr":"NYG","score":27,"hasPossession":false,"gameScoreDisplay":"W 27-26"},"awayTeam":{"nflTeamId":"23","opponentAbbr":"@DAL","score":26,"hasPossession":false,"gameScoreDisplay":"L 26-27"}},"2015091400":{"nflGameId":"2015091400","nflGameCenterUrl":"http:\/\/www.nfl.com\/gamecenter\/2015091400\/2015\/REG1\/eagles@falcons","gameDateAndTime":"2015-09-14T16:10:00-07:00","isGameRosterLocked":true,"gameStatus":"game_closed","gameClock":"Final","gameQuarter":"END OF GAME","playStatusDisplay":"Mercedes-Benz Stadium","isOffenseInRedZone":false,"network":"ESPN","lastStatFileProcessed":283,"lastClockTimeProcessed":"2015-09-14 19:13:20","onTheFieldPlayers":[],"down":4,"yardLine":"PHI 32","yardsRemaining":13,"homeTeam":{"nflTeamId":"1","opponentAbbr":"PHI","score":26,"hasPossession":false,"gameScoreDisplay":"W 26-24"},"awayTeam":{"nflTeamId":"25","opponentAbbr":"@ATL","score":24,"hasPossession":false,"gameScoreDisplay":"L 24-26"}},"2015091401":{"nflGameId":"2015091401","nflGameCenterUrl":"http:\/\/www.nfl.com\/gamecenter\/2015091401\/2015\/REG1\/vikings@49ers","gameDateAndTime":"2015-09-14T19:20:00-07:00","isGameRosterLocked":true,"gameStatus":"game_closed","gameClock":"Final","gameQuarter":"END OF GAME","playStatusDisplay":"Levi's\u00ae Stadium","isOffenseInRedZone":false,"network":"ESPN","lastStatFileProcessed":351,"lastClockTimeProcessed":"2015-09-14 22:09:02","onTheFieldPlayers":[],"down":4,"yardLine":"MIN 33","yardsRemaining":7,"homeTeam":{"nflTeamId":"29","opponentAbbr":"MIN","score":20,"hasPossession":false,"gameScoreDisplay":"W 20-3"},"awayTeam":{"nflTeamId":"20","opponentAbbr":"@SF","score":3,"hasPossession":false,"gameScoreDisplay":"L 3-20"}}}}