{"week":"2012-4","homeTeamStats":{"id":13,"playerNflIds":[],"pointsFirstQuarter":14,"pointsSecondQuarter":0,"pointsThirdQuarter":14,"pointsFourthQuarter":10,"pointsOverTime":0,"pointsTotal":38,"firstDowns":16,"totalYards":297,"passingYards":202,"rushingYards":95,"penalties":1,"penaltyYards":3,"turnovers":0,"punts":6,"puntYards":259,"timeOfPossessionSeconds":1946},"awayTeamStats":{"id":12,"playerNflIds":[],"pointsFirstQuarter":0,"pointsSecondQuarter":7,"pointsThirdQuarter":0,"pointsFourthQuarter":7,"pointsOverTime":0,"pointsTotal":14,"firstDowns":17,"totalYards":325,"passingYards":167,"rushingYards":158,"penalties":7,"penaltyYards":73,"turnovers":3,"punts":7,"puntYards":326,"timeOfPossessionSeconds":1654}}