{"week":"2013-13","homeTeamStats":{"id":3,"playerNflIds":[],"pointsFirstQuarter":14,"pointsSecondQuarter":3,"pointsThirdQuarter":7,"pointsFourthQuarter":7,"pointsOverTime":0,"pointsTotal":31,"firstDowns":18,"totalYards":405,"passingYards":210,"rushingYards":195,"penalties":6,"penaltyYards":49,"turnovers":2,"punts":7,"puntYards":299,"timeOfPossessionSeconds":1491},"awayTeamStats":{"id":1,"playerNflIds":[],"pointsFirstQuarter":7,"pointsSecondQuarter":10,"pointsThirdQuarter":7,"pointsFourthQuarter":7,"pointsOverTime":3,"pointsTotal":34,"firstDowns":26,"totalYards":423,"passingYards":272,"rushingYards":151,"penalties":8,"penaltyYards":75,"turnovers":1,"punts":7,"puntYards":278,"timeOfPossessionSeconds":2289}}