{"week":"2014-13","homeTeamStats":{"id":13,"playerNflIds":[],"pointsFirstQuarter":14,"pointsSecondQuarter":10,"pointsThirdQuarter":7,"pointsFourthQuarter":14,"pointsOverTime":0,"pointsTotal":45,"firstDowns":24,"totalYards":457,"passingYards":358,"rushingYards":99,"penalties":5,"penaltyYards":40,"turnovers":1,"punts":3,"puntYards":137,"timeOfPossessionSeconds":1996},"awayTeamStats":{"id":12,"playerNflIds":[],"pointsFirstQuarter":0,"pointsSecondQuarter":0,"pointsThirdQuarter":14,"pointsFourthQuarter":7,"pointsOverTime":0,"pointsTotal":21,"firstDowns":19,"totalYards":320,"passingYards":237,"rushingYards":83,"penalties":6,"penaltyYards":66,"turnovers":4,"punts":5,"puntYards":226,"timeOfPossessionSeconds":1604}}