{"week":"2015-16","homeTeamStats":{"id":18,"playerNflIds":[],"pointsFirstQuarter":7,"pointsSecondQuarter":3,"pointsThirdQuarter":2,"pointsFourthQuarter":8,"pointsOverTime":3,"pointsTotal":23,"firstDowns":14,"totalYards":281,"passingYards":175,"rushingYards":106,"penalties":16,"penaltyYards":121,"turnovers":1,"punts":8,"puntYards":400,"timeOfPossessionSeconds":2001},"awayTeamStats":{"id":28,"playerNflIds":[],"pointsFirstQuarter":7,"pointsSecondQuarter":10,"pointsThirdQuarter":0,"pointsFourthQuarter":3,"pointsOverTime":0,"pointsTotal":20,"firstDowns":19,"totalYards":343,"passingYards":271,"rushingYards":72,"penalties":9,"penaltyYards":75,"turnovers":1,"punts":5,"puntYards":214,"timeOfPossessionSeconds":2104}}