{"week":"2016-3","homeTeamStats":{"id":15,"playerNflIds":[],"pointsFirstQuarter":0,"pointsSecondQuarter":7,"pointsThirdQuarter":7,"pointsFourthQuarter":3,"pointsOverTime":0,"pointsTotal":17,"firstDowns":14,"totalYards":216,"passingYards":168,"rushingYards":48,"penalties":7,"penaltyYards":75,"turnovers":3,"punts":6,"puntYards":249,"timeOfPossessionSeconds":1734},"awayTeamStats":{"id":2,"playerNflIds":[],"pointsFirstQuarter":7,"pointsSecondQuarter":6,"pointsThirdQuarter":3,"pointsFourthQuarter":3,"pointsOverTime":0,"pointsTotal":19,"firstDowns":18,"totalYards":283,"passingYards":199,"rushingYards":84,"penalties":8,"penaltyYards":58,"turnovers":3,"punts":5,"puntYards":243,"timeOfPossessionSeconds":1866}}