{"week":"2016-16","homeTeamStats":{"id":22,"playerNflIds":[],"pointsFirstQuarter":7,"pointsSecondQuarter":6,"pointsThirdQuarter":15,"pointsFourthQuarter":3,"pointsOverTime":0,"pointsTotal":31,"firstDowns":25,"totalYards":417,"passingYards":294,"rushingYards":123,"penalties":7,"penaltyYards":59,"turnovers":0,"punts":3,"puntYards":124,"timeOfPossessionSeconds":1896},"awayTeamStats":{"id":31,"playerNflIds":[],"pointsFirstQuarter":0,"pointsSecondQuarter":7,"pointsThirdQuarter":14,"pointsFourthQuarter":3,"pointsOverTime":0,"pointsTotal":24,"firstDowns":23,"totalYards":349,"passingYards":260,"rushingYards":89,"penalties":7,"penaltyYards":63,"turnovers":2,"punts":3,"puntYards":153,"timeOfPossessionSeconds":1704}}