{"week":"2017-4","homeTeamStats":{"id":16,"playerNflIds":[],"pointsFirstQuarter":0,"pointsSecondQuarter":7,"pointsThirdQuarter":10,"pointsFourthQuarter":12,"pointsOverTime":0,"pointsTotal":29,"firstDowns":29,"totalYards":429,"passingYards":261,"rushingYards":168,"penalties":3,"penaltyYards":15,"turnovers":0,"punts":3,"puntYards":105,"timeOfPossessionSeconds":2229},"awayTeamStats":{"id":32,"playerNflIds":[],"pointsFirstQuarter":10,"pointsSecondQuarter":0,"pointsThirdQuarter":7,"pointsFourthQuarter":3,"pointsOverTime":0,"pointsTotal":20,"firstDowns":15,"totalYards":331,"passingYards":220,"rushingYards":111,"penalties":7,"penaltyYards":44,"turnovers":1,"punts":4,"puntYards":169,"timeOfPossessionSeconds":1371}}