{"week":"2017-2","homeTeamStats":{"id":4,"playerNflIds":[],"pointsFirstQuarter":3,"pointsSecondQuarter":3,"pointsThirdQuarter":0,"pointsFourthQuarter":3,"pointsOverTime":0,"pointsTotal":9,"firstDowns":19,"totalYards":255,"passingYards":178,"rushingYards":77,"penalties":6,"penaltyYards":40,"turnovers":0,"punts":6,"puntYards":249,"timeOfPossessionSeconds":2333},"awayTeamStats":{"id":3,"playerNflIds":[],"pointsFirstQuarter":0,"pointsSecondQuarter":0,"pointsThirdQuarter":0,"pointsFourthQuarter":3,"pointsOverTime":0,"pointsTotal":3,"firstDowns":10,"totalYards":176,"passingYards":107,"rushingYards":69,"penalties":5,"penaltyYards":44,"turnovers":0,"punts":6,"puntYards":297,"timeOfPossessionSeconds":1267}}