{"week":"2018-9","homeTeamStats":{"id":30,"playerNflIds":[],"pointsFirstQuarter":7,"pointsSecondQuarter":3,"pointsThirdQuarter":0,"pointsFourthQuarter":7,"pointsOverTime":0,"pointsTotal":17,"firstDowns":25,"totalYards":356,"passingYards":202,"rushingYards":154,"penalties":10,"penaltyYards":83,"turnovers":1,"punts":6,"puntYards":317,"timeOfPossessionSeconds":2141},"awayTeamStats":{"id":28,"playerNflIds":[],"pointsFirstQuarter":6,"pointsSecondQuarter":13,"pointsThirdQuarter":0,"pointsFourthQuarter":6,"pointsOverTime":0,"pointsTotal":25,"firstDowns":18,"totalYards":375,"passingYards":215,"rushingYards":160,"penalties":12,"penaltyYards":105,"turnovers":0,"punts":6,"puntYards":258,"timeOfPossessionSeconds":1459}}