{"week":"2018-10","homeTeamStats":{"id":27,"playerNflIds":[],"pointsFirstQuarter":21,"pointsSecondQuarter":10,"pointsThirdQuarter":14,"pointsFourthQuarter":7,"pointsOverTime":0,"pointsTotal":52,"firstDowns":25,"totalYards":457,"passingYards":319,"rushingYards":138,"penalties":1,"penaltyYards":24,"turnovers":0,"punts":2,"puntYards":80,"timeOfPossessionSeconds":1835},"awayTeamStats":{"id":4,"playerNflIds":[],"pointsFirstQuarter":7,"pointsSecondQuarter":7,"pointsThirdQuarter":0,"pointsFourthQuarter":7,"pointsOverTime":0,"pointsTotal":21,"firstDowns":18,"totalYards":242,"passingYards":147,"rushingYards":95,"penalties":5,"penaltyYards":42,"turnovers":2,"punts":5,"puntYards":205,"timeOfPossessionSeconds":1765}}