{"2012110100":{"home":{"score":{"1":7,"2":3,"3":0,"4":21,"5":0,"T":31},"abbr":"SD","to":2,"stats":{"passing":{"00-0022942":{"name":"P.Rivers","att":20,"cmp":18,"yds":220,"tds":2,"ints":1,"twopta":0,"twoptm":0}},"rushing":{"00-0027864":{"name":"R.Mathews","att":13,"yds":67,"tds":0,"lng":31,"lngtd":0,"twopta":0,"twoptm":0},"00-0023437":{"name":"R.Brown","att":6,"yds":38,"tds":0,"lng":10,"lngtd":0,"twopta":0,"twoptm":0},"00-0025701":{"name":"J.Battle","att":4,"yds":20,"tds":0,"lng":11,"lngtd":0,"twopta":0,"twoptm":0},"00-0025524":{"name":"L.McClain","att":1,"yds":0,"tds":0,"lng":0,"lngtd":0,"twopta":0,"twoptm":0},"00-0022942":{"name":"P.Rivers","att":2,"yds":-2,"tds":0,"lng":-1,"lngtd":0,"twopta":0,"twoptm":0}},"receiving":{"00-0023437":{"name":"R.Brown","rec":5,"yds":35,"tds":0,"lng":9,"lngtd":0,"twopta":0,"twoptm":0},"00-0022414":{"name":"M.Floyd","rec":4,"yds":48,"tds":1,"lng":16,"lngtd":13,"twopta":0,"twoptm":0},"00-0027912":{"name":"D.Alexander","rec":3,"yds":61,"tds":0,"lng":30,"lngtd":0,"twopta":0,"twoptm":0},"00-0021547":{"name":"A.Gates","rec":3,"yds":43,"tds":1,"lng":21,"lngtd":14,"twopta":0,"twoptm":0},"00-0027864":{"name":"R.Mathews","rec":2,"yds":5,"tds":0,"lng":6,"lngtd":0,"twopta":0,"twoptm":0},"00-0027581":{"name":"S.Ajirotutu","rec":1,"yds":28,"tds":0,"lng":28,"lngtd":0,"twopta":0,"twoptm":0}},"fumbles":{"00-0025424":{"name":"E.Weddle","tot":1,"rcv":0,"trcv":0,"yds":0,"lost":1},"00-0021381":{"name":"Q.Jammer","tot":0,"rcv":0,"trcv":1,"yds":0,"lost":0},"00-0022723":{"name":"S.Phillips","tot":0,"rcv":0,"trcv":1,"yds":0,"lost":0},"00-0027710":{"name":"D.Stuckey","tot":0,"rcv":0,"trcv":1,"yds":0,"lost":0}},"kicking":{"00-0023096":{"name":"N.Novak","fgm":1,"fga":1,"fgyds":25,"totpfg":3,"xpmade":4,"xpmissed":0,"xpa":4,"xpb":0,"xptot":4}},"punting":{"00-0022017":{"name":"M.Scifres","pts":2,"yds":69,"avg":35,"i20":2,"lng":38}},"kickret":{"00-0026745":{"name":"C.Brinkley","ret":1,"avg":24,"tds":0,"lng":24,"lngtd":0}},"puntret":{"00-0025424":{"name":"E.Weddle","ret":1,"avg":2,"tds":0,"lng":2,"lngtd":0}},"defense":{"00-0027682":{"name":"D.Butler","tkl":9,"ast":0,"sk":0,"int":0,"ffum":0},"00-0025424":{"name":"E.Weddle","tkl":7,"ast":0,"sk":0,"int":0,"ffum":0},"00-0023404":{"name":"A.Bigby","tkl":3,"ast":3,"sk":0,"int":0,"ffum":0},"00-0027988":{"name":"M.Gilchrist","tkl":5,"ast":0,"sk":0,"int":0,"ffum":0},"00-0015474":{"name":"T.Spikes","tkl":2,"ast":3,"sk":0,"int":0,"ffum":0},"00-0026167":{"name":"A.Cason","tkl":4,"ast":0,"sk":0,"int":0,"ffum":0},"00-0027956":{"name":"C.Liuget","tkl":3,"ast":1,"sk":0,"int":0,"ffum":0},"00-0021381":{"name":"Q.Jammer","tkl":3,"ast":1,"sk":0,"int":0,"ffum":0},"00-0029249":{"name":"M.Ingram","tkl":2,"ast":1,"sk":0,"int":0,"ffum":0},"00-0022139":{"name":"J.Johnson","tkl":2,"ast":0,"sk":1,"int":0,"ffum":1},"00-0022707":{"name":"D.Williams","tkl":2,"ast":0,"sk":0,"int":1,"ffum":1},"00-0022147":{"name":"A.Franklin","tkl":2,"ast":0,"sk":0,"int":0,"ffum":0},"00-0027082":{"name":"V.Martin","tkl":0,"ast":2,"sk":0,"int":0,"ffum":0},"00-0022169":{"name":"A.Garay","tkl":0,"ast":2,"sk":0,"int":0,"ffum":0},"00-0022723":{"name":"S.Phillips","tkl":1,"ast":0,"sk":0,"int":0,"ffum":0},"00-0027745":{"name":"C.Thomas","tkl":1,"ast":0,"sk":0,"int":0,"ffum":0},"00-0028027":{"name":"S.Wright","tkl":1,"ast":0,"sk":0,"int":0,"ffum":0},"00-0025521":{"name":"A.Barnes","tkl":1,"ast":0,"sk":0,"int":0,"ffum":0},"00-0026317":{"name":"C.Lynch","tkl":0,"ast":1,"sk":0,"int":0,"ffum":0},"00-0029256":{"name":"K.Reyes","tkl":0,"ast":1,"sk":0,"int":0,"ffum":0}},"team":{"totfd":18,"totyds":339,"pyds":216,"ryds":123,"pen":8,"penyds":54,"trnovr":2,"pt":2,"ptyds":69,"ptavg":35,"top":"28:29"}},"players":null},"away":{"score":{"1":0,"2":3,"3":3,"4":7,"5":0,"T":13},"abbr":"KC","to":2,"stats":{"passing":{"00-0023662":{"name":"M.Cassel","att":29,"cmp":19,"yds":181,"tds":0,"ints":1,"twopta":0,"twoptm":0}},"rushing":{"00-0026213":{"name":"J.Charles","att":12,"yds":39,"tds":0,"lng":15,"lngtd":0,"twopta":0,"twoptm":0},"00-0023662":{"name":"M.Cassel","att":6,"yds":37,"tds":0,"lng":14,"lngtd":0,"twopta":0,"twoptm":0},"00-0027651":{"name":"D.McCluster","att":4,"yds":17,"tds":0,"lng":13,"lngtd":0,"twopta":0,"twoptm":0},"00-0026367":{"name":"P.Hillis","att":7,"yds":14,"tds":0,"lng":11,"lngtd":0,"twopta":0,"twoptm":0},"00-0028202":{"name":"S.Draughn","att":1,"yds":6,"tds":1,"lng":6,"lngtd":6,"twopta":0,"twoptm":0}},"receiving":{"00-0025410":{"name":"D.Bowe","rec":8,"yds":79,"tds":0,"lng":14,"lngtd":0,"twopta":0,"twoptm":0},"00-0026213":{"name":"J.Charles","rec":3,"yds":27,"tds":0,"lng":22,"lngtd":0,"twopta":0,"twoptm":0},"00-0028202":{"name":"S.Draughn","rec":2,"yds":21,"tds":0,"lng":20,"lngtd":0,"twopta":0,"twoptm":0},"00-0027651":{"name":"D.McCluster","rec":2,"yds":17,"tds":0,"lng":12,"lngtd":0,"twopta":0,"twoptm":0},"00-0025529":{"name":"S.Breaston","rec":2,"yds":17,"tds":0,"lng":10,"lngtd":0,"twopta":0,"twoptm":0},"00-0027964":{"name":"J.Baldwin","rec":1,"yds":13,"tds":0,"lng":13,"lngtd":0,"twopta":0,"twoptm":0},"00-0026367":{"name":"P.Hillis","rec":1,"yds":7,"tds":0,"lng":7,"lngtd":0,"twopta":0,"twoptm":0}},"fumbles":{"00-0025410":{"name":"D.Bowe","tot":1,"rcv":0,"trcv":0,"yds":0,"lost":1},"00-0023662":{"name":"M.Cassel","tot":1,"rcv":0,"trcv":0,"yds":0,"lost":1},"00-0027651":{"name":"D.McCluster","tot":1,"rcv":0,"trcv":0,"yds":0,"lost":1},"00-0027639":{"name":"C.Greenwood","tot":0,"rcv":0,"trcv":1,"yds":0,"lost":0}},"kicking":{"00-0026968":{"name":"R.Succop","fgm":2,"fga":3,"fgyds":49,"totpfg":6,"xpmade":1,"xpmissed":0,"xpa":1,"xpb":0,"xptot":1}},"punting":{"00-0023534":{"name":"D.Colquitt","pts":1,"yds":43,"avg":41,"i20":0,"lng":43}},"kickret":{"00-0028202":{"name":"S.Draughn","ret":4,"avg":20,"tds":0,"lng":29,"lngtd":0}},"puntret":{"00-0027651":{"name":"D.McCluster","ret":1,"avg":0,"tds":0,"lng":0,"lngtd":0}},"defense":{"00-0027660":{"name":"J.Arenas","tkl":8,"ast":1,"sk":0,"int":0,"ffum":0},"00-0024235":{"name":"T.Hali","tkl":6,"ast":3,"sk":1,"int":0,"ffum":0},"00-0028008":{"name":"J.Houston","tkl":6,"ast":3,"sk":0,"int":0,"ffum":0},"00-0027858":{"name":"E.Berry","tkl":6,"ast":2,"sk":0,"int":1,"ffum":0},"00-0023449":{"name":"D.Johnson","tkl":4,"ast":1,"sk":0,"int":0,"ffum":0},"00-0026016":{"name":"R.Pitoitua","tkl":2,"ast":2,"sk":0,"int":0,"ffum":0},"00-0026869":{"name":"J.Belcher","tkl":3,"ast":0,"sk":0,"int":0,"ffum":0},"00-0023539":{"name":"T.Daniels","tkl":1,"ast":1,"sk":0,"int":0,"ffum":0},"00-0029688":{"name":"D.Poe","tkl":0,"ast":2,"sk":0,"int":0,"ffum":0},"00-0026145":{"name":"G.Dorsey","tkl":1,"ast":0,"sk":0,"int":0,"ffum":0},"00-0027736":{"name":"K.Lewis","tkl":1,"ast":0,"sk":0,"int":0,"ffum":0},"00-0026175":{"name":"B.Flowers","tkl":1,"ast":0,"sk":0,"int":0,"ffum":0},"00-0023405":{"name":"A.Elam","tkl":1,"ast":0,"sk":0,"int":0,"ffum":0},"00-0026980":{"name":"T.Jackson","tkl":1,"ast":0,"sk":0,"int":0,"ffum":0},"00-0028024":{"name":"A.Bailey","tkl":0,"ast":1,"sk":0,"int":0,"ffum":0}},"team":{"totfd":21,"totyds":289,"pyds":176,"ryds":113,"pen":5,"penyds":37,"trnovr":4,"pt":1,"ptyds":43,"ptavg":41,"top":"31:31"}},"players":null},"drives":{"1":{"posteam":"SD","qtr":1,"redzone":true,"plays":{"36":{"sp":0,"qtr":1,"down":0,"time":"15:00","yrdln":"KC 35","ydstogo":0,"ydsnet":0,"posteam":"KC","desc":"R.Succop kicks 65 yards from KC 35 to end zone, Touchback.","note":"KICKOFF","players":{"0":[{"sequence":2,"clubcode":"SD","playerName":null,"statId":51,"yards":0}],"00-0026968":[{"sequence":1,"clubcode":"KC","playerName":"R.Succop","statId":44,"yards":65}]}},"50":{"sp":0,"qtr":1,"down":1,"time":"15:00","yrdln":"SD 20","ydstogo":10,"ydsnet":8,"posteam":"SD","desc":"(15:00) R.Mathews up the middle to SD 28 for 8 yards (E.Berry, T.Hali).","note":null,"players":{"00-0024235":[{"sequence":2,"clubcode":"KC","playerName":"T.Hali","statId":82,"yards":0}],"00-0027864":[{"sequence":1,"clubcode":"SD","playerName":"R.Mathews","statId":10,"yards":8}],"00-0027858":[{"sequence":3,"clubcode":"KC","playerName":"E.Berry","statId":80,"yards":0}]}},"71":{"sp":0,"qtr":1,"down":2,"time":"14:27","yrdln":"SD 28","ydstogo":2,"ydsnet":9,"posteam":"SD","desc":"(14:27) R.Mathews left end to SD 29 for 1 yard (G.Dorsey, D.Poe).","note":null,"players":{"00-0029688":[{"sequence":2,"clubcode":"KC","playerName":"D.Poe","statId":82,"yards":0}],"00-0027864":[{"sequence":1,"clubcode":"SD","playerName":"R.Mathews","statId":10,"yards":1}],"00-0026145":[{"sequence":3,"clubcode":"KC","playerName":"G.Dorsey","statId":80,"yards":0}]}},"92":{"sp":0,"qtr":1,"down":3,"time":"13:46","yrdln":"SD 29","ydstogo":1,"ydsnet":5,"posteam":"SD","desc":"(13:46) PENALTY on SD-J.Gaither, False Start, 4 yards, enforced at SD 29 - No Play.","note":"PENALTY","players":{"00-0025787":[{"sequence":1,"clubcode":"SD","playerName":"J.Gaither","statId":93,"yards":4}]}},"115":{"sp":0,"qtr":1,"down":3,"time":"13:20","yrdln":"SD 25","ydstogo":5,"ydsnet":33,"posteam":"SD","desc":"(13:20) (Shotgun) P.Rivers pass deep left to S.Ajirotutu to KC 47 for 28 yards (E.Berry).","note":null,"players":{"00-0022942":[{"sequence":1,"clubcode":"SD","playerName":"P.Rivers","statId":15,"yards":28},{"sequence":8,"clubcode":"SD","playerName":"P.Rivers","statId":111,"yards":28}],"00-0027581":[{"sequence":2,"clubcode":"SD","playerName":"S.Ajirotutu","statId":21,"yards":28},{"sequence":5,"clubcode":"SD","playerName":"S.Ajirotutu","statId":113,"yards":0},{"sequence":6,"clubcode":"SD","playerName":"S.Ajirotutu","statId":115,"yards":0}],"0":[{"sequence":4,"clubcode":"SD","playerName":null,"statId":4,"yards":0},{"sequence":7,"clubcode":"SD","playerName":null,"statId":6,"yards":0}],"00-0027858":[{"sequence":3,"clubcode":"KC","playerName":"E.Berry","statId":79,"yards":0}]}},"139":{"sp":0,"qtr":1,"down":1,"time":"12:35","yrdln":"KC 47","ydstogo":10,"ydsnet":54,"posteam":"SD","desc":"(12:35) P.Rivers pass deep left to A.Gates to KC 26 for 21 yards (K.Lewis).","note":null,"players":{"00-0027736":[{"sequence":4,"clubcode":"KC","playerName":"K.Lewis","statId":79,"yards":0}],"00-0022942":[{"sequence":1,"clubcode":"SD","playerName":"P.Rivers","statId":111,"yards":20},{"sequence":3,"clubcode":"SD","playerName":"P.Rivers","statId":15,"yards":21}],"0":[{"sequence":5,"clubcode":"SD","playerName":null,"statId":4,"yards":0}],"00-0021547":[{"sequence":2,"clubcode":"SD","playerName":"A.Gates","statId":115,"yards":0},{"sequence":6,"clubcode":"SD","playerName":"A.Gates","statId":21,"yards":21},{"sequence":7,"clubcode":"SD","playerName":"A.Gates","statId":113,"yards":1}]}},"163":{"sp":0,"qtr":1,"down":1,"time":"11:51","yrdln":"KC 26","ydstogo":10,"ydsnet":61,"posteam":"SD","desc":"(11:51) (Shotgun) P.Rivers pass short right to M.Floyd to KC 19 for 7 yards (J.Belcher).","note":null,"players":{"00-0026869":[{"sequence":6,"clubcode":"KC","playerName":"J.Belcher","statId":79,"yards":0}],"00-0022942":[{"sequence":4,"clubcode":"SD","playerName":"P.Rivers","statId":111,"yards":7},{"sequence":5,"clubcode":"SD","playerName":"P.Rivers","statId":15,"yards":7}],"00-0022414":[{"sequence":1,"clubcode":"SD","playerName":"M.Floyd","statId":113,"yards":0},{"sequence":2,"clubcode":"SD","playerName":"M.Floyd","statId":115,"yards":0},{"sequence":3,"clubcode":"SD","playerName":"M.Floyd","statId":21,"yards":7}]}},"187":{"sp":0,"qtr":1,"down":2,"time":"11:14","yrdln":"KC 19","ydstogo":3,"ydsnet":80,"posteam":"SD","desc":"(11:14) R.Mathews right end to KC 14 for 5 yards (J.Houston, D.Poe).","note":null,"players":{"00-0029688":[{"sequence":2,"clubcode":"KC","playerName":"D.Poe","statId":82,"yards":0}],"0":[{"sequence":3,"clubcode":"SD","playerName":null,"statId":3,"yards":0}],"00-0027864":[{"sequence":1,"clubcode":"SD","playerName":"R.Mathews","statId":10,"yards":5}],"00-0028008":[{"sequence":4,"clubcode":"KC","playerName":"J.Houston","statId":80,"yards":0}]}},"208":{"sp":1,"qtr":1,"down":1,"time":"10:31","yrdln":"KC 14","ydstogo":10,"ydsnet":80,"posteam":"SD","desc":"(10:31) (Shotgun) P.Rivers pass short left to A.Gates for 14 yards, TOUCHDOWN.","note":"TD","players":{"00-0022942":[{"sequence":1,"clubcode":"SD","playerName":"P.Rivers","statId":16,"yards":14},{"sequence":4,"clubcode":"SD","playerName":"P.Rivers","statId":111,"yards":13}],"0":[{"sequence":5,"clubcode":"SD","playerName":null,"statId":4,"yards":0}],"00-0021547":[{"sequence":2,"clubcode":"SD","playerName":"A.Gates","statId":115,"yards":0},{"sequence":3,"clubcode":"SD","playerName":"A.Gates","statId":22,"yards":14},{"sequence":6,"clubcode":"SD","playerName":"A.Gates","statId":113,"yards":1}]}},"228":{"sp":1,"qtr":1,"down":0,"time":"10:24","yrdln":"KC 2","ydstogo":0,"ydsnet":80,"posteam":"SD","desc":"N.Novak extra point is GOOD, Center-M.Windt, Holder-M.Scifres.","note":"XP","players":{"00-0023096":[{"sequence":1,"clubcode":"SD","playerName":"N.Novak","statId":72,"yards":0}]}}},"fds":4,"result":"Touchdown","penyds":-4,"ydsgained":84,"numplays":10,"postime":"4:36","start":{"qtr":1,"time":"15:00","yrdln":"SD 20","team":"SD"},"end":{"qtr":1,"time":"10:24","yrdln":"KC 14","team":"SD"}},"2":{"posteam":"KC","qtr":1,"redzone":true,"plays":{"244":{"sp":0,"qtr":1,"down":0,"time":"10:24","yrdln":"SD 35","ydstogo":0,"ydsnet":0,"posteam":"SD","desc":"N.Novak kicks 67 yards from SD 35 to KC -2. S.Draughn MUFFS catch, and recovers at KC 8. S.Draughn to KC 13 for 5 yards (J.Battle).","note":"KICKOFF","players":{"00-0028202":[{"sequence":4,"clubcode":"KC","playerName":"S.Draughn","statId":45,"yards":5}],"00-0023096":[{"sequence":1,"clubcode":"SD","playerName":"N.Novak","statId":43,"yards":67},{"sequence":3,"clubcode":"SD","playerName":"N.Novak","statId":42,"yards":0}],"00-0025701":[{"sequence":2,"clubcode":"SD","playerName":"J.Battle","statId":79,"yards":0}]}},"274":{"sp":0,"qtr":1,"down":1,"time":"10:19","yrdln":"KC 13","ydstogo":10,"ydsnet":8,"posteam":"KC","desc":"(10:19) J.Charles right end to KC 21 for 8 yards (T.Spikes, A.Bigby).","note":null,"players":{"00-0015474":[{"sequence":3,"clubcode":"SD","playerName":"T.Spikes","statId":80,"yards":0}],"00-0026213":[{"sequence":1,"clubcode":"KC","playerName":"J.Charles","statId":10,"yards":8}],"00-0023404":[{"sequence":2,"clubcode":"SD","playerName":"A.Bigby","statId":82,"yards":0}]}},"295":{"sp":0,"qtr":1,"down":2,"time":"09:42","yrdln":"KC 21","ydstogo":2,"ydsnet":12,"posteam":"KC","desc":"(9:42) M.Cassel scrambles left end to KC 25 for 4 yards (A.Cason).","note":null,"players":{"00-0023662":[{"sequence":2,"clubcode":"KC","playerName":"M.Cassel","statId":10,"yards":4}],"00-0026167":[{"sequence":3,"clubcode":"SD","playerName":"A.Cason","statId":79,"yards":0}],"0":[{"sequence":1,"clubcode":"KC","playerName":null,"statId":3,"yards":0}]}},"316":{"sp":0,"qtr":1,"down":1,"time":"09:03","yrdln":"KC 25","ydstogo":10,"ydsnet":14,"posteam":"KC","desc":"(9:03) J.Charles right tackle to KC 27 for 2 yards (A.Franklin, T.Spikes).","note":null,"players":{"00-0015474":[{"sequence":1,"clubcode":"SD","playerName":"T.Spikes","statId":82,"yards":0}],"00-0026213":[{"sequence":2,"clubcode":"KC","playerName":"J.Charles","statId":10,"yards":2}],"00-0022147":[{"sequence":3,"clubcode":"SD","playerName":"A.Franklin","statId":80,"yards":0}]}},"337":{"sp":0,"qtr":1,"down":2,"time":"08:23","yrdln":"KC 27","ydstogo":8,"ydsnet":14,"posteam":"KC","desc":"(8:23) M.Cassel pass incomplete short left to J.Charles (C.Liuget).","note":null,"players":{"00-0023662":[{"sequence":1,"clubcode":"KC","playerName":"M.Cassel","statId":112,"yards":0},{"sequence":3,"clubcode":"KC","playerName":"M.Cassel","statId":14,"yards":0}],"00-0026213":[{"sequence":4,"clubcode":"KC","playerName":"J.Charles","statId":115,"yards":0}],"00-0027956":[{"sequence":2,"clubcode":"SD","playerName":"C.Liuget","statId":85,"yards":0}]}},"359":{"sp":0,"qtr":1,"down":3,"time":"08:19","yrdln":"KC 27","ydstogo":8,"ydsnet":28,"posteam":"KC","desc":"(8:19) (Shotgun) M.Cassel pass short right to D.Bowe to KC 41 for 14 yards (S.Phillips, A.Bigby).","note":null,"players":{"00-0023662":[{"sequence":3,"clubcode":"KC","playerName":"M.Cassel","statId":15,"yards":14},{"sequence":4,"clubcode":"KC","playerName":"M.Cassel","statId":111,"yards":8}],"00-0025410":[{"sequence":1,"clubcode":"KC","playerName":"D.Bowe","statId":113,"yards":6},{"sequence":8,"clubcode":"KC","playerName":"D.Bowe","statId":21,"yards":14},{"sequence":9,"clubcode":"KC","playerName":"D.Bowe","statId":115,"yards":0}],"0":[{"sequence":2,"clubcode":"KC","playerName":null,"statId":6,"yards":0},{"sequence":7,"clubcode":"KC","playerName":null,"statId":4,"yards":0}],"00-0022723":[{"sequence":5,"clubcode":"SD","playerName":"S.Phillips","statId":80,"yards":0}],"00-0023404":[{"sequence":6,"clubcode":"SD","playerName":"A.Bigby","statId":82,"yards":0}]}},"383":{"sp":0,"qtr":1,"down":1,"time":"07:42","yrdln":"KC 41","ydstogo":10,"ydsnet":26,"posteam":"KC","desc":"(7:42) Direct snap to D.McCluster.  D.McCluster right end ran ob at KC 39 for -2 yards (Q.Jammer).","note":null,"players":{"00-0027651":[{"sequence":5,"clubcode":"KC","playerName":"D.McCluster","statId":10,"yards":-2}],"0":[{"sequence":4,"clubcode":"KC","playerName":null,"statId":95,"yards":-2}],"00-0021381":[{"sequence":1,"clubcode":"SD","playerName":"Q.Jammer","statId":120,"yards":0},{"sequence":2,"clubcode":"SD","playerName":"Q.Jammer","statId":402,"yards":2},{"sequence":3,"clubcode":"SD","playerName":"Q.Jammer","statId":79,"yards":0}]}},"406":{"sp":0,"qtr":1,"down":2,"time":"07:11","yrdln":"KC 39","ydstogo":12,"ydsnet":26,"posteam":"KC","desc":"(7:11) (Shotgun) M.Cassel pass incomplete short right to T.Copper.","note":null,"players":{"00-0022388":[{"sequence":2,"clubcode":"KC","playerName":"T.Copper","statId":115,"yards":0}],"00-0023662":[{"sequence":1,"clubcode":"KC","playerName":"M.Cassel","statId":112,"yards":8},{"sequence":3,"clubcode":"KC","playerName":"M.Cassel","statId":14,"yards":0}]}},"428":{"sp":0,"qtr":1,"down":3,"time":"07:07","yrdln":"KC 39","ydstogo":12,"ydsnet":38,"posteam":"KC","desc":"(7:07) (Shotgun) M.Cassel pass short right to D.McCluster to SD 49 for 12 yards (M.Gilchrist).","note":null,"players":{"00-0023662":[{"sequence":3,"clubcode":"KC","playerName":"M.Cassel","statId":15,"yards":12},{"sequence":5,"clubcode":"KC","playerName":"M.Cassel","statId":111,"yards":12}],"00-0027651":[{"sequence":2,"clubcode":"KC","playerName":"D.McCluster","statId":115,"yards":0},{"sequence":4,"clubcode":"KC","playerName":"D.McCluster","statId":113,"yards":0},{"sequence":7,"clubcode":"KC","playerName":"D.McCluster","statId":21,"yards":12}],"00-0027988":[{"sequence":8,"clubcode":"SD","playerName":"M.Gilchrist","statId":79,"yards":0}],"0":[{"sequence":1,"clubcode":"KC","playerName":null,"statId":4,"yards":0},{"sequence":6,"clubcode":"KC","playerName":null,"statId":6,"yards":0}]}},"452":{"sp":0,"qtr":1,"down":1,"time":"06:26","yrdln":"SD 49","ydstogo":10,"ydsnet":38,"posteam":"KC","desc":"(6:26) J.Charles left end to SD 49 for no gain (M.Ingram).","note":null,"players":{"00-0026213":[{"sequence":1,"clubcode":"KC","playerName":"J.Charles","statId":10,"yards":0}],"00-0029249":[{"sequence":2,"clubcode":"SD","playerName":"M.Ingram","statId":79,"yards":0}]}},"473":{"sp":0,"qtr":1,"down":2,"time":"05:42","yrdln":"SD 49","ydstogo":10,"ydsnet":38,"posteam":"KC","desc":"(5:42) (Shotgun) M.Cassel pass incomplete short left to J.Baldwin.","note":null,"players":{"00-0023662":[{"sequence":2,"clubcode":"KC","playerName":"M.Cassel","statId":14,"yards":0},{"sequence":3,"clubcode":"KC","playerName":"M.Cassel","statId":112,"yards":14}],"00-0027964":[{"sequence":1,"clubcode":"KC","playerName":"J.Baldwin","statId":115,"yards":0}]}},"495":{"sp":0,"qtr":1,"down":3,"time":"05:37","yrdln":"SD 49","ydstogo":10,"ydsnet":49,"posteam":"KC","desc":"(5:37) (Shotgun) M.Cassel pass short left to D.Bowe ran ob at SD 38 for 11 yards (E.Weddle).","note":null,"players":{"00-0023662":[{"sequence":1,"clubcode":"KC","playerName":"M.Cassel","statId":15,"yards":11},{"sequence":6,"clubcode":"KC","playerName":"M.Cassel","statId":111,"yards":11}],"00-0025410":[{"sequence":2,"clubcode":"KC","playerName":"D.Bowe","statId":113,"yards":0},{"sequence":5,"clubcode":"KC","playerName":"D.Bowe","statId":115,"yards":0},{"sequence":7,"clubcode":"KC","playerName":"D.Bowe","statId":21,"yards":11}],"00-0025424":[{"sequence":4,"clubcode":"SD","playerName":"E.Weddle","statId":79,"yards":0}],"0":[{"sequence":3,"clubcode":"KC","playerName":null,"statId":4,"yards":0},{"sequence":8,"clubcode":"KC","playerName":null,"statId":6,"yards":0}]}},"519":{"sp":0,"qtr":1,"down":1,"time":"05:08","yrdln":"SD 38","ydstogo":10,"ydsnet":51,"posteam":"KC","desc":"(5:08) P.Hillis up the middle to SD 36 for 2 yards (D.Butler, T.Spikes).","note":null,"players":{"00-0026367":[{"sequence":1,"clubcode":"KC","playerName":"P.Hillis","statId":10,"yards":2}],"00-0015474":[{"sequence":2,"clubcode":"SD","playerName":"T.Spikes","statId":82,"yards":0}],"00-0027682":[{"sequence":3,"clubcode":"SD","playerName":"D.Butler","statId":80,"yards":0}]}},"540":{"sp":0,"qtr":1,"down":2,"time":"04:33","yrdln":"SD 36","ydstogo":8,"ydsnet":58,"posteam":"KC","desc":"(4:33) M.Cassel pass short middle to D.Bowe to SD 29 for 7 yards (D.Butler).","note":null,"players":{"00-0023662":[{"sequence":5,"clubcode":"KC","playerName":"M.Cassel","statId":111,"yards":4},{"sequence":6,"clubcode":"KC","playerName":"M.Cassel","statId":15,"yards":7}],"00-0025410":[{"sequence":1,"clubcode":"KC","playerName":"D.Bowe","statId":113,"yards":3},{"sequence":3,"clubcode":"KC","playerName":"D.Bowe","statId":21,"yards":7},{"sequence":4,"clubcode":"KC","playerName":"D.Bowe","statId":115,"yards":0}],"00-0027682":[{"sequence":2,"clubcode":"SD","playerName":"D.Butler","statId":79,"yards":0}]}},"564":{"sp":0,"qtr":1,"down":3,"time":"03:54","yrdln":"SD 29","ydstogo":1,"ydsnet":59,"posteam":"KC","desc":"(3:54) P.Hillis right guard to SD 28 for 1 yard (A.Bigby, T.Spikes).","note":null,"players":{"00-0026367":[{"sequence":1,"clubcode":"KC","playerName":"P.Hillis","statId":10,"yards":1}],"00-0015474":[{"sequence":3,"clubcode":"SD","playerName":"T.Spikes","statId":82,"yards":0}],"0":[{"sequence":2,"clubcode":"KC","playerName":null,"statId":6,"yards":0},{"sequence":4,"clubcode":"KC","playerName":null,"statId":3,"yards":0}],"00-0023404":[{"sequence":5,"clubcode":"SD","playerName":"A.Bigby","statId":80,"yards":0}]}},"585":{"sp":0,"qtr":1,"down":1,"time":"03:15","yrdln":"SD 28","ydstogo":10,"ydsnet":54,"posteam":"KC","desc":"(3:15) J.Charles left end to SD 33 for -5 yards (E.Weddle).","note":null,"players":{"00-0026213":[{"sequence":3,"clubcode":"KC","playerName":"J.Charles","statId":10,"yards":-5}],"0":[{"sequence":2,"clubcode":"KC","playerName":null,"statId":95,"yards":-5}],"00-0025424":[{"sequence":1,"clubcode":"SD","playerName":"E.Weddle","statId":79,"yards":0},{"sequence":4,"clubcode":"SD","playerName":"E.Weddle","statId":120,"yards":0},{"sequence":5,"clubcode":"SD","playerName":"E.Weddle","statId":402,"yards":5}]}},"606":{"sp":0,"qtr":1,"down":2,"time":"02:32","yrdln":"SD 33","ydstogo":15,"ydsnet":54,"posteam":"KC","desc":"(2:32) M.Cassel pass incomplete short right to D.McCluster.","note":null,"players":{"00-0023662":[{"sequence":2,"clubcode":"KC","playerName":"M.Cassel","statId":14,"yards":0},{"sequence":3,"clubcode":"KC","playerName":"M.Cassel","statId":112,"yards":5}],"00-0027651":[{"sequence":1,"clubcode":"KC","playerName":"D.McCluster","statId":115,"yards":0}]}},"628":{"sp":0,"qtr":1,"down":3,"time":"02:27","yrdln":"SD 33","ydstogo":15,"ydsnet":64,"posteam":"KC","desc":"(2:27) (Shotgun) M.Cassel pass short right to D.Bowe to SD 23 for 10 yards (D.Williams, M.Ingram). FUMBLES (D.Williams), RECOVERED by SD-Q.Jammer at SD 22. Q.Jammer to SD 22 for no gain (E.Winston).","note":"FUMBLE","players":{"00-0023662":[{"sequence":2,"clubcode":"KC","playerName":"M.Cassel","statId":111,"yards":10},{"sequence":13,"clubcode":"KC","playerName":"M.Cassel","statId":15,"yards":10}],"00-0024281":[{"sequence":8,"clubcode":"KC","playerName":"E.Winston","statId":79,"yards":0}],"00-0029249":[{"sequence":6,"clubcode":"SD","playerName":"M.Ingram","statId":82,"yards":0}],"00-0022707":[{"sequence":5,"clubcode":"SD","playerName":"D.Williams","statId":91,"yards":0},{"sequence":10,"clubcode":"SD","playerName":"D.Williams","statId":80,"yards":0}],"00-0025410":[{"sequence":1,"clubcode":"KC","playerName":"D.Bowe","statId":115,"yards":0},{"sequence":3,"clubcode":"KC","playerName":"D.Bowe","statId":113,"yards":0},{"sequence":4,"clubcode":"KC","playerName":"D.Bowe","statId":21,"yards":10},{"sequence":11,"clubcode":"KC","playerName":"D.Bowe","statId":52,"yards":0},{"sequence":12,"clubcode":"KC","playerName":"D.Bowe","statId":106,"yards":0}],"0":[{"sequence":9,"clubcode":"KC","playerName":null,"statId":7,"yards":0}],"00-0021381":[{"sequence":7,"clubcode":"SD","playerName":"Q.Jammer","statId":59,"yards":0}]}}},"fds":5,"result":"Fumble","penyds":0,"ydsgained":64,"numplays":18,"postime":"8:06","start":{"qtr":1,"time":"10:24","yrdln":"KC 13","team":"KC"},"end":{"qtr":1,"time":"02:18","yrdln":"SD 33","team":"KC"}},"3":{"posteam":"SD","qtr":2,"redzone":true,"plays":{"669":{"sp":0,"qtr":1,"down":1,"time":"02:18","yrdln":"SD 22","ydstogo":10,"ydsnet":4,"posteam":"SD","desc":"(2:18) R.Mathews left tackle to SD 26 for 4 yards (D.Johnson).","note":null,"players":{"00-0023449":[{"sequence":1,"clubcode":"KC","playerName":"D.Johnson","statId":79,"yards":0}],"00-0027864":[{"sequence":2,"clubcode":"SD","playerName":"R.Mathews","statId":10,"yards":4}]}},"690":{"sp":0,"qtr":1,"down":2,"time":"01:37","yrdln":"SD 26","ydstogo":6,"ydsnet":8,"posteam":"SD","desc":"(1:37) R.Mathews left end to SD 30 for 4 yards (J.Belcher, T.Hali).","note":null,"players":{"00-0026869":[{"sequence":3,"clubcode":"KC","playerName":"J.Belcher","statId":80,"yards":0}],"00-0024235":[{"sequence":1,"clubcode":"KC","playerName":"T.Hali","statId":82,"yards":0}],"00-0027864":[{"sequence":2,"clubcode":"SD","playerName":"R.Mathews","statId":10,"yards":4}]}},"711":{"sp":0,"qtr":1,"down":3,"time":"00:52","yrdln":"SD 30","ydstogo":2,"ydsnet":13,"posteam":"SD","desc":"(:52) (Shotgun) PENALTY on KC-J.Houston, Neutral Zone Infraction, 5 yards, enforced at SD 30 - No Play.","note":"PENALTY","players":{"0":[{"sequence":2,"clubcode":"SD","playerName":null,"statId":5,"yards":0}],"00-0028008":[{"sequence":1,"clubcode":"KC","playerName":"J.Houston","statId":93,"yards":5}]}},"734":{"sp":0,"qtr":1,"down":1,"time":"00:35","yrdln":"SD 35","ydstogo":10,"ydsnet":8,"posteam":"SD","desc":"(:35) PENALTY on SD-J.Gaither, False Start, 5 yards, enforced at SD 35 - No Play.","note":"PENALTY","players":{"00-0025787":[{"sequence":1,"clubcode":"SD","playerName":"J.Gaither","statId":93,"yards":5}]}},"757":{"sp":0,"qtr":1,"down":1,"time":"00:10","yrdln":"SD 30","ydstogo":15,"ydsnet":19,"posteam":"SD","desc":"(:10) P.Rivers pass short left to D.Alexander pushed ob at SD 41 for 11 yards (J.Arenas).","note":null,"players":{"00-0022942":[{"sequence":4,"clubcode":"SD","playerName":"P.Rivers","statId":111,"yards":11},{"sequence":5,"clubcode":"SD","playerName":"P.Rivers","statId":15,"yards":11}],"00-0027660":[{"sequence":6,"clubcode":"KC","playerName":"J.Arenas","statId":79,"yards":0}],"00-0027912":[{"sequence":1,"clubcode":"SD","playerName":"D.Alexander","statId":113,"yards":0},{"sequence":2,"clubcode":"SD","playerName":"D.Alexander","statId":115,"yards":0},{"sequence":3,"clubcode":"SD","playerName":"D.Alexander","statId":21,"yards":11}]}},"802":{"sp":0,"qtr":2,"down":2,"time":"15:00","yrdln":"SD 41","ydstogo":4,"ydsnet":22,"posteam":"SD","desc":"(15:00) R.Mathews right end to SD 44 for 3 yards (B.Flowers, J.Houston).","note":null,"players":{"00-0026175":[{"sequence":1,"clubcode":"KC","playerName":"B.Flowers","statId":80,"yards":0}],"00-0027864":[{"sequence":3,"clubcode":"SD","playerName":"R.Mathews","statId":10,"yards":3}],"00-0028008":[{"sequence":2,"clubcode":"KC","playerName":"J.Houston","statId":82,"yards":0}]}},"823":{"sp":0,"qtr":2,"down":3,"time":"14:16","yrdln":"SD 44","ydstogo":1,"ydsnet":25,"posteam":"SD","desc":"(14:16) J.Battle right tackle to SD 47 for 3 yards (D.Johnson).","note":null,"players":{"00-0023449":[{"sequence":1,"clubcode":"KC","playerName":"D.Johnson","statId":79,"yards":0}],"0":[{"sequence":2,"clubcode":"SD","playerName":null,"statId":3,"yards":0},{"sequence":3,"clubcode":"SD","playerName":null,"statId":6,"yards":0}],"00-0025701":[{"sequence":4,"clubcode":"SD","playerName":"J.Battle","statId":10,"yards":3}]}},"844":{"sp":0,"qtr":2,"down":1,"time":"13:37","yrdln":"SD 47","ydstogo":10,"ydsnet":31,"posteam":"SD","desc":"(13:37) P.Rivers pass short right to R.Mathews to KC 47 for 6 yards (J.Houston).","note":null,"players":{"00-0022942":[{"sequence":1,"clubcode":"SD","playerName":"P.Rivers","statId":111,"yards":4},{"sequence":2,"clubcode":"SD","playerName":"P.Rivers","statId":15,"yards":6}],"00-0027864":[{"sequence":4,"clubcode":"SD","playerName":"R.Mathews","statId":115,"yards":0},{"sequence":5,"clubcode":"SD","playerName":"R.Mathews","statId":21,"yards":6},{"sequence":6,"clubcode":"SD","playerName":"R.Mathews","statId":113,"yards":2}],"00-0028008":[{"sequence":3,"clubcode":"KC","playerName":"J.Houston","statId":79,"yards":0}]}},"868":{"sp":0,"qtr":2,"down":2,"time":"12:51","yrdln":"KC 47","ydstogo":4,"ydsnet":33,"posteam":"SD","desc":"(12:51) (Shotgun) R.Mathews left end to KC 45 for 2 yards (J.Arenas).","note":null,"players":{"00-0027660":[{"sequence":2,"clubcode":"KC","playerName":"J.Arenas","statId":79,"yards":0}],"00-0027864":[{"sequence":1,"clubcode":"SD","playerName":"R.Mathews","statId":10,"yards":2}]}},"889":{"sp":0,"qtr":2,"down":3,"time":"12:07","yrdln":"KC 45","ydstogo":2,"ydsnet":63,"posteam":"SD","desc":"(12:07) (Shotgun) P.Rivers pass short left to D.Alexander to KC 15 for 30 yards (A.Elam, D.Johnson).","note":null,"players":{"00-0023449":[{"sequence":3,"clubcode":"KC","playerName":"D.Johnson","statId":82,"yards":0}],"00-0022942":[{"sequence":4,"clubcode":"SD","playerName":"P.Rivers","statId":111,"yards":5},{"sequence":6,"clubcode":"SD","playerName":"P.Rivers","statId":15,"yards":30}],"00-0023405":[{"sequence":2,"clubcode":"KC","playerName":"A.Elam","statId":80,"yards":0}],"0":[{"sequence":7,"clubcode":"SD","playerName":null,"statId":4,"yards":0},{"sequence":8,"clubcode":"SD","playerName":null,"statId":6,"yards":0}],"00-0027912":[{"sequence":1,"clubcode":"SD","playerName":"D.Alexander","statId":21,"yards":30},{"sequence":5,"clubcode":"SD","playerName":"D.Alexander","statId":113,"yards":25},{"sequence":9,"clubcode":"SD","playerName":"D.Alexander","statId":115,"yards":0}]}},"913":{"sp":0,"qtr":2,"down":1,"time":"11:18","yrdln":"KC 15","ydstogo":10,"ydsnet":61,"posteam":"SD","desc":"(11:18) R.Mathews left end to KC 17 for -2 yards (J.Arenas).","note":null,"players":{"00-0027660":[{"sequence":1,"clubcode":"KC","playerName":"J.Arenas","statId":402,"yards":2},{"sequence":2,"clubcode":"KC","playerName":"J.Arenas","statId":120,"yards":0},{"sequence":4,"clubcode":"KC","playerName":"J.Arenas","statId":79,"yards":0}],"0":[{"sequence":5,"clubcode":"SD","playerName":null,"statId":95,"yards":-2}],"00-0027864":[{"sequence":3,"clubcode":"SD","playerName":"R.Mathews","statId":10,"yards":-2}]}},"934":{"sp":0,"qtr":2,"down":2,"time":"10:40","yrdln":"KC 17","ydstogo":12,"ydsnet":64,"posteam":"SD","desc":"(10:40) (Shotgun) P.Rivers pass short left to R.Brown to KC 14 for 3 yards (T.Hali).","note":null,"players":{"00-0024235":[{"sequence":3,"clubcode":"KC","playerName":"T.Hali","statId":79,"yards":0}],"00-0022942":[{"sequence":2,"clubcode":"SD","playerName":"P.Rivers","statId":15,"yards":3},{"sequence":4,"clubcode":"SD","playerName":"P.Rivers","statId":111,"yards":2}],"00-0023437":[{"sequence":1,"clubcode":"SD","playerName":"R.Brown","statId":21,"yards":3},{"sequence":5,"clubcode":"SD","playerName":"R.Brown","statId":113,"yards":1},{"sequence":6,"clubcode":"SD","playerName":"R.Brown","statId":115,"yards":0}]}},"958":{"sp":0,"qtr":2,"down":0,"time":"09:56","yrdln":"","ydstogo":0,"ydsnet":64,"posteam":"","desc":"Timeout #1 by SD at 09:56.","note":"TIMEOUT","players":{"0":[{"sequence":1,"clubcode":"SD","playerName":null,"statId":68,"yards":0}]}},"975":{"sp":0,"qtr":2,"down":3,"time":"09:56","yrdln":"KC 14","ydstogo":9,"ydsnet":71,"posteam":"SD","desc":"(9:56) (Shotgun) P.Rivers pass short left to R.Brown to KC 7 for 7 yards (E.Berry, T.Daniels).","note":null,"players":{"00-0022942":[{"sequence":3,"clubcode":"SD","playerName":"P.Rivers","statId":15,"yards":7},{"sequence":4,"clubcode":"SD","playerName":"P.Rivers","statId":111,"yards":2}],"00-0023437":[{"sequence":1,"clubcode":"SD","playerName":"R.Brown","statId":115,"yards":0},{"sequence":2,"clubcode":"SD","playerName":"R.Brown","statId":113,"yards":5},{"sequence":5,"clubcode":"SD","playerName":"R.Brown","statId":21,"yards":7}],"0":[{"sequence":6,"clubcode":"SD","playerName":null,"statId":7,"yards":0}],"00-0027858":[{"sequence":8,"clubcode":"KC","playerName":"E.Berry","statId":80,"yards":0}],"00-0023539":[{"sequence":7,"clubcode":"KC","playerName":"T.Daniels","statId":82,"yards":0}]}},"999":{"sp":1,"qtr":2,"down":4,"time":"09:13","yrdln":"KC 7","ydstogo":2,"ydsnet":71,"posteam":"SD","desc":"(9:13) N.Novak 25 yard field goal is GOOD, Center-M.Windt, Holder-M.Scifres.","note":"FG","players":{"00-0023096":[{"sequence":1,"clubcode":"SD","playerName":"N.Novak","statId":70,"yards":25}]}}},"fds":3,"result":"Field Goal","penyds":0,"ydsgained":71,"numplays":15,"postime":"8:08","start":{"qtr":1,"time":"02:18","yrdln":"SD 22","team":"SD"},"end":{"qtr":1,"time":"09:10","yrdln":"KC 7","team":"SD"}},"4":{"posteam":"KC","qtr":2,"redzone":true,"plays":{"1018":{"sp":0,"qtr":2,"down":0,"time":"09:10","yrdln":"SD 35","ydstogo":0,"ydsnet":0,"posteam":"SD","desc":"N.Novak kicks 73 yards from SD 35 to KC -8. S.Draughn to KC 20 for 28 yards (A.Bigby).","note":"KICKOFF","players":{"00-0028202":[{"sequence":2,"clubcode":"KC","playerName":"S.Draughn","statId":45,"yards":28}],"00-0023096":[{"sequence":1,"clubcode":"SD","playerName":"N.Novak","statId":43,"yards":73}],"00-0023404":[{"sequence":3,"clubcode":"SD","playerName":"A.Bigby","statId":79,"yards":0}]}},"1040":{"sp":0,"qtr":2,"down":1,"time":"09:05","yrdln":"KC 20","ydstogo":10,"ydsnet":0,"posteam":"KC","desc":"(9:05) J.Charles right tackle to KC 20 for no gain (A.Franklin, A.Bigby).","note":null,"players":{"00-0026213":[{"sequence":3,"clubcode":"KC","playerName":"J.Charles","statId":10,"yards":0}],"00-0022147":[{"sequence":2,"clubcode":"SD","playerName":"A.Franklin","statId":80,"yards":0}],"00-0023404":[{"sequence":1,"clubcode":"SD","playerName":"A.Bigby","statId":82,"yards":0}]}},"1061":{"sp":0,"qtr":2,"down":2,"time":"08:21","yrdln":"KC 20","ydstogo":10,"ydsnet":8,"posteam":"KC","desc":"(8:21) M.Cassel scrambles up the middle to KC 28 for 8 yards (D.Butler).","note":null,"players":{"00-0023662":[{"sequence":2,"clubcode":"KC","playerName":"M.Cassel","statId":10,"yards":8}],"00-0027682":[{"sequence":1,"clubcode":"SD","playerName":"D.Butler","statId":79,"yards":0}]}},"1082":{"sp":0,"qtr":2,"down":0,"time":"07:38","yrdln":"","ydstogo":0,"ydsnet":8,"posteam":"","desc":"Timeout #1 by KC at 07:38.","note":"TIMEOUT","players":{"0":[{"sequence":1,"clubcode":"KC","playerName":null,"statId":68,"yards":0}]}},"1099":{"sp":0,"qtr":2,"down":3,"time":"07:38","yrdln":"KC 28","ydstogo":2,"ydsnet":17,"posteam":"KC","desc":"(7:38) (Shotgun) M.Cassel pass short left to D.Bowe to KC 37 for 9 yards (A.Cason).","note":null,"players":{"00-0023662":[{"sequence":2,"clubcode":"KC","playerName":"M.Cassel","statId":15,"yards":9},{"sequence":7,"clubcode":"KC","playerName":"M.Cassel","statId":111,"yards":9}],"00-0026167":[{"sequence":8,"clubcode":"SD","playerName":"A.Cason","statId":79,"yards":0}],"00-0025410":[{"sequence":1,"clubcode":"KC","playerName":"D.Bowe","statId":113,"yards":0},{"sequence":4,"clubcode":"KC","playerName":"D.Bowe","statId":21,"yards":9},{"sequence":5,"clubcode":"KC","playerName":"D.Bowe","statId":115,"yards":0}],"0":[{"sequence":3,"clubcode":"KC","playerName":null,"statId":4,"yards":0},{"sequence":6,"clubcode":"KC","playerName":null,"statId":6,"yards":0}]}},"1123":{"sp":0,"qtr":2,"down":1,"time":"07:04","yrdln":"KC 37","ydstogo":10,"ydsnet":21,"posteam":"KC","desc":"(7:04) J.Charles right tackle to KC 41 for 4 yards (C.Liuget, V.Martin).","note":null,"players":{"00-0026213":[{"sequence":3,"clubcode":"KC","playerName":"J.Charles","statId":10,"yards":4}],"00-0027956":[{"sequence":2,"clubcode":"SD","playerName":"C.Liuget","statId":80,"yards":0}],"00-0027082":[{"sequence":1,"clubcode":"SD","playerName":"V.Martin","statId":82,"yards":0}]}},"1144":{"sp":0,"qtr":2,"down":2,"time":"06:22","yrdln":"KC 41","ydstogo":6,"ydsnet":22,"posteam":"KC","desc":"(6:22) P.Hillis right end to KC 42 for 1 yard (E.Weddle, V.Martin).","note":null,"players":{"00-0026367":[{"sequence":1,"clubcode":"KC","playerName":"P.Hillis","statId":10,"yards":1}],"00-0025424":[{"sequence":2,"clubcode":"SD","playerName":"E.Weddle","statId":80,"yards":0}],"00-0027082":[{"sequence":3,"clubcode":"SD","playerName":"V.Martin","statId":82,"yards":0}]}},"1165":{"sp":0,"qtr":2,"down":3,"time":"05:43","yrdln":"KC 42","ydstogo":5,"ydsnet":27,"posteam":"KC","desc":"(5:43) (Shotgun) M.Cassel pass incomplete deep right to D.Bowe. PENALTY on SD-A.Barnes, Neutral Zone Infraction, 5 yards, enforced at KC 42 - No Play.","note":"PENALTY","players":{"0":[{"sequence":2,"clubcode":"KC","playerName":null,"statId":5,"yards":0}],"00-0025521":[{"sequence":1,"clubcode":"SD","playerName":"A.Barnes","statId":93,"yards":5}]}},"1198":{"sp":0,"qtr":2,"down":1,"time":"05:37","yrdln":"KC 47","ydstogo":10,"ydsnet":40,"posteam":"KC","desc":"(5:37) (Shotgun) Direct snap to D.McCluster.  D.McCluster right end to SD 40 for 13 yards (A.Bigby).","note":null,"players":{"00-0027651":[{"sequence":2,"clubcode":"KC","playerName":"D.McCluster","statId":10,"yards":13}],"0":[{"sequence":1,"clubcode":"KC","playerName":null,"statId":3,"yards":0}],"00-0023404":[{"sequence":3,"clubcode":"SD","playerName":"A.Bigby","statId":79,"yards":0}]}},"1225":{"sp":0,"qtr":2,"down":1,"time":"04:55","yrdln":"SD 40","ydstogo":10,"ydsnet":43,"posteam":"KC","desc":"(4:55) (Shotgun) M.Cassel pass short middle to J.Charles to SD 37 for 3 yards (J.Johnson, C.Liuget).","note":null,"players":{"00-0022139":[{"sequence":1,"clubcode":"SD","playerName":"J.Johnson","statId":80,"yards":0}],"00-0023662":[{"sequence":3,"clubcode":"KC","playerName":"M.Cassel","statId":15,"yards":3},{"sequence":6,"clubcode":"KC","playerName":"M.Cassel","statId":111,"yards":3}],"00-0026213":[{"sequence":2,"clubcode":"KC","playerName":"J.Charles","statId":113,"yards":0},{"sequence":5,"clubcode":"KC","playerName":"J.Charles","statId":115,"yards":0},{"sequence":7,"clubcode":"KC","playerName":"J.Charles","statId":21,"yards":3}],"00-0027956":[{"sequence":4,"clubcode":"SD","playerName":"C.Liuget","statId":82,"yards":0}]}},"1249":{"sp":0,"qtr":2,"down":2,"time":"04:17","yrdln":"SD 37","ydstogo":7,"ydsnet":49,"posteam":"KC","desc":"(4:17) Direct snap to D.McCluster.  D.McCluster up the middle to SD 31 for 6 yards (C.Liuget).","note":null,"players":{"00-0027651":[{"sequence":1,"clubcode":"KC","playerName":"D.McCluster","statId":10,"yards":6}],"00-0027956":[{"sequence":2,"clubcode":"SD","playerName":"C.Liuget","statId":79,"yards":0}]}},"1272":{"sp":0,"qtr":2,"down":3,"time":"03:40","yrdln":"SD 31","ydstogo":1,"ydsnet":49,"posteam":"KC","desc":"(3:40) P.Hillis up the middle to SD 31 for no gain (D.Butler, A.Garay).","note":null,"players":{"00-0026367":[{"sequence":1,"clubcode":"KC","playerName":"P.Hillis","statId":10,"yards":0}],"00-0022169":[{"sequence":4,"clubcode":"SD","playerName":"A.Garay","statId":82,"yards":0}],"0":[{"sequence":2,"clubcode":"KC","playerName":null,"statId":7,"yards":0}],"00-0027682":[{"sequence":3,"clubcode":"SD","playerName":"D.Butler","statId":80,"yards":0}]}},"1293":{"sp":1,"qtr":2,"down":4,"time":"02:56","yrdln":"SD 31","ydstogo":1,"ydsnet":49,"posteam":"KC","desc":"(2:56) R.Succop 49 yard field goal is GOOD, Center-T.Gafford, Holder-D.Colquitt.","note":"FG","players":{"00-0026968":[{"sequence":1,"clubcode":"KC","playerName":"R.Succop","statId":70,"yards":49}]}}},"fds":3,"result":"Field Goal","penyds":5,"ydsgained":44,"numplays":13,"postime":"6:19","start":{"qtr":2,"time":"09:10","yrdln":"KC 20","team":"KC"},"end":{"qtr":2,"time":"02:51","yrdln":"SD 31","team":"KC"}},"5":{"posteam":"SD","qtr":2,"redzone":true,"plays":{"1312":{"sp":0,"qtr":2,"down":0,"time":"02:51","yrdln":"KC 35","ydstogo":0,"ydsnet":0,"posteam":"KC","desc":"R.Succop kicks 67 yards from KC 35 to SD -2. C.Brinkley to SD 22 for 24 yards (T.Copper). PENALTY on KC-J.Arenas, Unnecessary Roughness, 15 yards, enforced at SD 22. Penalty on KC-E.Jones, Unnecessary Roughness, declined.","note":"KICKOFF","players":{"00-0022388":[{"sequence":1,"clubcode":"KC","playerName":"T.Copper","statId":79,"yards":0}],"00-0026745":[{"sequence":4,"clubcode":"SD","playerName":"C.Brinkley","statId":45,"yards":24}],"00-0027660":[{"sequence":3,"clubcode":"KC","playerName":"J.Arenas","statId":93,"yards":15}],"00-0026968":[{"sequence":2,"clubcode":"KC","playerName":"R.Succop","statId":43,"yards":67}]}},"1345":{"sp":0,"qtr":2,"down":1,"time":"02:45","yrdln":"SD 37","ydstogo":10,"ydsnet":16,"posteam":"SD","desc":"(2:45) (Shotgun) P.Rivers pass deep middle to M.Floyd to KC 47 for 16 yards (J.Arenas).","note":null,"players":{"00-0022942":[{"sequence":2,"clubcode":"SD","playerName":"P.Rivers","statId":111,"yards":16},{"sequence":7,"clubcode":"SD","playerName":"P.Rivers","statId":15,"yards":16}],"00-0022414":[{"sequence":1,"clubcode":"SD","playerName":"M.Floyd","statId":21,"yards":16},{"sequence":3,"clubcode":"SD","playerName":"M.Floyd","statId":113,"yards":0},{"sequence":4,"clubcode":"SD","playerName":"M.Floyd","statId":115,"yards":0}],"00-0027660":[{"sequence":6,"clubcode":"KC","playerName":"J.Arenas","statId":79,"yards":0}],"0":[{"sequence":5,"clubcode":"SD","playerName":null,"statId":4,"yards":0}]}},"1369":{"sp":0,"qtr":2,"down":1,"time":"02:15","yrdln":"KC 47","ydstogo":10,"ydsnet":28,"posteam":"SD","desc":"(2:15) (Shotgun) P.Rivers pass short left to M.Floyd to KC 35 for 12 yards (J.Arenas).","note":null,"players":{"00-0022942":[{"sequence":2,"clubcode":"SD","playerName":"P.Rivers","statId":15,"yards":12},{"sequence":3,"clubcode":"SD","playerName":"P.Rivers","statId":111,"yards":12}],"00-0022414":[{"sequence":1,"clubcode":"SD","playerName":"M.Floyd","statId":21,"yards":12},{"sequence":6,"clubcode":"SD","playerName":"M.Floyd","statId":115,"yards":0},{"sequence":7,"clubcode":"SD","playerName":"M.Floyd","statId":113,"yards":0}],"00-0027660":[{"sequence":5,"clubcode":"KC","playerName":"J.Arenas","statId":79,"yards":0}],"0":[{"sequence":4,"clubcode":"SD","playerName":null,"statId":4,"yards":0}]}},"1410":{"sp":0,"qtr":2,"down":1,"time":"02:00","yrdln":"KC 35","ydstogo":10,"ydsnet":37,"posteam":"SD","desc":"(2:00) (Shotgun) P.Rivers pass short right to R.Brown to KC 26 for 9 yards (J.Arenas).","note":null,"players":{"00-0022942":[{"sequence":4,"clubcode":"SD","playerName":"P.Rivers","statId":15,"yards":9},{"sequence":5,"clubcode":"SD","playerName":"P.Rivers","statId":111,"yards":2}],"00-0023437":[{"sequence":1,"clubcode":"SD","playerName":"R.Brown","statId":113,"yards":7},{"sequence":2,"clubcode":"SD","playerName":"R.Brown","statId":21,"yards":9},{"sequence":3,"clubcode":"SD","playerName":"R.Brown","statId":115,"yards":0}],"00-0027660":[{"sequence":6,"clubcode":"KC","playerName":"J.Arenas","statId":79,"yards":0}]}},"1434":{"sp":0,"qtr":2,"down":2,"time":"01:36","yrdln":"KC 26","ydstogo":1,"ydsnet":43,"posteam":"SD","desc":"(1:36) (Shotgun) R.Brown up the middle to KC 20 for 6 yards (D.Johnson, J.Houston).","note":null,"players":{"00-0023449":[{"sequence":1,"clubcode":"KC","playerName":"D.Johnson","statId":80,"yards":0}],"00-0023437":[{"sequence":2,"clubcode":"SD","playerName":"R.Brown","statId":10,"yards":6}],"0":[{"sequence":4,"clubcode":"SD","playerName":null,"statId":3,"yards":0}],"00-0028008":[{"sequence":3,"clubcode":"KC","playerName":"J.Houston","statId":82,"yards":0}]}},"1455":{"sp":0,"qtr":2,"down":1,"time":"01:06","yrdln":"KC 20","ydstogo":10,"ydsnet":51,"posteam":"SD","desc":"(1:06) (Shotgun) P.Rivers pass short middle to A.Gates to KC 12 for 8 yards (D.Johnson, E.Berry).","note":null,"players":{"00-0023449":[{"sequence":1,"clubcode":"KC","playerName":"D.Johnson","statId":80,"yards":0}],"00-0022942":[{"sequence":4,"clubcode":"SD","playerName":"P.Rivers","statId":15,"yards":8},{"sequence":7,"clubcode":"SD","playerName":"P.Rivers","statId":111,"yards":8}],"00-0021547":[{"sequence":2,"clubcode":"SD","playerName":"A.Gates","statId":113,"yards":0},{"sequence":3,"clubcode":"SD","playerName":"A.Gates","statId":115,"yards":0},{"sequence":5,"clubcode":"SD","playerName":"A.Gates","statId":21,"yards":8}],"00-0027858":[{"sequence":6,"clubcode":"KC","playerName":"E.Berry","statId":82,"yards":0}]}},"1479":{"sp":0,"qtr":2,"down":2,"time":"00:45","yrdln":"KC 12","ydstogo":2,"ydsnet":55,"posteam":"SD","desc":"(:45) (Shotgun) R.Brown up the middle to KC 8 for 4 yards (J.Houston, J.Arenas).","note":null,"players":{"00-0023437":[{"sequence":4,"clubcode":"SD","playerName":"R.Brown","statId":10,"yards":4}],"00-0027660":[{"sequence":1,"clubcode":"KC","playerName":"J.Arenas","statId":82,"yards":0}],"0":[{"sequence":3,"clubcode":"SD","playerName":null,"statId":3,"yards":0}],"00-0028008":[{"sequence":2,"clubcode":"KC","playerName":"J.Houston","statId":80,"yards":0}]}},"1500":{"sp":0,"qtr":2,"down":0,"time":"00:40","yrdln":"","ydstogo":0,"ydsnet":55,"posteam":"","desc":"Timeout #2 by SD at 00:40.","note":"TIMEOUT","players":{"0":[{"sequence":1,"clubcode":"SD","playerName":null,"statId":68,"yards":0}]}},"1517":{"sp":0,"qtr":2,"down":1,"time":"00:40","yrdln":"KC 8","ydstogo":8,"ydsnet":55,"posteam":"SD","desc":"(:40) (Shotgun) P.Rivers pass incomplete short middle.","note":null,"players":{"00-0022942":[{"sequence":1,"clubcode":"SD","playerName":"P.Rivers","statId":112,"yards":8},{"sequence":2,"clubcode":"SD","playerName":"P.Rivers","statId":14,"yards":0}]}},"1539":{"sp":0,"qtr":2,"down":2,"time":"00:35","yrdln":"KC 8","ydstogo":8,"ydsnet":62,"posteam":"SD","desc":"(:35) (Shotgun) P.Rivers pass short left to R.Brown to KC 1 for 7 yards (J.Houston, E.Berry). KC-G.Dorsey was injured during the play.","note":null,"players":{"00-0022942":[{"sequence":4,"clubcode":"SD","playerName":"P.Rivers","statId":111,"yards":2},{"sequence":5,"clubcode":"SD","playerName":"P.Rivers","statId":15,"yards":7}],"00-0023437":[{"sequence":1,"clubcode":"SD","playerName":"R.Brown","statId":115,"yards":0},{"sequence":3,"clubcode":"SD","playerName":"R.Brown","statId":21,"yards":7},{"sequence":7,"clubcode":"SD","playerName":"R.Brown","statId":113,"yards":5}],"00-0027858":[{"sequence":2,"clubcode":"KC","playerName":"E.Berry","statId":82,"yards":0}],"00-0028008":[{"sequence":6,"clubcode":"KC","playerName":"J.Houston","statId":80,"yards":0}]}},"1566":{"sp":0,"qtr":2,"down":0,"time":"00:21","yrdln":"","ydstogo":0,"ydsnet":62,"posteam":"","desc":"Timeout #2 by KC at 00:21.","note":"TIMEOUT","players":{"0":[{"sequence":1,"clubcode":"KC","playerName":null,"statId":68,"yards":0}]}},"1583":{"sp":0,"qtr":2,"down":3,"time":"00:21","yrdln":"KC 1","ydstogo":1,"ydsnet":62,"posteam":"SD","desc":"(:21) P.Rivers pass short right intended for D.Rosario INTERCEPTED by E.Berry at KC 0. Touchback.","note":"INT","players":{"00-0022942":[{"sequence":1,"clubcode":"SD","playerName":"P.Rivers","statId":112,"yards":1},{"sequence":3,"clubcode":"SD","playerName":"P.Rivers","statId":19,"yards":0}],"00-0025542":[{"sequence":5,"clubcode":"SD","playerName":"D.Rosario","statId":115,"yards":0}],"0":[{"sequence":6,"clubcode":"SD","playerName":null,"statId":7,"yards":0}],"00-0027858":[{"sequence":2,"clubcode":"KC","playerName":"E.Berry","statId":25,"yards":0},{"sequence":4,"clubcode":"KC","playerName":"E.Berry","statId":85,"yards":0}]}}},"fds":4,"result":"Interception","penyds":0,"ydsgained":62,"numplays":12,"postime":"2:37","start":{"qtr":2,"time":"02:51","yrdln":"SD 37","team":"SD"},"end":{"qtr":2,"time":"00:14","yrdln":"KC 1","team":"SD"}},"6":{"posteam":"KC","qtr":2,"redzone":true,"plays":{"1606":{"sp":0,"qtr":2,"down":1,"time":"00:14","yrdln":"KC 20","ydstogo":10,"ydsnet":-1,"posteam":"KC","desc":"(:14) M.Cassel kneels, dead ball declared at KC 19 for -1 yards.","note":null,"players":{"00-0023662":[{"sequence":1,"clubcode":"KC","playerName":"M.Cassel","statId":10,"yards":-1}]}}},"fds":0,"result":"End of Half","penyds":0,"ydsgained":-1,"numplays":1,"postime":"0:14","start":{"qtr":2,"time":"00:14","yrdln":"KC 20","team":"KC"},"end":{"qtr":2,"time":"00:00","yrdln":"KC 20","team":"KC"}},"7":{"posteam":"KC","qtr":3,"redzone":true,"plays":{"1642":{"sp":0,"qtr":3,"down":0,"time":"15:00","yrdln":"SD 35","ydstogo":0,"ydsnet":9,"posteam":"SD","desc":"N.Novak kicks 68 yards from SD 35 to KC -3. S.Draughn to KC 26 for 29 yards (D.Stuckey, A.Bigby).","note":"KICKOFF","players":{"00-0027710":[{"sequence":4,"clubcode":"SD","playerName":"D.Stuckey","statId":80,"yards":0}],"00-0028202":[{"sequence":2,"clubcode":"KC","playerName":"S.Draughn","statId":45,"yards":29}],"00-0023096":[{"sequence":1,"clubcode":"SD","playerName":"N.Novak","statId":43,"yards":68}],"00-0023404":[{"sequence":3,"clubcode":"SD","playerName":"A.Bigby","statId":82,"yards":0}]}},"1664":{"sp":0,"qtr":3,"down":1,"time":"14:53","yrdln":"KC 26","ydstogo":10,"ydsnet":-1,"posteam":"KC","desc":"(14:53) J.Charles right tackle to KC 25 for -1 yards (D.Butler).","note":null,"players":{"00-0026213":[{"sequence":3,"clubcode":"KC","playerName":"J.Charles","statId":10,"yards":-1}],"0":[{"sequence":2,"clubcode":"KC","playerName":null,"statId":95,"yards":-1}],"00-0027682":[{"sequence":1,"clubcode":"SD","playerName":"D.Butler","statId":79,"yards":0},{"sequence":4,"clubcode":"SD","playerName":"D.Butler","statId":402,"yards":1},{"sequence":5,"clubcode":"SD","playerName":"D.Butler","statId":120,"yards":0}]}},"1685":{"sp":0,"qtr":3,"down":2,"time":"14:10","yrdln":"KC 25","ydstogo":11,"ydsnet":9,"posteam":"KC","desc":"(14:10) (Shotgun) M.Cassel pass short left to D.Bowe to KC 35 for 10 yards (A.Cason).","note":null,"players":{"00-0023662":[{"sequence":2,"clubcode":"KC","playerName":"M.Cassel","statId":111,"yards":-1},{"sequence":3,"clubcode":"KC","playerName":"M.Cassel","statId":15,"yards":10}],"00-0026167":[{"sequence":6,"clubcode":"SD","playerName":"A.Cason","statId":79,"yards":0}],"00-0025410":[{"sequence":1,"clubcode":"KC","playerName":"D.Bowe","statId":113,"yards":11},{"sequence":4,"clubcode":"KC","playerName":"D.Bowe","statId":115,"yards":0},{"sequence":5,"clubcode":"KC","playerName":"D.Bowe","statId":21,"yards":10}]}},"1709":{"sp":0,"qtr":3,"down":3,"time":"13:34","yrdln":"KC 35","ydstogo":1,"ydsnet":9,"posteam":"KC","desc":"(13:34) Direct snap to D.McCluster.  D.McCluster up the middle to KC 35 for no gain (D.Butler).","note":null,"players":{"00-0027651":[{"sequence":1,"clubcode":"KC","playerName":"D.McCluster","statId":10,"yards":0}],"0":[{"sequence":2,"clubcode":"KC","playerName":null,"statId":7,"yards":0}],"00-0027682":[{"sequence":3,"clubcode":"SD","playerName":"D.Butler","statId":79,"yards":0}]}},"1776":{"sp":0,"qtr":3,"down":4,"time":"12:41","yrdln":"KC 35","ydstogo":1,"ydsnet":9,"posteam":"KC","desc":"(12:41) D.Colquitt punts 43 yards to SD 22, Center-T.Gafford. E.Weddle to SD 24 for 2 yards (J.Brown). FUMBLES (J.Brown), RECOVERED by KC-C.Greenwood at SD 24. C.Greenwood to SD 24 for no gain (J.Battle).","note":"FUMBLE","players":{"00-0023534":[{"sequence":1,"clubcode":"KC","playerName":"D.Colquitt","statId":29,"yards":43}],"00-0025424":[{"sequence":4,"clubcode":"SD","playerName":"E.Weddle","statId":52,"yards":0},{"sequence":6,"clubcode":"SD","playerName":"E.Weddle","statId":33,"yards":2},{"sequence":7,"clubcode":"SD","playerName":"E.Weddle","statId":106,"yards":0}],"00-0028056":[{"sequence":3,"clubcode":"KC","playerName":"J.Brown","statId":79,"yards":0},{"sequence":8,"clubcode":"KC","playerName":"J.Brown","statId":91,"yards":0}],"00-0025701":[{"sequence":5,"clubcode":"SD","playerName":"J.Battle","statId":79,"yards":0}],"00-0027639":[{"sequence":2,"clubcode":"KC","playerName":"C.Greenwood","statId":59,"yards":0}]}}},"fds":0,"result":"Punt","penyds":0,"ydsgained":9,"numplays":5,"postime":"2:31","start":{"qtr":3,"time":"15:00","yrdln":"KC 26","team":"KC"},"end":{"qtr":3,"time":"12:29","yrdln":"KC 35","team":"KC"}},"8":{"posteam":"KC","qtr":3,"redzone":true,"plays":{"1818":{"sp":0,"qtr":3,"down":1,"time":"12:29","yrdln":"SD 24","ydstogo":10,"ydsnet":0,"posteam":"KC","desc":"(12:29) (Shotgun) M.Cassel pass incomplete deep right to D.Bowe.","note":null,"players":{"00-0023662":[{"sequence":1,"clubcode":"KC","playerName":"M.Cassel","statId":112,"yards":22},{"sequence":2,"clubcode":"KC","playerName":"M.Cassel","statId":14,"yards":0}],"00-0025410":[{"sequence":3,"clubcode":"KC","playerName":"D.Bowe","statId":115,"yards":0}]}},"1840":{"sp":0,"qtr":3,"down":2,"time":"12:23","yrdln":"SD 24","ydstogo":10,"ydsnet":3,"posteam":"KC","desc":"(12:23) (Shotgun) J.Charles up the middle to SD 21 for 3 yards (C.Liuget).","note":null,"players":{"00-0026213":[{"sequence":2,"clubcode":"KC","playerName":"J.Charles","statId":10,"yards":3}],"00-0027956":[{"sequence":1,"clubcode":"SD","playerName":"C.Liuget","statId":79,"yards":0}]}},"1861":{"sp":0,"qtr":3,"down":3,"time":"11:41","yrdln":"SD 21","ydstogo":7,"ydsnet":3,"posteam":"KC","desc":"(11:41) (Shotgun) M.Cassel pass incomplete deep right to D.Bowe.","note":null,"players":{"00-0023662":[{"sequence":1,"clubcode":"KC","playerName":"M.Cassel","statId":14,"yards":0},{"sequence":2,"clubcode":"KC","playerName":"M.Cassel","statId":112,"yards":21}],"00-0025410":[{"sequence":4,"clubcode":"KC","playerName":"D.Bowe","statId":115,"yards":0}],"0":[{"sequence":3,"clubcode":"KC","playerName":null,"statId":7,"yards":0}]}},"1883":{"sp":0,"qtr":3,"down":4,"time":"11:35","yrdln":"SD 21","ydstogo":7,"ydsnet":3,"posteam":"KC","desc":"(11:35) R.Succop 39 yard field goal is No Good, Wide Left, Center-T.Gafford, Holder-D.Colquitt.","note":"FGM","players":{"00-0026968":[{"sequence":1,"clubcode":"KC","playerName":"R.Succop","statId":69,"yards":39}]}}},"fds":0,"result":"Missed FG","penyds":0,"ydsgained":3,"numplays":4,"postime":"0:58","start":{"qtr":3,"time":"12:29","yrdln":"SD 24","team":"KC"},"end":{"qtr":3,"time":"11:31","yrdln":"SD 21","team":"KC"}},"9":{"posteam":"SD","qtr":3,"redzone":true,"plays":{"1903":{"sp":0,"qtr":3,"down":1,"time":"11:31","yrdln":"SD 29","ydstogo":10,"ydsnet":2,"posteam":"SD","desc":"(11:31) R.Mathews right end to SD 31 for 2 yards (J.Houston).","note":null,"players":{"00-0027864":[{"sequence":1,"clubcode":"SD","playerName":"R.Mathews","statId":10,"yards":2}],"00-0028008":[{"sequence":2,"clubcode":"KC","playerName":"J.Houston","statId":79,"yards":0}]}},"1924":{"sp":0,"qtr":3,"down":2,"time":"10:51","yrdln":"SD 31","ydstogo":8,"ydsnet":11,"posteam":"SD","desc":"(10:51) (Shotgun) P.Rivers pass short left to R.Brown to SD 40 for 9 yards (J.Arenas).","note":null,"players":{"00-0023437":[{"sequence":4,"clubcode":"SD","playerName":"R.Brown","statId":21,"yards":9},{"sequence":5,"clubcode":"SD","playerName":"R.Brown","statId":115,"yards":0},{"sequence":6,"clubcode":"SD","playerName":"R.Brown","statId":113,"yards":10}],"00-0022942":[{"sequence":2,"clubcode":"SD","playerName":"P.Rivers","statId":15,"yards":9},{"sequence":3,"clubcode":"SD","playerName":"P.Rivers","statId":111,"yards":-1}],"00-0027660":[{"sequence":7,"clubcode":"KC","playerName":"J.Arenas","statId":79,"yards":0}],"0":[{"sequence":1,"clubcode":"SD","playerName":"","statId":4,"yards":0}]}},"1948":{"sp":0,"qtr":3,"down":1,"time":"10:05","yrdln":"SD 40","ydstogo":10,"ydsnet":31,"posteam":"SD","desc":"(10:05) (Shotgun) P.Rivers pass short middle to D.Alexander to KC 40 for 20 yards (T.Daniels).","note":null,"players":{"00-0022942":[{"sequence":2,"clubcode":"SD","playerName":"P.Rivers","statId":15,"yards":20},{"sequence":3,"clubcode":"SD","playerName":"P.Rivers","statId":111,"yards":12}],"0":[{"sequence":1,"clubcode":"SD","playerName":"","statId":4,"yards":0}],"00-0023539":[{"sequence":7,"clubcode":"KC","playerName":"T.Daniels","statId":79,"yards":0}],"00-0027912":[{"sequence":4,"clubcode":"SD","playerName":"D.Alexander","statId":21,"yards":20},{"sequence":5,"clubcode":"SD","playerName":"D.Alexander","statId":115,"yards":0},{"sequence":6,"clubcode":"SD","playerName":"D.Alexander","statId":113,"yards":8}]}},"1972":{"sp":0,"qtr":3,"down":1,"time":"09:20","yrdln":"KC 40","ydstogo":10,"ydsnet":27,"posteam":"SD","desc":"(9:20) P.Rivers sacked at KC 44 for -4 yards (T.Hali).","note":null,"players":{"00-0024235":[{"sequence":2,"clubcode":"KC","playerName":"T.Hali","statId":83,"yards":-4},{"sequence":3,"clubcode":"KC","playerName":"T.Hali","statId":110,"yards":0},{"sequence":4,"clubcode":"KC","playerName":"T.Hali","statId":79,"yards":0},{"sequence":5,"clubcode":"KC","playerName":"T.Hali","statId":120,"yards":0},{"sequence":6,"clubcode":"KC","playerName":"T.Hali","statId":402,"yards":4}],"00-0022942":[{"sequence":1,"clubcode":"SD","playerName":"P.Rivers","statId":20,"yards":-4}]}},"1991":{"sp":0,"qtr":3,"down":2,"time":"08:42","yrdln":"KC 44","ydstogo":14,"ydsnet":26,"posteam":"SD","desc":"(8:42) (Shotgun) P.Rivers pass incomplete short left. PENALTY on SD-J.Gaither, Offensive Holding, 10 yards, enforced at KC 44 - No Play.","note":"PENALTY","players":{"00-0025787":[{"sequence":1,"clubcode":"SD","playerName":"J.Gaither","statId":93,"yards":10}]}},"2024":{"sp":0,"qtr":3,"down":2,"time":"08:34","yrdln":"SD 46","ydstogo":24,"ydsnet":16,"posteam":"SD","desc":"(8:34) (Shotgun) P.Rivers pass short right to R.Mathews to SD 45 for -1 yards (E.Berry).","note":null,"players":{"00-0022942":[{"sequence":1,"clubcode":"SD","playerName":"P.Rivers","statId":15,"yards":-1},{"sequence":2,"clubcode":"SD","playerName":"P.Rivers","statId":111,"yards":-5}],"00-0027864":[{"sequence":3,"clubcode":"SD","playerName":"R.Mathews","statId":21,"yards":-1},{"sequence":4,"clubcode":"SD","playerName":"R.Mathews","statId":115,"yards":0},{"sequence":5,"clubcode":"SD","playerName":"R.Mathews","statId":113,"yards":4}],"00-0027858":[{"sequence":6,"clubcode":"KC","playerName":"E.Berry","statId":79,"yards":0},{"sequence":7,"clubcode":"KC","playerName":"E.Berry","statId":120,"yards":0},{"sequence":8,"clubcode":"KC","playerName":"E.Berry","statId":402,"yards":1}]}},"2048":{"sp":0,"qtr":3,"down":3,"time":"07:54","yrdln":"SD 45","ydstogo":25,"ydsnet":26,"posteam":"SD","desc":"(7:54) (Shotgun) R.Brown up the middle to KC 45 for 10 yards (E.Berry).","note":null,"players":{"00-0023437":[{"sequence":2,"clubcode":"SD","playerName":"R.Brown","statId":10,"yards":10}],"0":[{"sequence":1,"clubcode":"SD","playerName":"","statId":7,"yards":0}],"00-0027858":[{"sequence":3,"clubcode":"KC","playerName":"E.Berry","statId":79,"yards":0}]}},"2069":{"sp":0,"qtr":3,"down":4,"time":"07:20","yrdln":"KC 45","ydstogo":15,"ydsnet":26,"posteam":"SD","desc":"(7:20) M.Scifres punts 38 yards to KC 7, Center-M.Windt, downed by SD-D.Stuckey.","note":"PUNT","players":{"00-0022017":[{"sequence":1,"clubcode":"SD","playerName":"M.Scifres","statId":29,"yards":38},{"sequence":2,"clubcode":"SD","playerName":"M.Scifres","statId":30,"yards":0}],"0":[{"sequence":3,"clubcode":"KC","playerName":"","statId":38,"yards":0}]}}},"fds":2,"result":"Punt","penyds":-10,"ydsgained":36,"numplays":8,"postime":"4:22","start":{"qtr":3,"time":"11:31","yrdln":"SD 29","team":"SD"},"end":{"qtr":3,"time":"07:09","yrdln":"KC 45","team":"SD"}},"10":{"posteam":"KC","qtr":3,"redzone":true,"plays":{"2089":{"sp":0,"qtr":3,"down":1,"time":"07:09","yrdln":"KC 7","ydstogo":10,"ydsnet":13,"posteam":"KC","desc":"(7:09) M.Cassel pass short right to D.Bowe to KC 20 for 13 yards (A.Bigby).","note":null,"players":{"00-0023662":[{"sequence":2,"clubcode":"KC","playerName":"M.Cassel","statId":15,"yards":13},{"sequence":3,"clubcode":"KC","playerName":"M.Cassel","statId":111,"yards":13}],"00-0025410":[{"sequence":4,"clubcode":"KC","playerName":"D.Bowe","statId":21,"yards":13},{"sequence":5,"clubcode":"KC","playerName":"D.Bowe","statId":115,"yards":0},{"sequence":6,"clubcode":"KC","playerName":"D.Bowe","statId":113,"yards":0}],"0":[{"sequence":1,"clubcode":"KC","playerName":"","statId":4,"yards":0}],"00-0023404":[{"sequence":7,"clubcode":"SD","playerName":"A.Bigby","statId":79,"yards":0}]}},"2113":{"sp":0,"qtr":3,"down":1,"time":"06:31","yrdln":"KC 20","ydstogo":10,"ydsnet":23,"posteam":"KC","desc":"(6:31) J.Charles up the middle to KC 30 for 10 yards (E.Weddle).","note":null,"players":{"00-0026213":[{"sequence":2,"clubcode":"KC","playerName":"J.Charles","statId":10,"yards":10}],"00-0025424":[{"sequence":3,"clubcode":"SD","playerName":"E.Weddle","statId":79,"yards":0}],"0":[{"sequence":1,"clubcode":"KC","playerName":"","statId":3,"yards":0}]}},"2134":{"sp":0,"qtr":3,"down":1,"time":"05:48","yrdln":"KC 30","ydstogo":10,"ydsnet":25,"posteam":"KC","desc":"(5:48) J.Charles right end to KC 32 for 2 yards (C.Thomas, K.Reyes).","note":null,"players":{"00-0026213":[{"sequence":1,"clubcode":"KC","playerName":"J.Charles","statId":10,"yards":2}],"00-0029256":[{"sequence":3,"clubcode":"SD","playerName":"K.Reyes","statId":82,"yards":0}],"00-0027745":[{"sequence":2,"clubcode":"SD","playerName":"C.Thomas","statId":80,"yards":0}]}},"2155":{"sp":0,"qtr":3,"down":2,"time":"05:01","yrdln":"KC 32","ydstogo":8,"ydsnet":40,"posteam":"KC","desc":"(5:01) J.Charles left end to KC 47 for 15 yards (E.Weddle).","note":null,"players":{"00-0026213":[{"sequence":2,"clubcode":"KC","playerName":"J.Charles","statId":10,"yards":15}],"00-0025424":[{"sequence":3,"clubcode":"SD","playerName":"E.Weddle","statId":79,"yards":0}],"0":[{"sequence":1,"clubcode":"KC","playerName":"","statId":3,"yards":0}]}},"2176":{"sp":0,"qtr":3,"down":1,"time":"04:24","yrdln":"KC 47","ydstogo":10,"ydsnet":54,"posteam":"KC","desc":"(4:24) M.Cassel scrambles up the middle to SD 39 for 14 yards (T.Spikes).","note":null,"players":{"00-0015474":[{"sequence":3,"clubcode":"SD","playerName":"T.Spikes","statId":79,"yards":0}],"00-0023662":[{"sequence":2,"clubcode":"KC","playerName":"M.Cassel","statId":10,"yards":14}],"0":[{"sequence":1,"clubcode":"KC","playerName":"","statId":3,"yards":0}]}},"2197":{"sp":0,"qtr":3,"down":1,"time":"03:38","yrdln":"SD 39","ydstogo":10,"ydsnet":65,"posteam":"KC","desc":"(3:38) P.Hillis right end to SD 28 for 11 yards (E.Weddle).","note":null,"players":{"00-0026367":[{"sequence":2,"clubcode":"KC","playerName":"P.Hillis","statId":10,"yards":11}],"00-0025424":[{"sequence":3,"clubcode":"SD","playerName":"E.Weddle","statId":79,"yards":0}],"0":[{"sequence":1,"clubcode":"KC","playerName":"","statId":3,"yards":0}]}},"2218":{"sp":0,"qtr":3,"down":1,"time":"02:59","yrdln":"SD 28","ydstogo":10,"ydsnet":62,"posteam":"KC","desc":"(2:59) P.Hillis left guard to SD 31 for -3 yards (M.Ingram).","note":null,"players":{"00-0026367":[{"sequence":1,"clubcode":"KC","playerName":"P.Hillis","statId":10,"yards":-3}],"00-0029249":[{"sequence":3,"clubcode":"SD","playerName":"M.Ingram","statId":79,"yards":0},{"sequence":4,"clubcode":"SD","playerName":"M.Ingram","statId":120,"yards":0},{"sequence":5,"clubcode":"SD","playerName":"M.Ingram","statId":402,"yards":3}],"0":[{"sequence":2,"clubcode":"KC","playerName":"","statId":95,"yards":-3}]}},"2239":{"sp":0,"qtr":3,"down":2,"time":"02:16","yrdln":"SD 31","ydstogo":13,"ydsnet":57,"posteam":"KC","desc":"(2:16) (Shotgun) PENALTY on KC-E.Winston, False Start, 5 yards, enforced at SD 31 - No Play.","note":"PENALTY","players":{"00-0024281":[{"sequence":1,"clubcode":"KC","playerName":"E.Winston","statId":93,"yards":5}]}},"2262":{"sp":0,"qtr":3,"down":2,"time":"01:50","yrdln":"SD 36","ydstogo":18,"ydsnet":57,"posteam":"KC","desc":"(1:50) (Shotgun) M.Cassel pass incomplete deep right to D.McCluster (D.Butler).","note":null,"players":{"00-0023662":[{"sequence":1,"clubcode":"KC","playerName":"M.Cassel","statId":14,"yards":0},{"sequence":4,"clubcode":"KC","playerName":"M.Cassel","statId":112,"yards":18}],"00-0027651":[{"sequence":2,"clubcode":"KC","playerName":"D.McCluster","statId":115,"yards":0}],"00-0027682":[{"sequence":3,"clubcode":"SD","playerName":"D.Butler","statId":85,"yards":0}]}},"2284":{"sp":0,"qtr":3,"down":3,"time":"01:44","yrdln":"SD 36","ydstogo":18,"ydsnet":70,"posteam":"KC","desc":"(1:44) (Shotgun) M.Cassel pass short right to J.Baldwin to SD 23 for 13 yards (S.Wright, Q.Jammer).","note":null,"players":{"00-0023662":[{"sequence":2,"clubcode":"KC","playerName":"M.Cassel","statId":15,"yards":13},{"sequence":3,"clubcode":"KC","playerName":"M.Cassel","statId":111,"yards":9}],"00-0027964":[{"sequence":4,"clubcode":"KC","playerName":"J.Baldwin","statId":21,"yards":13},{"sequence":5,"clubcode":"KC","playerName":"J.Baldwin","statId":115,"yards":0},{"sequence":6,"clubcode":"KC","playerName":"J.Baldwin","statId":113,"yards":4}],"0":[{"sequence":1,"clubcode":"KC","playerName":"","statId":7,"yards":0}],"00-0028027":[{"sequence":7,"clubcode":"SD","playerName":"S.Wright","statId":80,"yards":0}],"00-0021381":[{"sequence":8,"clubcode":"SD","playerName":"Q.Jammer","statId":82,"yards":0}]}},"2308":{"sp":1,"qtr":3,"down":4,"time":"00:58","yrdln":"SD 23","ydstogo":5,"ydsnet":70,"posteam":"KC","desc":"(:58) R.Succop 41 yard field goal is GOOD, Center-T.Gafford, Holder-D.Colquitt.","note":"FG","players":{"00-0026968":[{"sequence":1,"clubcode":"KC","playerName":"R.Succop","statId":70,"yards":41}]}}},"fds":5,"result":"Field Goal","penyds":-5,"ydsgained":75,"numplays":11,"postime":"6:16","start":{"qtr":3,"time":"07:09","yrdln":"KC 7","team":"KC"},"end":{"qtr":3,"time":"00:53","yrdln":"SD 23","team":"KC"}},"11":{"posteam":"SD","qtr":4,"redzone":true,"plays":{"2327":{"sp":0,"qtr":3,"down":0,"time":"00:53","yrdln":"KC 35","ydstogo":0,"ydsnet":0,"posteam":"KC","desc":"R.Succop kicks 71 yards from KC 35 to SD -6. C.Brinkley, Touchback.","note":"KICKOFF","players":{"0":[{"sequence":2,"clubcode":"SD","playerName":"","statId":51,"yards":0}],"00-0026968":[{"sequence":1,"clubcode":"KC","playerName":"R.Succop","statId":44,"yards":65}]}},"2345":{"sp":0,"qtr":3,"down":1,"time":"00:53","yrdln":"SD 20","ydstogo":10,"ydsnet":31,"posteam":"SD","desc":"(:53) R.Mathews up the middle to KC 49 for 31 yards (J.Arenas).","note":null,"players":{"00-0027660":[{"sequence":3,"clubcode":"KC","playerName":"J.Arenas","statId":79,"yards":0}],"0":[{"sequence":1,"clubcode":"SD","playerName":"","statId":3,"yards":0}],"00-0027864":[{"sequence":2,"clubcode":"SD","playerName":"R.Mathews","statId":10,"yards":31}]}},"2366":{"sp":0,"qtr":3,"down":1,"time":"00:08","yrdln":"KC 49","ydstogo":10,"ydsnet":42,"posteam":"SD","desc":"(:08) J.Battle left end to KC 38 for 11 yards (J.Belcher).","note":null,"players":{"00-0026869":[{"sequence":3,"clubcode":"KC","playerName":"J.Belcher","statId":79,"yards":0}],"0":[{"sequence":1,"clubcode":"SD","playerName":"","statId":3,"yards":0}],"00-0025701":[{"sequence":2,"clubcode":"SD","playerName":"J.Battle","statId":10,"yards":11}]}},"2387":{"sp":0,"qtr":3,"down":0,"time":"","yrdln":"","ydstogo":0,"ydsnet":42,"posteam":"","desc":"END QUARTER 3","note":null,"players":{}},"2403":{"sp":0,"qtr":4,"down":1,"time":"15:00","yrdln":"KC 38","ydstogo":10,"ydsnet":47,"posteam":"SD","desc":"(15:00) R.Mathews right guard to KC 33 for 5 yards (R.Pitoitua).","note":null,"players":{"00-0027864":[{"sequence":1,"clubcode":"SD","playerName":"R.Mathews","statId":10,"yards":5}],"00-0026016":[{"sequence":2,"clubcode":"KC","playerName":"R.Pitoitua","statId":79,"yards":0}]}},"2424":{"sp":0,"qtr":4,"down":2,"time":"14:23","yrdln":"KC 33","ydstogo":5,"ydsnet":49,"posteam":"SD","desc":"(14:23) R.Mathews left end to KC 31 for 2 yards (T.Hali, R.Pitoitua).","note":null,"players":{"00-0024235":[{"sequence":2,"clubcode":"KC","playerName":"T.Hali","statId":80,"yards":0}],"00-0027864":[{"sequence":1,"clubcode":"SD","playerName":"R.Mathews","statId":10,"yards":2}],"00-0026016":[{"sequence":3,"clubcode":"KC","playerName":"R.Pitoitua","statId":82,"yards":0}]}},"2445":{"sp":0,"qtr":4,"down":3,"time":"13:41","yrdln":"KC 31","ydstogo":3,"ydsnet":56,"posteam":"SD","desc":"(13:41) (Shotgun) R.Brown up the middle to KC 24 for 7 yards (T.Hali, A.Bailey).","note":null,"players":{"00-0024235":[{"sequence":4,"clubcode":"KC","playerName":"T.Hali","statId":80,"yards":0}],"00-0023437":[{"sequence":3,"clubcode":"SD","playerName":"R.Brown","statId":10,"yards":7}],"0":[{"sequence":1,"clubcode":"SD","playerName":"","statId":3,"yards":0},{"sequence":2,"clubcode":"SD","playerName":"","statId":6,"yards":0}],"00-0028024":[{"sequence":5,"clubcode":"KC","playerName":"A.Bailey","statId":82,"yards":0}]}},"2466":{"sp":0,"qtr":4,"down":1,"time":"13:04","yrdln":"KC 24","ydstogo":10,"ydsnet":58,"posteam":"SD","desc":"(13:04) R.Mathews left tackle to KC 22 for 2 yards (T.Hali, R.Pitoitua).","note":null,"players":{"00-0024235":[{"sequence":2,"clubcode":"KC","playerName":"T.Hali","statId":80,"yards":0}],"00-0027864":[{"sequence":1,"clubcode":"SD","playerName":"R.Mathews","statId":10,"yards":2}],"00-0026016":[{"sequence":3,"clubcode":"KC","playerName":"R.Pitoitua","statId":82,"yards":0}]}},"2487":{"sp":0,"qtr":4,"down":0,"time":"12:20","yrdln":"","ydstogo":0,"ydsnet":58,"posteam":"","desc":"Timeout #1 by SD at 12:20.","note":"TIMEOUT","players":{"0":[{"sequence":1,"clubcode":"SD","playerName":"","statId":68,"yards":0}]}},"2504":{"sp":0,"qtr":4,"down":2,"time":"12:20","yrdln":"KC 22","ydstogo":8,"ydsnet":67,"posteam":"SD","desc":"(12:20) R.Brown left guard to KC 13 for 9 yards (E.Berry).","note":null,"players":{"00-0023437":[{"sequence":2,"clubcode":"SD","playerName":"R.Brown","statId":10,"yards":9}],"0":[{"sequence":1,"clubcode":"SD","playerName":"","statId":3,"yards":0}],"00-0027858":[{"sequence":3,"clubcode":"KC","playerName":"E.Berry","statId":79,"yards":0}]}},"2525":{"sp":1,"qtr":4,"down":1,"time":"11:37","yrdln":"KC 13","ydstogo":10,"ydsnet":80,"posteam":"SD","desc":"(11:37) (Shotgun) P.Rivers pass short left to M.Floyd for 13 yards, TOUCHDOWN.","note":"TD","players":{"00-0022942":[{"sequence":2,"clubcode":"SD","playerName":"P.Rivers","statId":16,"yards":13},{"sequence":3,"clubcode":"SD","playerName":"P.Rivers","statId":111,"yards":13}],"00-0022414":[{"sequence":4,"clubcode":"SD","playerName":"M.Floyd","statId":22,"yards":13},{"sequence":5,"clubcode":"SD","playerName":"M.Floyd","statId":115,"yards":0},{"sequence":6,"clubcode":"SD","playerName":"M.Floyd","statId":113,"yards":0}],"0":[{"sequence":1,"clubcode":"SD","playerName":"","statId":4,"yards":0}]}},"2545":{"sp":1,"qtr":4,"down":0,"time":"11:33","yrdln":"KC 2","ydstogo":0,"ydsnet":80,"posteam":"SD","desc":"N.Novak extra point is GOOD, Center-M.Windt, Holder-M.Scifres.","note":"XP","players":{"00-0023096":[{"sequence":1,"clubcode":"SD","playerName":"N.Novak","statId":72,"yards":0}]}}},"fds":5,"result":"Touchdown","penyds":0,"ydsgained":80,"numplays":12,"postime":"4:20","start":{"qtr":3,"time":"00:53","yrdln":"SD 20","team":"SD"},"end":{"qtr":3,"time":"11:33","yrdln":"KC 13","team":"SD"}},"12":{"posteam":"KC","qtr":4,"redzone":true,"plays":{"2561":{"sp":0,"qtr":4,"down":0,"time":"11:33","yrdln":"SD 35","ydstogo":0,"ydsnet":0,"posteam":"SD","desc":"N.Novak kicks 70 yards from SD 35 to KC -5. S.Draughn to KC 16 for 21 yards (D.Stuckey, A.Gachkar). PENALTY on KC-D.Stephenson, Face Mask (15 Yards), 8 yards, enforced at KC 16.","note":"KICKOFF","players":{"00-0027710":[{"sequence":4,"clubcode":"SD","playerName":"D.Stuckey","statId":80,"yards":0}],"00-0028202":[{"sequence":2,"clubcode":"KC","playerName":"S.Draughn","statId":45,"yards":21}],"00-0023096":[{"sequence":1,"clubcode":"SD","playerName":"N.Novak","statId":43,"yards":70},{"sequence":3,"clubcode":"SD","playerName":"N.Novak","statId":42,"yards":0}],"00-0029543":[{"sequence":6,"clubcode":"KC","playerName":"D.Stephenson","statId":93,"yards":8}],"00-0028172":[{"sequence":5,"clubcode":"SD","playerName":"A.Gachkar","statId":82,"yards":0}]}},"2594":{"sp":0,"qtr":4,"down":1,"time":"11:25","yrdln":"KC 8","ydstogo":10,"ydsnet":-4,"posteam":"KC","desc":"(11:25) PENALTY on KC-E.Winston, False Start, 4 yards, enforced at KC 8 - No Play.","note":"PENALTY","players":{"00-0024281":[{"sequence":1,"clubcode":"KC","playerName":"E.Winston","statId":93,"yards":4}]}},"2617":{"sp":0,"qtr":4,"down":1,"time":"11:25","yrdln":"KC 4","ydstogo":14,"ydsnet":-3,"posteam":"KC","desc":"(11:25) J.Charles left end to KC 5 for 1 yard (D.Butler).","note":null,"players":{"00-0026213":[{"sequence":1,"clubcode":"KC","playerName":"J.Charles","statId":10,"yards":1}],"00-0027682":[{"sequence":2,"clubcode":"SD","playerName":"D.Butler","statId":79,"yards":0}]}},"2649":{"sp":1,"qtr":4,"down":2,"time":"10:46","yrdln":"KC 5","ydstogo":13,"ydsnet":-8,"posteam":"KC","desc":"(10:46) M.Cassel sacked at KC 0 for -5 yards (J.Johnson). FUMBLES (J.Johnson), RECOVERED by SD-S.Phillips at KC 0. TOUCHDOWN.","note":"TD","players":{"00-0022139":[{"sequence":2,"clubcode":"SD","playerName":"J.Johnson","statId":83,"yards":-5},{"sequence":3,"clubcode":"SD","playerName":"J.Johnson","statId":79,"yards":0},{"sequence":6,"clubcode":"SD","playerName":"J.Johnson","statId":91,"yards":0}],"00-0023662":[{"sequence":1,"clubcode":"KC","playerName":"M.Cassel","statId":20,"yards":-5},{"sequence":4,"clubcode":"KC","playerName":"M.Cassel","statId":52,"yards":0},{"sequence":5,"clubcode":"KC","playerName":"M.Cassel","statId":106,"yards":0}],"00-0022723":[{"sequence":7,"clubcode":"SD","playerName":"S.Phillips","statId":60,"yards":0}]}}},"fds":0,"result":"Fumble","penyds":-4,"ydsgained":-4,"numplays":4,"postime":"0:54","start":{"qtr":4,"time":"11:33","yrdln":"KC 8","team":"KC"},"end":{"qtr":4,"time":"10:39","yrdln":"KC 5","team":"KC"}},"13":{"posteam":"KC","qtr":4,"redzone":true,"plays":{"2691":{"sp":0,"qtr":4,"down":0,"time":"10:39","yrdln":"SD 35","ydstogo":0,"ydsnet":0,"posteam":"SD","desc":"N.Novak kicks 69 yards from SD 35 to KC -4. S.Draughn, Touchback.","note":"KICKOFF","players":{"00-0023096":[{"sequence":1,"clubcode":"SD","playerName":"N.Novak","statId":44,"yards":65}],"0":[{"sequence":2,"clubcode":"KC","playerName":"","statId":51,"yards":0}]}},"2714":{"sp":0,"qtr":4,"down":1,"time":"10:39","yrdln":"KC 20","ydstogo":10,"ydsnet":22,"posteam":"KC","desc":"(10:39) (Shotgun) M.Cassel pass short left to J.Charles ran ob at KC 42 for 22 yards (E.Weddle). KC-B.Albert was injured during the play.","note":null,"players":{"00-0023662":[{"sequence":2,"clubcode":"KC","playerName":"M.Cassel","statId":15,"yards":22},{"sequence":3,"clubcode":"KC","playerName":"M.Cassel","statId":111,"yards":-4}],"00-0026213":[{"sequence":4,"clubcode":"KC","playerName":"J.Charles","statId":21,"yards":22},{"sequence":5,"clubcode":"KC","playerName":"J.Charles","statId":115,"yards":0},{"sequence":6,"clubcode":"KC","playerName":"J.Charles","statId":113,"yards":26}],"00-0025424":[{"sequence":7,"clubcode":"SD","playerName":"E.Weddle","statId":79,"yards":0}],"0":[{"sequence":1,"clubcode":"KC","playerName":"","statId":4,"yards":0}]}},"2741":{"sp":0,"qtr":4,"down":1,"time":"10:14","yrdln":"KC 42","ydstogo":10,"ydsnet":27,"posteam":"KC","desc":"(10:14) (Shotgun) M.Cassel pass short right to D.Bowe to KC 47 for 5 yards (Q.Jammer).","note":null,"players":{"00-0023662":[{"sequence":1,"clubcode":"KC","playerName":"M.Cassel","statId":15,"yards":5},{"sequence":2,"clubcode":"KC","playerName":"M.Cassel","statId":111,"yards":0}],"00-0025410":[{"sequence":3,"clubcode":"KC","playerName":"D.Bowe","statId":21,"yards":5},{"sequence":4,"clubcode":"KC","playerName":"D.Bowe","statId":115,"yards":0},{"sequence":5,"clubcode":"KC","playerName":"D.Bowe","statId":113,"yards":5}],"00-0021381":[{"sequence":6,"clubcode":"SD","playerName":"Q.Jammer","statId":79,"yards":0}]}},"2765":{"sp":0,"qtr":4,"down":2,"time":"09:43","yrdln":"KC 47","ydstogo":5,"ydsnet":32,"posteam":"KC","desc":"(9:43) (Shotgun) M.Cassel pass incomplete deep right to D.McCluster (C.Lynch).","note":null,"players":{"00-0023662":[{"sequence":1,"clubcode":"KC","playerName":"M.Cassel","statId":14,"yards":0},{"sequence":4,"clubcode":"KC","playerName":"M.Cassel","statId":112,"yards":28}],"00-0026317":[{"sequence":3,"clubcode":"SD","playerName":"C.Lynch","statId":85,"yards":0}],"00-0027651":[{"sequence":2,"clubcode":"KC","playerName":"D.McCluster","statId":115,"yards":0}]}},"2787":{"sp":0,"qtr":4,"down":3,"time":"09:37","yrdln":"KC 47","ydstogo":5,"ydsnet":32,"posteam":"KC","desc":"(9:37) (Shotgun) M.Cassel pass short left to D.McCluster pushed ob at SD 48 for 5 yards (M.Gilchrist).","note":null,"players":{"00-0023662":[{"sequence":3,"clubcode":"KC","playerName":"M.Cassel","statId":15,"yards":5},{"sequence":4,"clubcode":"KC","playerName":"M.Cassel","statId":111,"yards":3}],"00-0027651":[{"sequence":5,"clubcode":"KC","playerName":"D.McCluster","statId":21,"yards":5},{"sequence":6,"clubcode":"KC","playerName":"D.McCluster","statId":115,"yards":0},{"sequence":7,"clubcode":"KC","playerName":"D.McCluster","statId":113,"yards":2}],"00-0027988":[{"sequence":8,"clubcode":"SD","playerName":"M.Gilchrist","statId":79,"yards":0}],"0":[{"sequence":1,"clubcode":"KC","playerName":"","statId":4,"yards":0},{"sequence":2,"clubcode":"KC","playerName":"","statId":6,"yards":0}]}},"2811":{"sp":0,"qtr":4,"down":1,"time":"09:14","yrdln":"SD 48","ydstogo":10,"ydsnet":34,"posteam":"KC","desc":"(9:14) (Shotgun) M.Cassel pass short right to J.Charles to SD 46 for 2 yards (D.Butler, C.Lynch). KC-J.Charles was injured during the play.","note":null,"players":{"00-0023662":[{"sequence":1,"clubcode":"KC","playerName":"M.Cassel","statId":15,"yards":2},{"sequence":2,"clubcode":"KC","playerName":"M.Cassel","statId":111,"yards":0}],"00-0026317":[{"sequence":7,"clubcode":"SD","playerName":"C.Lynch","statId":82,"yards":0}],"00-0026213":[{"sequence":3,"clubcode":"KC","playerName":"J.Charles","statId":21,"yards":2},{"sequence":4,"clubcode":"KC","playerName":"J.Charles","statId":115,"yards":0},{"sequence":5,"clubcode":"KC","playerName":"J.Charles","statId":113,"yards":2}],"00-0027682":[{"sequence":6,"clubcode":"SD","playerName":"D.Butler","statId":80,"yards":0}]}},"2850":{"sp":1,"qtr":4,"down":2,"time":"08:46","yrdln":"SD 46","ydstogo":8,"ydsnet":34,"posteam":"KC","desc":"(8:46) (Shotgun) M.Cassel pass short right intended for D.McCluster INTERCEPTED by D.Williams at SD 41. D.Williams for 59 yards, TOUCHDOWN.","note":"TD","players":{"00-0023662":[{"sequence":1,"clubcode":"KC","playerName":"M.Cassel","statId":19,"yards":0},{"sequence":3,"clubcode":"KC","playerName":"M.Cassel","statId":112,"yards":5}],"00-0027651":[{"sequence":2,"clubcode":"KC","playerName":"D.McCluster","statId":115,"yards":0}],"00-0022707":[{"sequence":4,"clubcode":"SD","playerName":"D.Williams","statId":26,"yards":59},{"sequence":5,"clubcode":"SD","playerName":"D.Williams","statId":85,"yards":0}]}}},"fds":2,"result":"Interception","penyds":0,"ydsgained":34,"numplays":7,"postime":"2:06","start":{"qtr":4,"time":"10:39","yrdln":"KC 20","team":"KC"},"end":{"qtr":4,"time":"08:33","yrdln":"SD 46","team":"KC"}},"14":{"posteam":"KC","qtr":4,"redzone":true,"plays":{"2889":{"sp":0,"qtr":4,"down":0,"time":"08:33","yrdln":"SD 35","ydstogo":0,"ydsnet":0,"posteam":"SD","desc":"N.Novak kicks 74 yards from SD 35 to KC -9. S.Draughn, Touchback.","note":"KICKOFF","players":{"00-0023096":[{"sequence":1,"clubcode":"SD","playerName":"N.Novak","statId":44,"yards":65}],"0":[{"sequence":2,"clubcode":"KC","playerName":"","statId":51,"yards":0}]}},"2907":{"sp":0,"qtr":4,"down":1,"time":"08:33","yrdln":"KC 20","ydstogo":10,"ydsnet":2,"posteam":"KC","desc":"(8:33) (Shotgun) P.Hillis up the middle to KC 22 for 2 yards (A.Barnes, A.Garay).","note":null,"players":{"00-0026367":[{"sequence":1,"clubcode":"KC","playerName":"P.Hillis","statId":10,"yards":2}],"00-0022169":[{"sequence":3,"clubcode":"SD","playerName":"A.Garay","statId":82,"yards":0}],"00-0025521":[{"sequence":2,"clubcode":"SD","playerName":"A.Barnes","statId":80,"yards":0}]}},"2928":{"sp":0,"qtr":4,"down":2,"time":"08:05","yrdln":"KC 22","ydstogo":8,"ydsnet":12,"posteam":"KC","desc":"(8:05) (Shotgun) M.Cassel pass short left to S.Breaston to KC 32 for 10 yards (M.Gilchrist).","note":null,"players":{"00-0023662":[{"sequence":2,"clubcode":"KC","playerName":"M.Cassel","statId":15,"yards":10},{"sequence":3,"clubcode":"KC","playerName":"M.Cassel","statId":111,"yards":7}],"00-0025529":[{"sequence":4,"clubcode":"KC","playerName":"S.Breaston","statId":21,"yards":10},{"sequence":5,"clubcode":"KC","playerName":"S.Breaston","statId":115,"yards":0},{"sequence":6,"clubcode":"KC","playerName":"S.Breaston","statId":113,"yards":3}],"00-0027988":[{"sequence":7,"clubcode":"SD","playerName":"M.Gilchrist","statId":79,"yards":0}],"0":[{"sequence":1,"clubcode":"KC","playerName":"","statId":4,"yards":0}]}},"2952":{"sp":0,"qtr":4,"down":1,"time":"07:39","yrdln":"KC 32","ydstogo":10,"ydsnet":12,"posteam":"KC","desc":"(7:39) (Shotgun) M.Cassel pass incomplete deep left.","note":null,"players":{"00-0023662":[{"sequence":1,"clubcode":"KC","playerName":"M.Cassel","statId":14,"yards":0},{"sequence":2,"clubcode":"KC","playerName":"M.Cassel","statId":112,"yards":18}]}},"2974":{"sp":0,"qtr":4,"down":2,"time":"07:32","yrdln":"KC 32","ydstogo":10,"ydsnet":27,"posteam":"KC","desc":"(7:32) (Shotgun) M.Cassel pass incomplete short right to D.Bowe. PENALTY on SD-Q.Jammer, Defensive Pass Interference, 15 yards, enforced at KC 32 - No Play.","note":"PENALTY","players":{"0":[{"sequence":1,"clubcode":"KC","playerName":"","statId":5,"yards":0}],"00-0021381":[{"sequence":2,"clubcode":"SD","playerName":"Q.Jammer","statId":93,"yards":15}]}},"3016":{"sp":0,"qtr":4,"down":0,"time":"07:25","yrdln":"","ydstogo":0,"ydsnet":27,"posteam":"","desc":"Timeout #1 by KC at 07:25.","note":"TIMEOUT","players":{"0":[{"sequence":1,"clubcode":"KC","playerName":"","statId":68,"yards":0}]}},"3033":{"sp":0,"qtr":4,"down":1,"time":"07:25","yrdln":"KC 47","ydstogo":10,"ydsnet":28,"posteam":"KC","desc":"(7:25) (Shotgun) M.Cassel pass short right to S.Draughn to KC 48 for 1 yard (Q.Jammer).","note":null,"players":{"00-0028202":[{"sequence":3,"clubcode":"KC","playerName":"S.Draughn","statId":21,"yards":1},{"sequence":4,"clubcode":"KC","playerName":"S.Draughn","statId":115,"yards":0},{"sequence":5,"clubcode":"KC","playerName":"S.Draughn","statId":113,"yards":5}],"00-0023662":[{"sequence":1,"clubcode":"KC","playerName":"M.Cassel","statId":15,"yards":1},{"sequence":2,"clubcode":"KC","playerName":"M.Cassel","statId":111,"yards":-4}],"00-0021381":[{"sequence":6,"clubcode":"SD","playerName":"Q.Jammer","statId":79,"yards":0}]}},"3057":{"sp":0,"qtr":4,"down":2,"time":"06:53","yrdln":"KC 48","ydstogo":9,"ydsnet":35,"posteam":"KC","desc":"(6:53) (Shotgun) M.Cassel pass short left to P.Hillis to SD 45 for 7 yards (M.Gilchrist).","note":null,"players":{"00-0026367":[{"sequence":3,"clubcode":"KC","playerName":"P.Hillis","statId":21,"yards":7},{"sequence":4,"clubcode":"KC","playerName":"P.Hillis","statId":115,"yards":0},{"sequence":5,"clubcode":"KC","playerName":"P.Hillis","statId":113,"yards":5}],"00-0023662":[{"sequence":1,"clubcode":"KC","playerName":"M.Cassel","statId":15,"yards":7},{"sequence":2,"clubcode":"KC","playerName":"M.Cassel","statId":111,"yards":2}],"00-0027988":[{"sequence":6,"clubcode":"SD","playerName":"M.Gilchrist","statId":79,"yards":0}]}},"3081":{"sp":0,"qtr":4,"down":3,"time":"06:19","yrdln":"SD 45","ydstogo":2,"ydsnet":42,"posteam":"KC","desc":"(6:19) (Shotgun) M.Cassel pass short left to S.Breaston to SD 38 for 7 yards (A.Cason).","note":null,"players":{"00-0023662":[{"sequence":3,"clubcode":"KC","playerName":"M.Cassel","statId":15,"yards":7},{"sequence":4,"clubcode":"KC","playerName":"M.Cassel","statId":111,"yards":7}],"00-0026167":[{"sequence":8,"clubcode":"SD","playerName":"A.Cason","statId":79,"yards":0}],"00-0025529":[{"sequence":5,"clubcode":"KC","playerName":"S.Breaston","statId":21,"yards":7},{"sequence":6,"clubcode":"KC","playerName":"S.Breaston","statId":115,"yards":0},{"sequence":7,"clubcode":"KC","playerName":"S.Breaston","statId":113,"yards":0}],"0":[{"sequence":1,"clubcode":"KC","playerName":"","statId":4,"yards":0},{"sequence":2,"clubcode":"KC","playerName":"","statId":6,"yards":0}]}},"3105":{"sp":0,"qtr":4,"down":1,"time":"05:50","yrdln":"SD 38","ydstogo":10,"ydsnet":47,"posteam":"KC","desc":"(5:50) (Shotgun) M.Cassel scrambles up the middle to SD 33 for 5 yards (M.Gilchrist).","note":null,"players":{"00-0023662":[{"sequence":1,"clubcode":"KC","playerName":"M.Cassel","statId":10,"yards":5}],"00-0027988":[{"sequence":2,"clubcode":"SD","playerName":"M.Gilchrist","statId":79,"yards":0}]}},"3126":{"sp":0,"qtr":4,"down":2,"time":"05:11","yrdln":"SD 33","ydstogo":5,"ydsnet":74,"posteam":"KC","desc":"(5:11) (Shotgun) M.Cassel scrambles up the middle to SD 26 for 7 yards (D.Butler).","note":null,"players":{"00-0023662":[{"sequence":2,"clubcode":"KC","playerName":"M.Cassel","statId":10,"yards":7}],"0":[{"sequence":1,"clubcode":"KC","playerName":"","statId":3,"yards":0}],"00-0027682":[{"sequence":3,"clubcode":"SD","playerName":"D.Butler","statId":79,"yards":0}]}},"3147":{"sp":0,"qtr":4,"down":1,"time":"04:36","yrdln":"SD 26","ydstogo":10,"ydsnet":74,"posteam":"KC","desc":"(4:36) (Shotgun) M.Cassel pass deep left to S.Draughn ran ob at SD 6 for 20 yards (D.Williams).","note":null,"players":{"00-0028202":[{"sequence":4,"clubcode":"KC","playerName":"S.Draughn","statId":21,"yards":20},{"sequence":5,"clubcode":"KC","playerName":"S.Draughn","statId":115,"yards":0},{"sequence":6,"clubcode":"KC","playerName":"S.Draughn","statId":113,"yards":4}],"00-0023662":[{"sequence":2,"clubcode":"KC","playerName":"M.Cassel","statId":15,"yards":20},{"sequence":3,"clubcode":"KC","playerName":"M.Cassel","statId":111,"yards":16}],"00-0022707":[{"sequence":7,"clubcode":"SD","playerName":"D.Williams","statId":79,"yards":0}],"0":[{"sequence":1,"clubcode":"KC","playerName":"","statId":4,"yards":0}]}},"3171":{"sp":1,"qtr":4,"down":1,"time":"04:30","yrdln":"SD 6","ydstogo":6,"ydsnet":80,"posteam":"KC","desc":"(4:30) (Shotgun) S.Draughn up the middle for 6 yards, TOUCHDOWN.","note":"TD","players":{"00-0028202":[{"sequence":2,"clubcode":"KC","playerName":"S.Draughn","statId":11,"yards":6}],"0":[{"sequence":1,"clubcode":"KC","playerName":"","statId":3,"yards":0}]}},"3189":{"sp":1,"qtr":4,"down":0,"time":"04:26","yrdln":"SD 2","ydstogo":0,"ydsnet":80,"posteam":"KC","desc":"R.Succop extra point is GOOD, Center-T.Gafford, Holder-D.Colquitt.","note":"XP","players":{"00-0026968":[{"sequence":1,"clubcode":"KC","playerName":"R.Succop","statId":72,"yards":0}]}}},"fds":6,"result":"Touchdown","penyds":15,"ydsgained":65,"numplays":14,"postime":"4:07","start":{"qtr":4,"time":"08:33","yrdln":"KC 20","team":"KC"},"end":{"qtr":4,"time":"04:26","yrdln":"SD 6","team":"KC"}},"15":{"posteam":"SD","qtr":4,"redzone":true,"plays":{"3205":{"sp":0,"qtr":4,"down":0,"time":"04:26","yrdln":"KC 35","ydstogo":0,"ydsnet":-2,"posteam":"KC","desc":"R.Succop kicks onside 5 yards from KC 35 to KC 40. C.Lynch (didn't try to advance) to KC 40 for no gain (A.Studebaker).","note":"KICKOFF","players":{"00-0026343":[{"sequence":2,"clubcode":"KC","playerName":"A.Studebaker","statId":79,"yards":0}],"00-0026968":[{"sequence":1,"clubcode":"KC","playerName":"R.Succop","statId":41,"yards":5}]}},"3234":{"sp":0,"qtr":4,"down":1,"time":"04:25","yrdln":"KC 40","ydstogo":10,"ydsnet":-5,"posteam":"SD","desc":"(4:25) PENALTY on SD-M.Harris, False Start, 5 yards, enforced at KC 40 - No Play.","note":"PENALTY","players":{"00-0029457":[{"sequence":1,"clubcode":"SD","playerName":"M.Harris","statId":93,"yards":5}]}},"3257":{"sp":0,"qtr":4,"down":1,"time":"04:25","yrdln":"KC 45","ydstogo":15,"ydsnet":-2,"posteam":"SD","desc":"(4:25) J.Battle right end to KC 42 for 3 yards (J.Houston).","note":null,"players":{"00-0025701":[{"sequence":1,"clubcode":"SD","playerName":"J.Battle","statId":10,"yards":3}],"00-0028008":[{"sequence":2,"clubcode":"KC","playerName":"J.Houston","statId":79,"yards":0}]}},"3278":{"sp":0,"qtr":4,"down":2,"time":"03:41","yrdln":"KC 42","ydstogo":12,"ydsnet":1,"posteam":"SD","desc":"(3:41) J.Battle up the middle to KC 39 for 3 yards (R.Pitoitua, T.Hali).","note":null,"players":{"00-0024235":[{"sequence":3,"clubcode":"KC","playerName":"T.Hali","statId":82,"yards":0}],"00-0026016":[{"sequence":2,"clubcode":"KC","playerName":"R.Pitoitua","statId":80,"yards":0}],"00-0025701":[{"sequence":1,"clubcode":"SD","playerName":"J.Battle","statId":10,"yards":3}]}},"3299":{"sp":0,"qtr":4,"down":3,"time":"02:54","yrdln":"KC 39","ydstogo":9,"ydsnet":-4,"posteam":"SD","desc":"(2:54) (Shotgun) PENALTY on SD-P.Rivers, Delay of Game, 5 yards, enforced at KC 39 - No Play.","note":"PENALTY","players":{"00-0022942":[{"sequence":1,"clubcode":"SD","playerName":"P.Rivers","statId":93,"yards":5}]}},"3322":{"sp":0,"qtr":4,"down":3,"time":"02:53","yrdln":"KC 44","ydstogo":14,"ydsnet":-2,"posteam":"SD","desc":"(2:53) (Shotgun) R.Brown up the middle to KC 42 for 2 yards (T.Jackson, J.Houston).","note":null,"players":{"00-0023437":[{"sequence":2,"clubcode":"SD","playerName":"R.Brown","statId":10,"yards":2}],"0":[{"sequence":1,"clubcode":"SD","playerName":"","statId":7,"yards":0}],"00-0026980":[{"sequence":3,"clubcode":"KC","playerName":"T.Jackson","statId":80,"yards":0}],"00-0028008":[{"sequence":4,"clubcode":"KC","playerName":"J.Houston","statId":82,"yards":0}]}},"3343":{"sp":0,"qtr":4,"down":4,"time":"02:53","yrdln":"KC 42","ydstogo":12,"ydsnet":-7,"posteam":"SD","desc":"(2:53) (Punt formation) PENALTY on SD, Delay of Game, 5 yards, enforced at KC 42 - No Play.","note":"PENALTY","players":{"0":[{"sequence":1,"clubcode":"SD","playerName":"","statId":93,"yards":5}]}},"3370":{"sp":0,"qtr":4,"down":4,"time":"02:06","yrdln":"KC 47","ydstogo":17,"ydsnet":-7,"posteam":"SD","desc":"(2:06) M.Scifres punts 29 yards to KC 18, Center-M.Windt. D.McCluster MUFFS catch, RECOVERED by SD-D.Stuckey at KC 16. D.Stuckey to KC 16 for no gain (D.McCluster). SD-A.Barnes was injured during the play.","note":"FUMBLE","players":{"00-0027710":[{"sequence":6,"clubcode":"SD","playerName":"D.Stuckey","statId":59,"yards":0}],"00-0027651":[{"sequence":2,"clubcode":"KC","playerName":"D.McCluster","statId":53,"yards":0},{"sequence":3,"clubcode":"KC","playerName":"D.McCluster","statId":106,"yards":0},{"sequence":4,"clubcode":"KC","playerName":"D.McCluster","statId":33,"yards":0},{"sequence":7,"clubcode":"KC","playerName":"D.McCluster","statId":79,"yards":0}],"00-0022017":[{"sequence":1,"clubcode":"SD","playerName":"M.Scifres","statId":29,"yards":31},{"sequence":5,"clubcode":"SD","playerName":"M.Scifres","statId":30,"yards":0}]}}},"fds":0,"result":"Punt","penyds":-15,"ydsgained":8,"numplays":8,"postime":"2:29","start":{"qtr":4,"time":"04:26","yrdln":"KC 40","team":"SD"},"end":{"qtr":4,"time":"01:57","yrdln":"KC 47","team":"SD"}},"16":{"posteam":"SD","qtr":4,"redzone":true,"plays":{"3403":{"sp":0,"qtr":4,"down":1,"time":"01:57","yrdln":"KC 16","ydstogo":10,"ydsnet":0,"posteam":"SD","desc":"(1:57) L.McClain up the middle to KC 16 for no gain (T.Hali).","note":null,"players":{"00-0024235":[{"sequence":2,"clubcode":"KC","playerName":"T.Hali","statId":79,"yards":0}],"00-0025524":[{"sequence":1,"clubcode":"SD","playerName":"L.McClain","statId":10,"yards":0}]}},"3424":{"sp":0,"qtr":4,"down":2,"time":"01:12","yrdln":"KC 16","ydstogo":10,"ydsnet":-1,"posteam":"SD","desc":"(1:12) P.Rivers kneels, dead ball declared at KC 17 for -1 yards.","note":null,"players":{"00-0022942":[{"sequence":1,"clubcode":"SD","playerName":"P.Rivers","statId":10,"yards":-1}]}},"3444":{"sp":0,"qtr":4,"down":3,"time":"00:30","yrdln":"KC 17","ydstogo":11,"ydsnet":-2,"posteam":"SD","desc":"(:30) P.Rivers kneels, dead ball declared at KC 18 for -1 yards.","note":null,"players":{"00-0022942":[{"sequence":2,"clubcode":"SD","playerName":"P.Rivers","statId":10,"yards":-1}],"0":[{"sequence":1,"clubcode":"SD","playerName":"","statId":7,"yards":0}]}},"3464":{"sp":0,"qtr":4,"down":0,"time":"00:00","yrdln":"","ydstogo":0,"ydsnet":-2,"posteam":"","desc":"END GAME","note":null,"players":{}}},"fds":0,"result":"End of Game","penyds":0,"ydsgained":-2,"numplays":4,"postime":"1:57","start":{"qtr":4,"time":"01:57","yrdln":"KC 16","team":"SD"},"end":{"qtr":4,"time":"00:00","yrdln":"","team":"SD"}},"crntdrv":16},"scrsummary":{"208":{"type":"TD","desc":"A.Gates 14 yd. pass from P.Rivers (N.Novak kick is good) Drive: 7 plays, 80 yards in 4:36","qtr":1,"team":"SD","players":{"P.Rivers":"00-0022942","A.Gates":"00-0021547","":"0","N.Novak":"00-0023096"}},"999":{"type":"FG","desc":"N.Novak 25 yd. Field Goal Drive: 12 plays, 71 yards in 8:08","qtr":2,"team":"SD","players":{"N.Novak":"00-0023096"}},"1293":{"type":"FG","desc":"R.Succop 49 yd. Field Goal Drive: 10 plays, 49 yards in 6:19","qtr":2,"team":"KC","players":{"R.Succop":"00-0026968"}},"2308":{"type":"FG","desc":"R.Succop 41 yd. Field Goal Drive: 10 plays, 70 yards in 6:16","qtr":3,"team":"KC","players":{"R.Succop":"00-0026968"}},"2525":{"type":"TD","desc":"M.Floyd 13 yd. pass from P.Rivers (N.Novak kick is good) Drive: 8 plays, 80 yards in 4:20","qtr":4,"team":"SD","players":{"":"0","P.Rivers":"00-0022942","M.Floyd":"00-0022414","N.Novak":"00-0023096"}},"2649":{"type":"TD","desc":"S.Phillips fumble recovery in end zone (N.Novak kick is good)","qtr":4,"team":"SD","players":{"M.Cassel":"00-0023662","J.Johnson":"00-0022139","S.Phillips":"00-0022723","N.Novak":"00-0023096"}},"2850":{"type":"TD","desc":"D.Williams 59 yd. interception return (N.Novak kick is good)","qtr":4,"team":"SD","players":{"M.Cassel":"00-0023662","D.McCluster":"00-0027651","D.Williams":"00-0022707","N.Novak":"00-0023096"}},"3171":{"type":"TD","desc":"S.Draughn 6 yd. run (R.Succop kick is good) Drive: 10 plays, 80 yards in 4:07","qtr":4,"team":"KC","players":{"":"0","S.Draughn":"00-0028202","R.Succop":"00-0026968"}}},"weather":null,"media":null,"yl":"","qtr":"Final","note":null,"down":0,"togo":0,"redzone":true,"clock":"00:30","posteam":"SD","stadium":null},"nextupdate":204}